Workbook

Sheet BConstraints Fig 2-1 & 2-2 
A1: Fig 2-1 | AS1: أكتوبر - ديسمبر 2021 | AU1: يناير – مارس 2022 | AW1: أبريل– يونيو 2022 | AZ1: يوليو - سبتمبر 2022 | BB1: أكتوبر - ديسمبر 2022 | BD1: يناير – مارس 2023 | BF1: أبريل– يونيو 2023 | BH1: يوليو - سبتمبر 2023 | BJ1: أكتوبر - ديسمبر 2023 | BK1: يناير – مارس 2024 | BM1: أبريل– يونيو 2024 | BO1: يوليو - سبتمبر 2024 | BQ1: أكتوبر - ديسمبر 2024 | BS1: يناير – مارس 2025 | BU1: أبريل– يونيو 2025 | BW1: يوليو - سبتمبر 2025
E2: Constraints | F2: نوع المعوقات وشدتها | G2: Jan-Mar 2017 | I2: Apr-Jun 2017 | K2: Jul-Sep 2017 | M2: Oct-Dec 2017 | O2: Jan-Mar 2018 | Q2: Apr-Jun 2018 | S2: Jul-Sep 2018 | U2: Oct-Dec 2018 | W2: Jan-Mar 2019 | Y2: Apr-Jun 2019 | AA2: Jul-Sep 2019 | AC2: Oct-Dec 2019 | AE2: Jan-Mar 2020 | AG2: Apr-Jun 2020 | AI2: Jul-Sep 2020 | AK2: Oct-Dec 2020 | AM2: Jan-Mar 2021 | AO2: Apr-Jun 2021 | AQ2: Jul-Sep 2021 | AS2: Oct-Dec 2021 | AU2: Jan-Mar 2022 | AW2: Apr-Jun 2022 | AZ2: Jul-Sep 2022 | BB2: Oct-Dec 2022 | BD2: Jan-Mar 2023 | BF2: Apr-Jun 2023 | BH2: Jul-Sep 2023 | BI2: Oct-Dec 2023 | BK2: Jan-Mar 2024 | BM2: Apr-Jun 2024 | BN2: Apr-Jun 2024 | BO2: Jul-Sep 2024 | BQ2: Oct-Dec 2024 | BS2: Jan-Mar 2025 | BU2: Apr-Jun 2025 | BV2: Apr-Jun 2024 | BW2: Jul-Sep 2025
E3: High costs of energy and water | F3: ارتفاع تكاليف الطاقة والمياه | AM3: 100 | AO3: 100 | AQ3: 100 | AS3: 100 | AU3: 100 | AW3: 100 | AZ3: 74.832962 | BB3: 91.831683 | BD3: 91 | BF3: 86.419753 | BH3: 87.692308 | BJ3: 84.761905 | BL3: _ | BN3: 92.894737 | BP3: 99 | BR3: 79.946524 | BT3: 96.793003 | BV3: 100 | BX3: 89.968652
E4: Export procedures | F4: المشكلات المرتبطة بإجراءات التصدير | AM4: 58.928571 | AO4: 75.387038 | AQ4: 72 | AS4: 89.908257 | AU4: 96.089526 | AW4: 74.914089 | AZ4: 62.583519 | BB4: 80.693069 | BD4: 81 | BF4: 76.54321 | BH4: 76.923077 | BJ4: 67.380952 | BL4: _ | BN4: 14.473684 | BP4: 15 | BR4: 16.042781 | BT4: 14.285714 | BV4: 19.55836 | BX4: 11.285266
E5: Increased government fees | F5: زيادة الرسوم المفروضة على الخدمات الحكومية | AM5: 80.555556 | AO5: 78.108108 | AQ5: 70 | AS5: 58.490315 | AU5: 55.117052 | AW5: 53.930126 | AZ5: 59.910913 | BB5: 56.930693 | BD5: 65 | BF5: 50.123457 | BH5: 53.333333 | BJ5: 55.714286 | BL5: 62.464986 | BN5: 56.052632 | BP5: 61 | BR5: 64.705882 | BT5: 60.349854 | BV5: 64.353312 | BX5: 42.633229
E6: Government procedures | F6: إجراءات التعامل مع الجهات الحكومية | AM6: 40.909091 | AO6: 68.286635 | AQ6: 68 | AS6: 48.620074 | AU6: 42.059548 | AW6: 46.052692 | AZ6: 52.783964 | BB6: 60.643564 | BD6: 61 | BF6: 59.753086 | BH6: 71.025641 | BJ6: 60.47619 | BL6: 69.187675 | BN6: 63.421053 | BP6: 72 | BR6: 72.192513 | BT6: 57.142857 | BV6: 71.608833 | BX6: 49.216301
E7: Taxation system | F7: المنظومة الضريبية | AM7: 36.052632 | AO7: 71.19552 | AQ7: 66 | AS7: 48.25451 | AU7: 45.579175 | AW7: 41.003055 | AZ7: 45.879733 | BB7: 63.861386 | BD7: 67 | BF7: 68.641975 | BH7: 64.102564 | BJ7: 62.380952 | BL7: 71.428571 | BN7: 80.789474 | BP7: 68 | BR7: 60.962567 | BT7: 59.475219 | BV7: 61.829653 | BX7: 57.053292
E8: High inflation | F8: ارتفاع التضخم | AM8: 25.872093 | AO8: 40.150962 | AQ8: 55 | AS8: 58.370516 | AU8: 69.512641 | AW8: 88.065674 | AZ8: 100 | BB8: 100 | BD8: 100 | BF8: 100 | BH8: 99.230769 | BJ8: 100 | BL8: 88.235294 | BN8: 100 | BP8: 100 | BR8: 100 | BT8: 100 | BV8: 96.529968 | BX8: 100
E9: Difficulty in finding qualified labor | F9: صعوبة الحصول علي العمالة المؤهلة | AM9: 29.411765 | AO9: 48.034398 | AQ9: 42 | AS9: 24.492819 | AU9: 21.117764 | AW9: 20.539447 | AZ9: 20.935412 | BB9: 23.267327 | BD9: 25 | BF9: 32.098765 | BH9: 37.435897 | BJ9: 45.952381 | BL9: 38.095238 | BN9: 40.526316 | BP9: 42 | BR9: 33.957219 | BT9: 44.023324 | BV9: 45.425868 | BX9: 59.561129
E10: Customs | F10: المنظومة الجمركية | AM10: 25 | AO10: 45.441045 | AQ10: 39 | AS10: 72.652212 | AU10: 59 | AW10: 54.60882 | AZ10: 19.599109 | BB10: 35.148515 | BD10: 31 | BF10: 30.123457 | BH10: 30.25641 | BJ10: 22.142857 | BL10: 24.64986 | BN10: 28.157895 | BP10: 29 | BR10: 28.074866 | BT10: 27.696793 | BV10: 27.760252 | BX10: 26.332288
E11: Unstable economic policies | F11: تخبط السياسات الاقتصادية | AM11: 21.22093 | AO11: 16.971025 | AQ11: 35 | AS11: 27.326325 | AU11: 35.196274 | AW11: 38.175258 | AZ11: 38.084633 | BB11: 48.514851 | BD11: 51 | BF11: 45.185185 | BH11: 57.435897 | BJ11: 70.47619 | BL11: 73.669468 | BN11: 66.578947 | BP11: 54 | BR11: 50 | BT11: 37.026239 | BV11: 48.264984 | BX11: 33.22884
E12: Power outage | F12: إنقطاع الكهرباء | AM12: 20.294118 | AO12: 28.560993 | AQ12: 23 | AS12: 14.871469 | AU12: 11.273942 | AW12: 8.6853761 | AZ12: 8.6859688 | BB12: 24.009901 | BD12: 18 | BF12: 11.358025 | BH12: 17.692308 | BJ12: 15.714286 | BL12: _ | BN12: 66.315789 | BP12: 7 | BR12: 13.636364 | BT12: 7.2886297 | BV12: 11.987382 | BX12: 9.7178683
E13: Lack of information on domestic and foreign markets | F13: غياب المعلومات عن السوق المحلي والخارجي | AM13: 17.816092 | AO13: 31.458486 | AQ13: 19 | AS13: 10.60137 | AU13: 5.2794411 | AW13: 5.6555937 | AZ13: 4.2316258 | BB13: 22.277228 | BD13: 20 | BF13: 15.308642 | BH13: 17.179487 | BJ13: 14.285714 | BL13: _ | BN13: 43.684211 | BP13: 32 | BR13: 31.283422 | BT13: 18.075802 | BV13: 36.59306 | BX13: 23.197492
E14: Others | F14: أخرى | AM14: - | AO14: - | AQ14: 18 | AS14: 13.738374 | AU14: 8.4471058 | AW14: 5.6555937 | AZ14: 6.2360802 | BB14: 5.9405941 | BD14: 9 | BF14: 8.3950617 | BH14: 5.1282051 | BJ14: 14.285714 | BL14: 11.204482 | BN14: 17.894737 | BP14: 6 | BR14: 17.112299 | BT14: 16.326531 | BV14: 24.921136 | BX14: 13.793103
E15: Government contracts don't give priority to locally manufactured products | F15: عدم تفضيل المنتج المحلي في التعاقدات الحكومية | AM15: - | AO15: 15 | AQ15: 17 | AS15: 20.362872 | AU15: 10.554485 | AW15: 16.814609 | AZ15: 0 | BB15: 2.7227723 | BD15: 2 | BF15: 1.4814815 | BH15: 2.0512821 | BJ15: 5 | BL15: _ | BN15: 28.157895 | BP15: 16 | BR15: 13.101604 | BT15: 8.7463557 | BV15: 8.8328076 | BX15: 7.523511
E16: Unfair competition from the state | F16: المنافسة غير العادلة من الدولة | AM16: 58.333333 | AO16: 29.506571 | AQ16: 11 | AS16: 4.5380306 | AU16: 1.7895147 | AW16: 1.9122887 | AZ16: 0 | BB16: 1.7326733 | BD16: 1 | BF16: 0 | BH16: 0 | BJ16: 4.2857143 | BL16: _ | BN16: 38.421053 | BP16: 33 | BR16: 27.540107 | BT16: 22.44898 | BV16: 21.451104 | BX16: 10.344828
E17: Difficulty in obtaining funding | F17: صعوبة الحصول على التمويل | AM17: 8.7349398 | AO17: 11.802628 | AQ17: 10 | AS17: 9.0174337 | AU17: 4.4789603 | AW17: 4.0257316 | AZ17: 2.6726058 | BB17: 8.1683168 | BD17: 9 | BF17: 6.6666667 | BH17: 10 | BJ17: 15.47619 | BL17: 21.288515 | BN17: 24.473684 | BP17: 21 | BR17: 27.272727 | BT17: 25.655977 | BV17: 26.81388 | BX17: 25.07837
E18: Economic policy uncertainty | F18: عدم وضوح توجهات السياسة الاقتصادية في المستقبل | AM18: 5.7228916 | AO18: 9.1891892 | AQ18: 9 | AS18: 9.0174337 | AU18: 4 | AW18: 4.0257316 | AZ18: 1.7817372 | BB18: 7.4257426 | BD18: 8 | BF18: 6.4197531 | BH18: 8.2051282 | BJ18: 11.666667 | BL18: _ | BN18: 77.368421 | BP18: 79 | BR18: 66.042781 | BT18: 58.017493 | BV18: 70.977918 | BX18: 42.946708
E19: Exchange rate | F19: سعر الصرف | AM19: 12.804878 | AO19: 9.5203311 | AQ19: 5 | AS19: 0.91391117 | AU19: 56.369712 | AW19: 73.325825 | AZ19: 84.187082 | BB19: 89.851485 | BD19: 92 | BF19: 96.049383 | BH19: 100 | BJ19: 97.380952 | BL19: 100 | BN19: 68.421053 | BP19: 51 | BR19: 69.518717 | BT19: 45.772595 | BV19: 41.640379 | BX19: 33.855799
E20: Transportation and logistics | F20: النقل واللوجستيات | AM20: 3.9156627 | AO20: 4.5945946 | AQ20: 3 | AS20: 1.878632 | AU20: 7 | AW20: 4.0257316 | AZ20: 2.0044543 | BB20: 21.782178 | BD20: 25 | BF20: 22.469136 | BH20: 33.333333 | BJ20: 36.190476 | BL20: _ | BN20: 31.052632 | BP20: 30 | BR20: 25.13369 | BT20: 39.941691 | BV20: 40.378549 | BX20: 46.081505
A22: Fig 2-2 | G22: Jan-Mar 2017 | I22: Apr-Jun 2017 | K22: Jul-Sep 2017 | M22: Oct-Dec 2017 | O22: Jan-Mar 2018 | Q22: Apr-Jun 2018 | S22: Jul-Sep 2018 | U22: Oct-Dec 2018 | W22: Jan-Mar 2019 | Y22: Apr-Jun 2019 | AA22: Jul-Sep 2019 | AC22: Oct-Dec 2019 | AE22: Jan-Mar 2020 | AG22: Apr-Jun 2020 | AI22: Jul-Sep 2020 | AK22: Oct-Dec 2020 | AM22: Jan-Mar 2021 | AO22: Apr-Jun 2021 | AQ22: Jul-Sep 2021 | AS22: Oct-Dec 2021 | AU22: Jan-Mar 2022 | AW22: Apr-Jun 2022 | AY22: Jul-Sep 2022 | BA22: Oct-Dec 2022 | BC22: Jan-Mar 2023 | BE22: Apr-Jun 2023 | BG22: Jul-Sep 2023 | BI22: Oct-Dec 2023 | BK22: Jan-Mar 2024 | BM22: Apr-Jun 2024 | BO22: Jul-Sep 2024 | BQ22: Oct-Dec 2024 | BS22: Jan-Mar 2025 | BU22: Apr-Jun 2025 | BW22: Jul-Sep 2025
A23: الشركات الكبيرة | B23: الشركات الصغيرة والمتوسطة | C23: Large | D23: SMEs | E23: Constraints | F23: نوع المعوقات وشدتها | G23: الشركات الكبيرة | H23: الشركات الصغيرة والمتوسطة | I23: الشركات الكبيرة | J23: الشركات الصغيرة والمتوسطة | K23: الشركات الكبيرة | L23: الشركات الصغيرة والمتوسطة | M23: الشركات الكبيرة | N23: الشركات الصغيرة والمتوسطة | O23: الشركات الكبيرة | P23: الشركات الصغيرة والمتوسطة | Q23: الشركات الكبيرة | R23: الشركات الصغيرة والمتوسطة | S23: الشركات الكبيرة | T23: الشركات الصغيرة والمتوسطة | U23: الشركات الكبيرة | V23: الشركات الصغيرة والمتوسطة | W23: الشركات الكبيرة | X23: الشركات الصغيرة والمتوسطة | Y23: الشركات الكبيرة | Z23: الشركات الصغيرة والمتوسطة | AA23: الشركات الكبيرة | AB23: الشركات الصغيرة والمتوسطة | AC23: الشركات الكبيرة | AD23: الشركات الصغيرة والمتوسطة | AE23: الشركات الكبيرة | AF23: الشركات الصغيرة والمتوسطة | AG23: الشركات الكبيرة | AH23: الشركات الصغيرة والمتوسطة | AI23: الشركات الكبيرة | AJ23: الشركات الصغيرة والمتوسطة | AK23: الشركات الكبيرة | AL23: الشركات الصغيرة والمتوسطة | AM23: الشركات الكبيرة | AN23: الشركات الصغيرة والمتوسطة | AO23: الشركات الكبيرة | AP23: الشركات الصغيرة والمتوسطة | AQ23: الشركات الكبيرة | AR23: الشركات الصغيرة والمتوسطة | AS23: الشركات الكبيرة | AT23: الشركات الصغيرة والمتوسطة | AU23: الشركات الكبيرة | AV23: الشركات الصغيرة والمتوسطة | AW23: الشركات الكبيرة | AX23: الشركات الصغيرة والمتوسطة | AY23: الشركات الكبيرة | AZ23: الشركات الصغيرة والمتوسطة | BA23: الشركات الكبيرة | BB23: الشركات الصغيرة والمتوسطة | BC23: الشركات الكبيرة | BD23: الشركات الصغيرة والمتوسطة | BE23: الشركات الكبيرة | BF23: الشركات الصغيرة والمتوسطة | BG23: الشركات الكبيرة | BH23: الشركات الصغيرة والمتوسطة | BI23: الشركات الكبيرة | BJ23: الشركات الصغيرة والمتوسطة | BK23: الشركات الكبيرة | BL23: الشركات الصغيرة والمتوسطة | BM23: الشركات الكبيرة | BN23: الشركات الصغيرة والمتوسطة | BO23: الشركات الكبيرة | BP23: الشركات الصغيرة والمتوسطة | BQ23: الشركات الكبيرة | BR23: الشركات الصغيرة والمتوسطة | BS23: الشركات الكبيرة | BT23: الشركات الصغيرة والمتوسطة | BU23: الشركات الكبيرة | BV23: الشركات الصغيرة والمتوسطة | BW23: الشركات الكبيرة | BX23: الشركات الصغيرة والمتوسطة
E24: High costs of energy and water | F24: ارتفاع تكاليف الطاقة والمياه | AO24: 100 | AP24: 76.109937 | AQ24: 98 | AR24: 73 | AS24: 100 | AT24: 100 | AU24: 99.275 | AV24: 100 | AW24: 90.461717 | AX24: 100 | AY24: 81.707317 | AZ24: 73.297003 | BA24: 88.75 | BB24: 92.592593 | BC24: 96 | BD24: 90 | BE24: 89.041096 | BF24: 85.843373 | BG24: 98.684211 | BH24: 83.17757 | BI24: 85.526316 | BJ24: 84.104046 | BK24: 100 | BL24: 75.838926 | BM24: 80 | BN24: 95.555556 | BO24: 94 | BP24: 100 | BQ24: 68.656716 | BR24: 82.410423 | BS24: 71.875 | BT24: 100 | BU24: 95 | BV24: 100 | BW24: 96.666667 | BX24: 88.416988
E25: Export procedures | F25: المشكلات المرتبطة بإجراءات التصدير | AO25: 71.157495 | AP25: 69.93007 | AQ25: 58 | AR25: 63 | AS25: 91.525424 | AT25: 89.552239 | AU25: 100 | AV25: 94.776119 | AW25: 60.307811 | AX25: 77.056277 | AY25: 59.756098 | AZ25: 63.215259 | BA25: 82.5 | BB25: 80.246914 | BC25: 79 | BD25: 81 | BE25: 84.931507 | BF25: 74.698795 | BG25: 85.526316 | BH25: 73.208723 | BI25: 65.789474 | BJ25: 67.34104 | BK25: 76.666667 | BL25: 69.463087 | BM25: 24.615385 | BN25: 12.380952 | BO25: 28 | BP25: 13 | BQ25: 20.895522 | BR25: 14.983713 | BS25: 7.8125 | BT25: 15.384615 | BU25: 30 | BV25: 16.923077 | BW25: 16.666667 | BX25: 10.03861
E26: Increased government fees | F26: زيادة الرسوم المفروضة على الخدمات الحكومية | AO26: 56.451613 | AP26: 82.01581 | AQ26: 72 | AR26: 68 | AS26: 52.146508 | AT26: 59.917199 | AU26: 70.857438 | AV26: 51.601277 | AW26: 55.319149 | AX26: 51.987145 | AY26: 62.195122 | AZ26: 59.400545 | BA26: 43.75 | BB26: 60.185185 | BC26: 51 | BD26: 68 | BE26: 53.424658 | BF26: 49.39759 | BG26: 44.736842 | BH26: 54.205607 | BI26: 46.052632 | BJ26: 57.514451 | BK26: 55 | BL26: 63.758389 | BM26: 41.538462 | BN26: 59.047619 | BO26: 58 | BP26: 61 | BQ26: 58.208955 | BR26: 66.123779 | BS26: 37.5 | BT26: 63.986014 | BU26: 45 | BV26: 68.076923 | BW26: 40 | BX26: 43.243243
E27: Government procedures | F27: إجراءات التعامل مع الجهات الحكومية | AO27: 59.139785 | AP27: 100 | AQ27: 100 | AR27: 100 | AS27: 53.130405 | AT27: 47.574705 | AU27: 54.593573 | AV27: 39.266311 | AW27: 51.06383 | AX27: 43.524121 | AY27: 52.439024 | AZ27: 52.861035 | BA27: 55 | BB27: 62.037037 | BC27: 56 | BD27: 62 | BE27: 60.273973 | BF27: 59.638554 | BG27: 61.842105 | BH27: 71.65109 | BI27: 51.315789 | BJ27: 62.138728 | BK27: 73.333333 | BL27: 68.120805 | BM27: 47.692308 | BN27: 66.666667 | BO27: 64 | BP27: 73 | BQ27: 77.61194 | BR27: 71.009772 | BS27: 32.8125 | BT27: 61.188811 | BU27: 75 | BV27: 70 | BW27: 38.333333 | BX27: 51.737452
E28: Taxation system | F28: المنظومة الضريبية | AO28: 48.387097 | AP28: 75.268817 | AQ28: 72 | AR28: 64 | AS28: 42.307544 | AT28: 49.594385 | AU28: 35.258349 | AV28: 46.872873 | AW28: 46.808511 | AX28: 38.446307 | AY28: 29.268293 | AZ28: 49.591281 | BA28: 50 | BB28: 67.283951 | BC28: 42 | BD28: 73 | BE28: 53.424658 | BF28: 71.987952 | BG28: 50 | BH28: 66.043614 | BI28: 47.368421 | BJ28: 65.317919 | BK28: 60 | BL28: 73.489933 | BM28: 70.769231 | BN28: 82.857143 | BO28: 64 | BP28: 69 | BQ28: 49.253731 | BR28: 63.517915 | BS28: 45.3125 | BT28: 61.188811 | BU28: 50 | BV28: 63.846154 | BW28: 40 | BX28: 61.003861
E29: High inflation | F29: ارتفاع التضخم | AO29: 53.763441 | AP29: 48.875855 | AQ29: 44 | AR29: 42 | AS29: 65.921058 | AT29: 56.577776 | AU29: 87.57719 | AV29: 65.375323 | AW29: 100 | AX29: 82.69583 | AY29: 100 | AZ29: 100 | BA29: 100 | BB29: 100 | BC29: 100 | BD29: 100 | BE29: 100 | BF29: 100 | BG29: 100 | BH29: 96.884735 | BI29: 97.368421 | BJ29: 100 | BK29: 95 | BL29: 86.577181 | BM29: 100 | BN29: 100 | BO29: 100 | BP29: 99 | BQ29: 100 | BR29: 100 | BS29: 100 | BT29: 97.552448 | BU29: 100 | BV29: 94.615385 | BW29: 100 | BX29: 100
E30: Difficulty in finding qualified labor | F30: صعوبة الحصول علي العمالة المؤهلة | AO30: 42.694497 | AP30: 42.383292 | AQ30: 42 | AR30: 39 | AS30: 18.694031 | AT30: 25.807033 | AU30: 15.923125 | AV30: 21.791774 | AW30: 23.404255 | AX30: 19.263873 | AY30: 25.609756 | AZ30: 19.891008 | BA30: 12.5 | BB30: 25.925926 | BC30: 27 | BD30: 25 | BE30: 28.767123 | BF30: 32.831325 | BG30: 40.789474 | BH30: 35.825545 | BI30: 51.315789 | BJ30: 44.508671 | BK30: 58.333333 | BL30: 33.892617 | BM30: 35.384615 | BN30: 41.587302 | BO30: 50 | BP30: 41 | BQ30: 44.776119 | BR30: 31.596091 | BS30: 21.875 | BT30: 47.902098 | BU30: 33.333333 | BV30: 47.692308 | BW30: 55 | BX30: 61.003861
E31: Customs | F31: المنظومة الجمركية | AO31: 59.772296 | AP31: 17.106549 | AQ31: 33 | AR31: 31 | AS31: 63.057885 | AT31: 72.415522 | AU31: 40.853909 | AV31: 67 | AW31: 41.555851 | AX31: 58.418381 | AY31: 31.707317 | AZ31: 16.893733 | BA31: 47.5 | BB31: 32.098765 | BC31: 46 | BD31: 27 | BE31: 47.945205 | BF31: 26.204819 | BG31: 47.368421 | BH31: 25.545171 | BI31: 31.578947 | BJ31: 19.942197 | BK31: 40 | BL31: 21.47651 | BM31: 43.076923 | BN31: 25.079365 | BO31: 52 | BP31: 25 | BQ31: 50.746269 | BR31: 23.127036 | BS31: 28.125 | BT31: 26.923077 | BU31: 40 | BV31: 24.615385 | BW31: 31.666667 | BX31: 25.096525
E32: Unstable economic policies | F32: تخبط السياسات الاقتصادية | AO32: 16.129032 | AP32: 37.634409 | AQ32: 58 | AR32: 55 | AS32: 32.542373 | AT32: 26.255851 | AU32: 48.906742 | AV32: 32.276496 | AW32: 34.042553 | AX32: 37.962706 | AY32: 34.146341 | AZ32: 38.964578 | BA32: 47.5 | BB32: 48.765432 | BC32: 41 | BD32: 53 | BE32: 46.575342 | BF32: 44.879518 | BG32: 52.631579 | BH32: 57.320872 | BI32: 68.421053 | BJ32: 70.520231 | BK32: 81.666667 | BL32: 71.812081 | BM32: 69.230769 | BN32: 66.031746 | BO32: 56 | BP32: 53 | BQ32: 37.313433 | BR32: 52.76873 | BS32: 14.0625 | BT32: 41.258741 | BU32: 38.333333 | BV32: 50 | BW32: 35 | BX32: 32.818533
E33: Power outage | F33: إنقطاع الكهرباء | AO33: 37.634409 | AP33: - | AQ33: 14 | AR33: 15 | AS33: 9.8389638 | AT33: 16.034188 | AU33: 6.2155647 | AV33: 11.923801 | AW33: 9.5744681 | AX33: 8.2212229 | AY33: 1.2195122 | AZ33: 10.354223 | BA33: 18.75 | BB33: 25.308642 | BC33: 12 | BD33: 20 | BE33: 9.5890411 | BF33: 11.746988 | BG33: 15.789474 | BH33: 17.757009 | BI33: 10.526316 | BJ33: 16.763006 | BK33: 6.6666667 | BL33: 28.52349 | BM33: 46.153846 | BN33: 70.47619 | BO33: 3 | BP33: 8 | BQ33: 8.9552239 | BR33: 14.65798 | BS33: 6.25 | BT33: 7.3426573 | BU33: 15 | BV33: 11.153846 | BW33: 11.666667 | BX33: 9.2664093
E34: Lack of information on domestic and foreign markets | F34: غياب المعلومات عن السوق المحلي والخارجي | AO34: 26.88172 | AP34: 12.487512 | AQ34: 12 | AR34: 11 | AS34: 9.8389638 | AT34: 10.771631 | AU34: 13.648393 | AV34: 3.70049 | AW34: 10.638298 | AX34: 4.3524121 | AY34: 4.8780488 | AZ34: 4.0871935 | BA34: 15 | BB34: 24.074074 | BC34: 20 | BD34: 20 | BE34: 19.178082 | BF34: 14.457831 | BG34: 5.2631579 | BH34: 19.626168 | BI34: 6.5789474 | BJ34: 15.895954 | BK34: 13.333333 | BL34: 18.456376 | BM34: 40 | BN34: 44.444444 | BO34: 31 | BP34: 32 | BQ34: 31.343284 | BR34: 31.270358 | BS34: 9.375 | BT34: 19.58042 | BU34: 23.333333 | BV34: 39.230769 | BW34: 25 | BX34: 22.779923
E35: Others | F35: أخرى | AO35: - | AP35: 26.88172 | AQ35: 32 | AR35: 24 | AS35: 3.2808946 | AT35: 16.492377 | AU35: 4.5494644 | AV35: 9.0456422 | AW35: 12.765957 | AX35: 3.8688108 | AY35: 0 | AZ35: 7.6294278 | BA35: 5 | BB35: 6.1728395 | BC35: 0 | BD35: 12 | BE35: 4.109589 | BF35: 9.3373494 | BG35: 0 | BH35: 6.2305296 | BI35: 15.789474 | BJ35: 13.872832 | BK35: 8.3333333 | BL35: 11.744966 | BM35: 18.461538 | BN35: 17.777778 | BO35: 6 | BP35: 6 | BQ35: 17.910448 | BR35: 16.938111 | BS35: 12.5 | BT35: 16.783217 | BU35: 20 | BV35: 25.769231 | BW35: 6.6666667 | BX35: 15.444015
E36: Government contracts don't give priority to locally manufactured products | F36: عدم تفضيل المنتج المحلي في التعاقدات الحكومية | AO36: 17.281106 | AP36: 14.167651 | AQ36: 26 | AR36: 15 | AS36: 6.779661 | AT36: 23.137318 | AU36: 0 | AV36: 12.089552 | AW36: 10.055102 | AX36: 18.705009 | AY36: 0 | AZ36: 0 | BA36: 1.25 | BB36: 3.0864198 | BC36: 2 | BD36: 2 | BE36: 0 | BF36: 1.8072289 | BG36: 5.2631579 | BH36: 1.2461059 | BI36: 3.9473684 | BJ36: 5.2023121 | BK36: 15 | BL36: 9.7315436 | BM36: 23.076923 | BN36: 29.206349 | BO36: 14 | BP36: 16 | BQ36: 8.9552239 | BR36: 14.006515 | BS36: 3.125 | BT36: 9.7902098 | BU36: 10 | BV36: 8.4615385 | BW36: 3.3333333 | BX36: 8.4942085
E37: Unfair competition from the state | F37: المنافسة غير العادلة من الدولة | AO37: 43.010753 | AP37: 32.258065 | AQ37: 28 | AR37: 20 | AS37: 6.5084746 | AT37: 4.1230768 | AU37: 3.4120983 | AV37: 1.4692164 | AW37: 3.3244681 | AX37: 1.2974144 | AY37: 0 | AZ37: 0 | BA37: 0 | BB37: 2.1604938 | BC37: 2 | BD37: 1 | BE37: 0 | BF37: 0 | BG37: 0 | BH37: 0 | BI37: 3.9473684 | BJ37: 4.3352601 | BK37: 18.333333 | BL37: 7.0469799 | BM37: 27.692308 | BN37: 40.634921 | BO37: 36 | BP37: 32 | BQ37: 29.850746 | BR37: 27.035831 | BS37: 7.8125 | BT37: 25.174825 | BU37: 16.666667 | BV37: 22.307692 | BW37: 5 | BX37: 11.583012
E38: Difficulty in obtaining funding | F38: صعوبة الحصول على التمويل | AO38: 8.0645161 | AP38: 7.8201369 | AQ38: 4 | AR38: 5 | AS38: 1.6949153 | AT38: 11.042582 | AU38: 0 | AV38: 5 | AW38: 4.5230858 | AX38: 3.729433 | AY38: 0 | AZ38: 3.2697548 | BA38: 2.5 | BB38: 9.5679012 | BC38: 5 | BD38: 11 | BE38: 5.4794521 | BF38: 6.9277108 | BG38: 10.526316 | BH38: 9.6573209 | BI38: 21.052632 | BJ38: 14.16185 | BK38: 25 | BL38: 20.469799 | BM38: 29.230769 | BN38: 23.492063 | BO38: 19 | BP38: 22 | BQ38: 44.776119 | BR38: 23.452769 | BS38: 20.3125 | BT38: 26.223776 | BU38: 36.666667 | BV38: 24.230769 | BW38: 18.333333 | BX38: 26.640927
E39: Economic policy uncertainty | F39: عدم وضوح توجهات السياسة الاقتصادية في المستقبل | AO39: 8.5388994 | AP39: 19.061584 | AQ39: 4 | AR39: 7 | AS39: 3.3898305 | AT39: 10.562469 | AU39: 0 | AV39: 5 | AW39: 3.0153906 | AX39: 4.2622091 | AY39: 0 | AZ39: 2.1798365 | BA39: 2.5 | BB39: 8.6419753 | BC39: 4 | BD39: 8 | BE39: 5.4794521 | BF39: 6.626506 | BG39: 9.2105263 | BH39: 7.788162 | BI39: 9.2105263 | BJ39: 12.138728 | BK39: 30 | BL39: 18.456376 | BM39: 81.538462 | BN39: 76.507937 | BO39: 80 | BP39: 78 | BQ39: 59.701493 | BR39: 67.42671 | BS39: 43.75 | BT39: 59.79021 | BU39: 56.666667 | BV39: 73.461538 | BW39: 38.333333 | BX39: 44.015444
E40: Exchange rate | F40: سعر الصرف | AO40: 13.44086 | AP40: 26.973027 | AQ40: 12 | AR40: 9 | AS40: 1.9677928 | AT40: 4.4881797 | AU40: 0 | AV40: 1.850245 | AW40: 2.1276596 | AX40: 1.450804 | AY40: 2.4390244 | AZ40: 1.3623978 | BA40: 7.5 | BB40: 13.888889 | BC40: 10 | BD40: 13 | BE40: 12.328767 | BF40: 5.4216867 | BG40: 5.2631579 | BH40: 5.9190031 | BI40: 5.2631579 | BJ40: 4.0462428 | BK40: 0 | BL40: 8.0536913 | BM40: 84.615385 | BN40: 65.079365 | BO40: 56 | BP40: 49 | BQ40: 64.179104 | BR40: 70.684039 | BS40: 53.125 | BT40: 43.006993 | BU40: 53.333333 | BV40: 38.461538 | BW40: 26.666667 | BX40: 35.521236
E41: Transportation and logistics | F41: النقل واللوجستيات | AO41: 18.817204 | AP41: 9.2864125 | AQ41: 7 | AR41: 9 | AS41: 1.9677928 | AT41: 0.67322695 | AU41: 78.478261 | AV41: 51.632463 | AW41: 75.031398 | AX41: 70.605797 | AY41: 84.146341 | AZ41: 84.196185 | BA41: 91.25 | BB41: 89.506173 | BC41: 95 | BD41: 92 | BE41: 98.630137 | BF41: 95.481928 | BG41: 90.789474 | BH41: 100 | BI41: 100 | BJ41: 96.242775 | BK41: 98.333333 | BL41: 100 | BM41: 29.230769 | BN41: 31.428571 | BO41: 41 | BP41: 27 | BQ41: 28.358209 | BR41: 24.429967 | BS41: 42.1875 | BT41: 38.461538 | BU41: 46.666667 | BV41: 38.461538 | BW41: 36.666667 | BX41: 48.262548
A81: Figure 2-1
A83: نوع المعوقات وشدتها | B83: Q1 2021 | E83: أبريل – يونيو 2021 | F83: يوليو – سبتمبر 2021
A85: ارتفاع تكاليف الإنتاج | B85: 100 | E85: 100 | F85: 100
A86: ضعف القوة الشرائية | B86: 58.928571 | E86: 75.387038 | F86: 72
A87: زيادة الرسوم المفروضة على الخدمات الحكومية | B87: 80.555556 | E87: 78.108108 | F87: 70
A88: إجراءات التعامل مع الجهات الحكومية | B88: 40.909091 | E88: 68.286635 | F88: 68
A89: المنظومة الضريبية | B89: 36.052632 | E89: 71.19552 | F89: 66
A90: ارتفاع التضخم | B90: 25.872093 | E90: 40.150962 | F90: 55
A91: عدم توفر العمالة المؤهلة | B91: 29.411765 | E91: 48.034398 | F91: 42
A92: المنظومة الجمركية | B92: 25 | E92: 45.441045 | F92: 39
A93: تخبط السياسات الاقتصادية والمالية والنقدية | B93: 21.22093 | E93: 16.971025 | F93: 35
A94: البنية التحتية | B94: 20.294118 | E94: 28.560993 | F94: 23
A95: انتشار الفساد | B95: 17.816092 | E95: 31.458486 | F95: 19
A96: أخرى | B96: - | E96: - | F96: 18
A97: عدم وجود شفافية في سوق الأوراق المالية (البورصة) | B97: - | E97: 15 | F97: 17
A98: تطبيق الإجراءات الاحترازية | B98: 58.333333 | E98: 29.506571 | F98: 11
A99: الحصول على الخدمات المالية والائتمانية | B99: 8.7349398 | E99: 11.802628 | F99: 10
A100: صعوبة شروط منح الائتمان | B100: 5.7228916 | E100: 9.1891892 | F100: 9
A101: الجرائم والسرقات | B101: 13.235294 | E101: 18.212807 | F101: 8
A102: تغير سعر الصرف | B102: 12.804878 | E102: 9.5203311 | F102: 5
A103: ارتفاع سعر الفائدة على القروض | B103: 3.9156627 | E103: 4.5945946 | F103: 3
A106: Figure 2-2
A107: SMEs Size Business Constraints
A110: نوع المعوقات وشدتها | B110: Q2-2021 | E110: Q3-2021
A112: ارتفاع تكاليف الإنتاج | B112: 100 | E112: 100
A113: ضعف القوة الشرائية | B113: 76.109937 | E113: 73
A114: زيادة الرسوم المفروضة على الخدمات الحكومية | B114: 82.01581 | E114: 68
A115: المنظومة الضريبية | B115: 75.268817 | E115: 64
A116: إجراءات التعامل مع الجهات الحكومية | B116: 69.93007 | E116: 63
A117: ارتفاع التضخم | B117: 37.634409 | E117: 55
A118: عدم توفر العمالة المؤهلة | B118: 48.875855 | E118: 42
A119: المنظومة الجمركية | B119: 42.383292 | E119: 39
A120: تخبط السياسات الاقتصادية والمالية والنقدية | B120: 17.106549 | E120: 31
A121: البنية التحتية | B121: 26.88172 | E121: 24
A122: انتشار الفساد | B122: 32.258065 | E122: 20
A123: عدم وجود شفافية فى سوق الاوراق المالية (البورصة) | B123: 14.167651 | E123: 15
A124: أخري | B124: - | E124: 15
A125: الحصول على الخدمات المالية والائتمانية | B125: 12.487512 | E125: 11
A126: تطبيق الإجراءات الاحترازية | B126: 26.973027 | E126: 9
A127: صعوبة شروط منح الائتمان | B127: 9.2864125 | E127: 9
A128: الجرائم والسرقات | B128: 19.061584 | E128: 7
A129: تغير سعر الصرف | B129: 7.8201369 | E129: 5
A130: ارتفاع سعر الفائدة على القروض | B130: 3.458498 | E130: 3
A135: Figure 2-2
A136: Large Size Business Constraints
A141: نوع المعوقات وشدتها | B141: Q2-2021 | E141: Q3-2021
A143: إجراءات التعامل مع الجهات الحكومية | B143: 59.139785 | E143: 100 | AP143: الصغيرة والمتوسطة | AQ143: 5-2: أنواع المعوقات وشدتها | AR143: الكبيرة
A144: ارتفاع تكاليف الإنتاج | B144: 100 | E144: 98 | AP144: 63 | AQ144: إجراءات التعامل مع الجهات الحكومية | AR144: 100
A145: زيادة الرسوم المفروضة على الخدمات الحكومية | B145: 56.451613 | E145: 72 | AP145: 100 | AQ145: ارتفاع تكاليف الإنتاج | AR145: 98
A146: المنظومة الضريبية | B146: 48.387097 | E146: 72 | AP146: 68 | AQ146: زيادة الرسوم المفروضة على الخدمات الحكومية | AR146: 72
A147: ضعف القوة الشرائية | B147: 71.157495 | E147: 58 | AP147: 64 | AQ147: المنظومة الضريبية | AR147: 72
A148: تخبط السياسات الاقتصادية والمالية والنقدية | B148: 16.129032 | E148: 58 | AP148: 73 | AQ148: ضعف القوة الشرائية | AR148: 58
A149: ارتفاع التضخم | B149: 53.763441 | E149: 44 | AP149: 31 | AQ149: تخبط السياسات الاقتصادية والمالية والنقدية | AR149: 58
A150: عدم توفر العمالة المؤهلة | B150: 42.694497 | E150: 42 | AP150: 55 | AQ150: ارتفاع التضخم | AR150: 44
A151: المنظومة الجمركية | B151: 59.772296 | E151: 33 | AP151: 42 | AQ151: عدم توفر العمالة المؤهلة | AR151: 42
A152: أخري | B152: - | E152: 32 | AP152: 39 | AQ152: المنظومة الجمركية | AR152: 33
A153: تطبيق الإجراءات الاحترازية | B153: 43.010753 | E153: 28 | AP153: 15 | AQ153: أخري | AR153: 32
A154: عدم وجود شفافية فى سوق الأوراق المالية (البورصة) | B154: 17.281106 | E154: 26 | AP154: 9 | AQ154: تطبيق الإجراءات الاحترازية | AR154: 28
A155: البنية التحتية | B155: 37.634409 | E155: 14 | AP155: 15 | AQ155: عدم وجود شفافية فى سوق الأوراق المالية (البورصة) | AR155: 26
A156: انتشار الفساد | B156: 26.88172 | E156: 12 | AP156: 24 | AQ156: البنية التحتية | AR156: 14
...

Sheet Sectoral Constraints Fig 2-3 AR
B1: يناير - مارس 2017 | H1: أبريل - يونيو 2017 | N1: يوليو - سبتمبر 2017 | T1: أكتوبر-ديسمبر 2017 | Z1: يناير - مارس 2018 | AF1: أبريل - يونيو 2018 | AL1: يوليو - سبتمبر 2018 | AR1: أكتوبر-ديسمبر 2018 | AX1: يناير - مارس 2019 | BD1: أبريل - يونيو 2019 | BJ1: يوليو - سبتمبر 2019 | BP1: أكتوبر-ديسمبر 2019 | BV1: يناير - مارس 2020 | CB1: أبريل - يونيو 2020 | CH1: يوليو - سبتمبر 2020 | CN1: أكتوبر-ديسمبر 2020 | CT1: يناير - مارس 2021 | CZ1: أبريل - يونيو 2021 | DF1: يوليو - سبتمبر 2021 | DL1: أكتوبر-ديسمبر 2021 | DR1: يناير- مارس 2022 | DX1: أبريل- يونيو 2022 | ED1: يوليو - سبتمبر 2022 | EJ1: أكتوبر - ديسمبر 2022 | EP1: يناير - مارس 2023 | EV1: أبريل- يونيو 2023 | FB1: يوليو-سبتمبر 2023 | FH1: أكتوبر - ديسمبر 2023 | FN1: يناير - مارس 2024 | FT1: أبريل - يونيو 2024 | FZ1: يوليو-سبتمبر 2024 | GF1: أكتوبر - ديسمبر 2024 | GL1: يناير - مارس 2024 | GR1: أبريل - يونيو 2025 | GX1: يوليو-سبتمبر 2024
B5: قطاع الصناعة التحويلية | C5: قطاع التشييد والبناء | D5: قطاع السياحة | E5: قطاع النقل | F5: قطاع الاتصالات | G5: قطاع الخدمات المالية | H5: قطاع الصناعة التحويلية | I5: قطاع التشييد والبناء | J5: قطاع السياحة | K5: قطاع النقل | L5: قطاع الاتصالات | M5: قطاع الخدمات المالية | N5: قطاع الصناعة التحويلية | O5: قطاع التشييد والبناء | P5: قطاع السياحة | Q5: قطاع النقل | R5: قطاع الاتصالات | S5: قطاع الخدمات المالية | T5: قطاع الصناعة التحويلية | U5: قطاع التشييد والبناء | V5: قطاع السياحة | W5: قطاع النقل | X5: قطاع الاتصالات | Y5: قطاع الخدمات المالية | Z5: قطاع الصناعة التحويلية | AA5: قطاع التشييد والبناء | AB5: قطاع السياحة | AC5: قطاع النقل | AD5: قطاع الاتصالات | AE5: قطاع الخدمات المالية | AF5: قطاع الصناعة التحويلية | AG5: قطاع التشييد والبناء | AH5: قطاع السياحة | AI5: قطاع النقل | AJ5: قطاع الاتصالات | AK5: قطاع الخدمات المالية | AL5: قطاع الصناعة التحويلية | AM5: قطاع التشييد والبناء | AN5: قطاع السياحة | AO5: قطاع النقل | AP5: قطاع الاتصالات | AQ5: قطاع الخدمات المالية | AR5: قطاع الصناعة التحويلية | AS5: قطاع التشييد والبناء | AT5: قطاع السياحة | AU5: قطاع النقل | AV5: قطاع الاتصالات | AW5: قطاع الخدمات المالية | AX5: قطاع الصناعة التحويلية | AY5: قطاع التشييد والبناء | AZ5: قطاع السياحة | BA5: قطاع النقل | BB5: قطاع الاتصالات | BC5: قطاع الخدمات المالية | BD5: قطاع الصناعة التحويلية | BE5: قطاع التشييد والبناء | BF5: قطاع السياحة | BG5: قطاع النقل | BH5: قطاع الاتصالات | BI5: قطاع الخدمات المالية | BJ5: قطاع الصناعة التحويلية | BK5: قطاع التشييد والبناء | BL5: قطاع السياحة | BM5: قطاع النقل | BN5: قطاع الاتصالات | BO5: قطاع الخدمات المالية | BP5: قطاع الصناعة التحويلية | BQ5: قطاع التشييد والبناء | BR5: قطاع السياحة | BS5: قطاع النقل | BT5: قطاع الاتصالات | BU5: قطاع الخدمات المالية | BV5: قطاع الصناعة التحويلية | BW5: قطاع التشييد والبناء | BX5: قطاع السياحة | BY5: قطاع النقل | BZ5: قطاع الاتصالات | CA5: قطاع الخدمات المالية | CB5: قطاع الصناعة التحويلية | CC5: قطاع التشييد والبناء | CD5: قطاع السياحة | CE5: قطاع النقل | CF5: قطاع الاتصالات | CG5: قطاع الخدمات المالية | CH5: قطاع الصناعة التحويلية | CI5: قطاع التشييد والبناء | CJ5: قطاع السياحة | CK5: قطاع النقل | CL5: قطاع الاتصالات | CM5: قطاع الخدمات المالية | CN5: قطاع الصناعة التحويلية | CO5: قطاع التشييد والبناء | CP5: قطاع السياحة | CQ5: قطاع النقل | CR5: قطاع الاتصالات | CS5: قطاع الخدمات المالية | CT5: قطاع الصناعة التحويلية | CU5: قطاع التشييد والبناء | CV5: قطاع السياحة | CW5: قطاع النقل | CX5: قطاع الاتصالات | CY5: قطاع الخدمات المالية | CZ5: قطاع الصناعة التحويلية | DA5: قطاع التشييد والبناء | DB5: قطاع السياحة | DC5: قطاع النقل | DD5: قطاع الاتصالات | DE5: قطاع الخدمات المالية | DF5: قطاع الصناعة التحويلية | DG5: قطاع التشييد والبناء | DH5: قطاع السياحة | DI5: قطاع النقل | DJ5: قطاع الاتصالات | DK5: قطاع الخدمات المالية | DL5: قطاع الصناعة التحويلية | DM5: قطاع التشييد والبناء | DN5: قطاع السياحة | DO5: قطاع النقل | DP5: قطاع الاتصالات | DQ5: قطاع الخدمات المالية | DR5: قطاع الصناعة التحويلية | DS5: قطاع التشييد والبناء | DT5: قطاع السياحة | DU5: قطاع النقل | DV5: قطاع الاتصالات | DW5: قطاع الخدمات المالية | DX5: قطاع الصناعة التحويلية | DY5: قطاع التشييد والبناء | DZ5: قطاع السياحة | EA5: قطاع النقل | EB5: قطاع الاتصالات | EC5: قطاع الخدمات المالية | ED5: قطاع الصناعة التحويلية | EE5: قطاع التشييد والبناء | EF5: قطاع السياحة | EG5: قطاع النقل | EH5: قطاع الاتصالات | EI5: قطاع الخدمات المالية | EJ5: قطاع الصناعة التحويلية | EK5: قطاع التشييد والبناء | EL5: قطاع السياحة | EM5: قطاع النقل | EN5: قطاع الاتصالات | EO5: قطاع الخدمات المالية | EP5: قطاع الصناعة التحويلية | EQ5: قطاع التشييد والبناء | ER5: قطاع السياحة | ES5: قطاع النقل | ET5: قطاع الاتصالات | EU5: قطاع الخدمات المالية | EV5: قطاع الصناعة التحويلية | EW5: قطاع التشييد والبناء | EX5: قطاع السياحة | EY5: قطاع النقل | EZ5: قطاع الاتصالات | FA5: قطاع الخدمات المالية | FB5: قطاع الصناعة التحويلية | FC5: قطاع التشييد والبناء | FD5: قطاع السياحة | FE5: قطاع النقل | FF5: قطاع الاتصالات | FG5: قطاع الخدمات المالية | FH5: قطاع الصناعة التحويلية | FI5: قطاع التشييد والبناء | FJ5: قطاع السياحة | FK5: قطاع النقل | FL5: قطاع الاتصالات | FM5: قطاع الخدمات المالية | FN5: قطاع الصناعة التحويلية | FO5: قطاع التشييد والبناء | FP5: قطاع السياحة | FQ5: قطاع النقل | FR5: قطاع الاتصالات | FS5: قطاع الخدمات المالية | FT5: قطاع الصناعة التحويلية | FU5: قطاع التشييد والبناء | FV5: قطاع السياحة | FW5: قطاع النقل | FX5: قطاع الاتصالات | FY5: قطاع الخدمات المالية | FZ5: قطاع الصناعة التحويلية | GA5: قطاع التشييد والبناء | GB5: قطاع السياحة | GC5: قطاع النقل | GD5: قطاع الاتصالات | GE5: قطاع الخدمات المالية | GF5: قطاع الصناعة التحويلية | GG5: قطاع التشييد والبناء | GH5: قطاع السياحة | GI5: قطاع النقل | GJ5: قطاع الاتصالات | GK5: قطاع الخدمات المالية | GL5: قطاع الصناعة التحويلية | GM5: قطاع التشييد والبناء | GN5: قطاع السياحة | GO5: قطاع النقل | GP5: قطاع الاتصالات | GQ5: قطاع الخدمات المالية | GR5: قطاع الصناعة التحويلية | GS5: قطاع التشييد والبناء | GT5: قطاع السياحة | GU5: قطاع النقل | GV5: قطاع الاتصالات | GW5: قطاع الخدمات المالية | GX5: قطاع الصناعة التحويلية | GY5: قطاع التشييد والبناء | GZ5: قطاع السياحة | HA5: قطاع النقل | HB5: قطاع الاتصالات | HC5: قطاع الخدمات المالية
A6: ارتفاع تكاليف الطاقة والمياة | DF6: 100 | DG6: 100 | DH6: 43 | DI6: 100 | DJ6: 55 | DK6: 40 | DL6: 100 | DM6: 100 | DN6: 100 | DO6: 100 | DP6: 72.727273 | DQ6: - | DR6: 100 | DS6: 100 | DT6: 100 | DU6: - | DV6: 100 | DW6: - | DX6: 90.625 | DY6: 100 | DZ6: 60 | EA6: _ | EB6: 46.428571 | EC6: _ | ED6: 98.689956 | EE6: 96.428571 | EF6: 75 | EG6: 0 | EH6: 81.25 | EI6: 0 | EJ6: 98.237885 | EK6: 88.888889 | EL6: 100 | EM6: 92.857143 | EN6: 81.25 | EO6: 1.7857143 | EP6: 99 | EQ6: 100 | ER6: 82 | ES6: 96 | ET6: 84 | EU6: 0 | EV6: 96.888889 | EW6: 96.296296 | EX6: 62.857143 | EY6: 89.130435 | EZ6: 60.714286 | FA6: 0 | FB6: 97.413793 | FC6: 92 | FD6: 87.5 | FE6: 20.454545 | FF6: 81.25 | FG6: 0 | FH6: 100 | FI6: 98.214286 | FJ6: 84.615385 | FK6: 0 | FL6: 100 | FM6: 16.981132 | FN6: 100 | FO6: 87.804878 | FP6: 90 | FQ6: 0 | FR6: 76.923077 | FS6: 23.214286 | FT6: 89.371981 | FU6: 95.833333 | FV6: 100 | FW6: 100 | FX6: 90.322581 | FY6: 40.740741 | FZ6: 99 | GA6: 98 | GB6: 92 | GC6: 87 | GD6: 72 | GE6: 53 | GF6: 87.5 | GG6: 61.538462 | GH6: 72.727273 | GI6: 100 | GJ6: 41.37931 | GK6: 33.333333 | GL6: 100 | GM6: 62.745098 | GN6: 100 | GO6: 100 | GP6: 96 | GQ6: 30.612245 | GR6: 100 | GS6: 76.923077 | GT6: 100 | GU6: 95.833333 | GV6: 68 | GW6: 25.806452 | GX6: 94.086022 | GY6: 76.190476 | GZ6: 100 | HA6: 0 | HB6: 93.333333
A7: زيادة الرسوم المفروضة على الخدمات الحكومية | DF7: 83 | DG7: 96 | DH7: 86 | DI7: 25 | DJ7: 91 | DK7: 10 | DL7: 81.447964 | DM7: 87.272727 | DN7: 86.666667 | DO7: 12.222222 | DP7: 100 | DQ7: 34.799802 | DR7: 83.204931 | DS7: 90.566038 | DT7: 63.888889 | DU7: 43.091168 | DV7: 60 | DW7: 43.103448 | DX7: 68.75 | DY7: 78.431373 | DZ7: 42.5 | EA7: 30.952381 | EB7: 39.285714 | EC7: 53.333333 | ED7: 74.235808 | EE7: 83.928571 | EF7: 45 | EG7: 6.25 | EH7: 50 | EI7: 28.846154 | EJ7: 54.185022 | EK7: 59.259259 | EL7: 79.411765 | EM7: 71.428571 | EN7: 56.25 | EO7: 0 | EP7: 63 | EQ7: 57 | ER7: 79 | ES7: 70 | ET7: 63 | EU7: 19 | EV7: 52 | EW7: 68.518519 | EX7: 37.142857 | EY7: 60.869565 | EZ7: 28.571429 | FA7: 0 | FB7: 51.293103 | FC7: 58 | FD7: 57.5 | FE7: 20.454545 | FF7: 87.5 | FG7: 0 | FH7: 67.826087 | FI7: 55.357143 | FJ7: 38.461538 | FK7: 12.5 | FL7: 62.068966 | FM7: 15.09434 | FN7: 67.368421 | FO7: 60.97561 | FP7: 43.333333 | FQ7: 50 | FR7: 80.769231 | FS7: 28.571429 | FT7: 63.768116 | FU7: 64.583333 | FV7: 46.153846 | FW7: 21.212121 | FX7: 45.16129 | FY7: 20.37037 | FZ7: 57 | GA7: 90 | GB7: 37 | GC7: 30 | GD7: 60 | GE7: 42 | GF7: 62.019231 | GG7: 53.846154 | GH7: 51.515152 | GI7: 88.235294 | GJ7: 48.275862 | GK7: 53.333333 | GL7: 57.653061 | GM7: 37.254902 | GN7: 68.75 | GO7: 75.757576 | GP7: 72 | GQ7: 20.408163 | GR7: 57.948718 | GS7: 71.794872 | GT7: 58.333333 | GU7: 70.833333 | GV7: 72 | GW7: 11.290323 | GX7: 51.075269 | GY7: 52.380952 | GZ7: 20 | HA7: 15 | HB7: 20
A8: إجراءات التعامل مع الجهات الحكومية | DF8: 80 | DG8: 73 | DH8: 100 | DI8: 25 | DJ8: 100 | DK8: 25 | DL8: 71.945701 | DM8: 67.272727 | DN8: 73.333333 | DO8: 11.111111 | DP8: 100 | DQ8: 9.4908552 | DR8: 70.454545 | DS8: 69.811321 | DT8: 50 | DU8: 15.081909 | DV8: 80 | DW8: 3.4482759 | DX8: 67.857143 | DY8: 58.823529 | DZ8: 30 | EA8: 26.190476 | EB8: 60.714286 | EC8: 10 | ED8: 69.432314 | EE8: 66.071429 | EF8: 30 | EG8: 14.583333 | EH8: 68.75 | EI8: 0 | EJ8: 66.960352 | EK8: 50 | EL8: 61.764706 | EM8: 52.380952 | EN8: 68.75 | EO8: 1.7857143 | EP8: 65 | EQ8: 60 | ER8: 54 | ES8: 62 | ET8: 75 | EU8: 0 | EV8: 68.444444 | EW8: 61.111111 | EX8: 31.428571 | EY8: 56.521739 | EZ8: 64.285714 | FA8: 0 | FB8: 65.948276 | FC8: 58 | FD8: 52.5 | FE8: 22.727273 | FF8: 87.5 | FG8: 76.595745 | FH8: 68.26087 | FI8: 57.142857 | FJ8: 30.769231 | FK8: 16.666667 | FL8: 75.862069 | FM8: 43.396226 | FN8: 78.947368 | FO8: 65.853659 | FP8: 40 | FQ8: 37.5 | FR8: 84.615385 | FS8: 37.5 | FT8: 68.115942 | FU8: 70.833333 | FV8: 84.615385 | FW8: 0 | FX8: 77.419355 | FY8: 16.666667 | FZ8: 69 | GA8: 77 | GB8: 76 | GC8: 13 | GD8: 84 | GE8: 63 | GF8: 68.269231 | GG8: 65.384615 | GH8: 78.787879 | GI8: 55.882353 | GJ8: 93.103448 | GK8: 48.888889 | GL8: 63.77551 | GM8: 58.823529 | GN8: 40.625 | GO8: 0 | GP8: 80 | GQ8: 16.326531 | GR8: 69.230769 | GS8: 69.230769 | GT8: 66.666667 | GU8: 54.166667 | GV8: 96 | GW8: 6.4516129 | GX8: 55.913978 | GY8: 61.904762 | GZ8: 25 | HA8: 0 | HB8: 46.666667
A9: مشاكل اجراء التصدير | DF9: 74 | DG9: 90 | DH9: 64 | DI9: 71 | DJ9: 9 | DK9: 27 | DL9: 93.665158 | DM9: 98.181818 | DN9: 56.666667 | DO9: 100 | DP9: 50 | DQ9: - | DR9: 100.12797 | DS9: 90.566038 | DT9: 91.666667 | DU9: - | DV9: 80 | DW9: - | DX9: 66.517857 | DY9: 88.235294 | DZ9: 47.5 | EA9: _ | EB9: 17.857143 | EC9: _ | ED9: 83.842795 | EE9: 100 | EF9: 55 | EG9: 0 | EH9: 34.375 | EI9: 0 | EJ9: 87.665198 | EK9: 96.296296 | EL9: 64.705882 | EM9: 100 | EN9: 34.375 | EO9: 0 | EP9: 90 | EQ9: 89 | ER9: 64 | ES9: 96 | ET9: 50 | EU9: 0 | EV9: 81.777778 | EW9: 94.444444 | EX9: 57.142857 | EY9: 89.130435 | EZ9: 50 | FA9: 0 | FB9: 87.068966 | FC9: 94 | FD9: 57.5 | FE9: 22.727273 | FF9: 56.25 | FG9: 0 | FH9: 76.956522 | FI9: 87.5 | FJ9: 74.358974 | FK9: 0 | FL9: 75.862069 | FM9: 11.320755 | FN9: 80.526316 | FO9: 80.487805 | FP9: 83.333333 | FQ9: 0 | FR9: 84.615385 | FS9: 35.714286 | FT9: 24.637681 | FU9: 0 | FV9: 0 | FW9: 12.121212 | FX9: 0 | FY9: 0 | FZ9: 26 | GA9: 0 | GB9: 11 | GC9: 0 | GD9: 0 | GE9: 0 | GF9: 26.923077 | GG9: 0 | GH9: 0 | GI9: 0 | GJ9: 13.793103 | GK9: 0 | GL9: 25 | GM9: 0 | GN9: 0 | GO9: 0 | GP9: 0 | GQ9: 0 | GR9: 31.282051 | GS9: 0 | GT9: 0 | GU9: 0 | GV9: 4 | GW9: 0 | GX9: 17.204301 | GY9: 0 | GZ9: 0 | HA9: 20 | HB9: 0
A10: المنظومة الضريبية | DF10: 71 | DG10: 69 | DH10: 14 | DI10: 6 | DJ10: 64 | DK10: 100 | DL10: 57.013575 | DM10: 49.090909 | DN10: 80 | DO10: 11.111111 | DP10: 72.727273 | DQ10: 80.672269 | DR10: 60.909091 | DS10: 47.169811 | DT10: 61.111111 | DU10: 28.009259 | DV10: 68 | DW10: 82.758621 | DX10: 40.625 | DY10: 41.176471 | DZ10: 62.5 | EA10: 0 | EB10: 53.571429 | EC10: 85 | ED10: 39.30131 | EE10: 62.5 | EF10: 42.5 | EG10: 20.833333 | EH10: 43.75 | EI10: 76.923077 | EJ10: 51.54185 | EK10: 46.296296 | EL10: 70.588235 | EM10: 47.619048 | EN10: 50 | EO10: 100 | EP10: 53 | EQ10: 40 | ER10: 92 | ES10: 66 | ET10: 63 | EU10: 81 | EV10: 51.111111 | EW10: 57.407407 | EX10: 65.714286 | EY10: 60.869565 | EZ10: 64.285714 | FA10: 100 | FB10: 56.034483 | FC10: 44 | FD10: 80 | FE10: 29.545455 | FF10: 87.5 | FG10: 53.191489 | FH10: 58.26087 | FI10: 57.142857 | FJ10: 33.333333 | FK10: 25 | FL10: 79.310345 | FM10: 90.566038 | FN10: 67.368421 | FO10: 51.219512 | FP10: 63.333333 | FQ10: 30 | FR10: 88.461538 | FS10: 92.857143 | FT10: 67.149758 | FU10: 79.166667 | FV10: 97.435897 | FW10: 36.363636 | FX10: 83.870968 | FY10: 100 | FZ10: 70 | GA10: 73 | GB10: 61 | GC10: 35 | GD10: 100 | GE10: 27 | GF10: 63.461538 | GG10: 44.230769 | GH10: 63.636364 | GI10: 23.529412 | GJ10: 86.206897 | GK10: 42.222222 | GL10: 66.326531 | GM10: 43.137255 | GN10: 75 | GO10: 9.0909091 | GP10: 100 | GQ10: 0 | GR10: 49.230769 | GS10: 53.846154 | GT10: 50 | GU10: 50 | GV10: 96 | GW10: 40.322581 | GX10: 61.827957 | GY10: 45.238095 | GZ10: 50 | HA10: 15 | HB10: 83.333333
A11: صعوبة الحصول علي العمالة المؤهلة | DF11: 61 | DG11: 33 | DH11: 29 | DI11: 6 | DJ11: 45 | DK11: 13 | DL11: 44.343891 | DM11: 36.363636 | DN11: 13.333333 | DO11: 2.2222222 | DP11: 36.363636 | DQ11: 0 | DR11: 43.636364 | DS11: 16.981132 | DT11: 5.5555556 | DU11: 0 | DV11: 52 | DW11: 0 | DX11: 28.125 | DY11: 27.45098 | DZ11: 20 | EA11: 0 | EB11: 39.285714 | EC11: 7.5851852 | ED11: 29.257642 | EE11: 8.9285714 | EF11: 15 | EG11: 0 | EH11: 43.75 | EI11: 3.8461538 | EJ11: 29.515419 | EK11: 14.814815 | EL11: 8.8235294 | EM11: 28.571429 | EN11: 6.25 | EO11: 3.5714286 | EP11: 38 | EQ11: 17 | ER11: 0 | ES11: 13 | ET11: 9 | EU11: 0 | EV11: 45.777778 | EW11: 12.962963 | EX11: 8.5714286 | EY11: 10.869565 | EZ11: 42.857143 | FA11: 0 | FB11: 40.517241 | FC11: 16 | FD11: 32.5 | FE11: 2.2727273 | FF11: 78.125 | FG11: 10.638298 | FH11: 56.086957 | FI11: 28.571429 | FJ11: 46.153846 | FK11: 0 | FL11: 79.310345 | FM11: 13.207547 | FN11: 45.263158 | FO11: 12.195122 | FP11: 46.666667 | FQ11: 0 | FR11: 76.923077 | FS11: 19.642857 | FT11: 49.275362 | FU11: 37.5 | FV11: 23.076923 | FW11: 0 | FX11: 74.193548 | FY11: 3.7037037 | FZ11: 48 | GA11: 10 | GB11: 32 | GC11: 4 | GD11: 68 | GE11: 38 | GF11: 41.346154 | GG11: 13.461538 | GH11: 27.272727 | GI11: 11.764706 | GJ11: 31.034483 | GK11: 26.666667 | GL11: 53.571429 | GM11: 17.647059 | GN11: 37.5 | GO11: 6.0606061 | GP11: 76 | GQ11: 8.1632653 | GR11: 52.307692 | GS11: 20.512821 | GT11: 36.111111 | GU11: 12.5 | GV11: 72 | GW11: 0 | GX11: 72.043011 | GY11: 26.190476 | GZ11: 42.5 | HA11: 0 | HB11: 93.333333
A12: ارتفاع التضخم | DF12: 53 | DG12: 83 | DH12: 57 | DI12: 35 | DJ12: 45 | DK12: 27 | DL12: 89.37984 | DM12: 92.727273 | DN12: 73.333333 | DO12: 12.777778 | DP12: 68.181818 | DQ12: 18.98171 | DR12: 95.454545 | DS12: 96.226415 | DT12: 83.333333 | DU12: 79.718661 | DV12: 84 | DW12: 79.310345 | DX12: 100 | DY12: 100 | DZ12: 100 | EA12: 97.619048 | EB12: 100 | EC12: 86.666667 | ED12: 100 | EE12: 98.214286 | EF12: 100 | EG12: 85.416667 | EH12: 100 | EI12: 100 | EJ12: 100 | EK12: 100 | EL12: 100 | EM12: 100 | EN12: 100 | EO12: 26.785714 | EP12: 100 | EQ12: 94 | ER12: 100 | ES12: 100 | ET12: 100 | EU12: 36 | EV12: 100 | EW12: 100 | EX12: 100 | EY12: 100 | EZ12: 100 | FA12: 26.984127 | FB12: 100 | FC12: 92 | FD12: 95 | FE12: 88.636364 | FF12: 100 | FG12: 0 | FH12: 100 | FI12: 96.428571 | FJ12: 100 | FK12: 95.833333 | FL12: 100 | FM12: 41.509434 | FN12: 98.421053 | FO12: 100 | FP12: 100 | FQ12: 30 | FR12: 100 | FS12: 33.928571 | FT12: 100 | FU12: 95.833333 | FV12: 100 | FW12: 93.939394 | FX12: 100 | FY12: 48.148148 | FZ12: 100 | GA12: 100 | GB12: 100 | GC12: 100 | GD12: 84 | GE12: 33 | GF12: 100 | GG12: 100 | GH12: 100 | GI12: 94.117647 | GJ12: 100 | GK12: 44.444444 | GL12: 97.959184 | GM12: 100 | GN12: 100 | GO12: 69.69697 | GP12: 96 | GQ12: 42.857143 | GR12: 93.333333 | GS12: 100 | GT12: 100 | GU12: 100 | GV12: 100 | GW12: 0 | GX12: 100 | GY12: 100 | GZ12: 97.5 | HA12: 80 | HB12: 100
A13: المنظومة الجمركية | DF13: 38 | DG13: 15 | DH13: 0 | DI13: 40 | DJ13: 36 | DK13: ــ | DL13: 67.836595 | DM13: 51.136364 | DN13: - | DO13: 21.728395 | DP13: 86.363636 | DQ13: - | DR13: 51.717172 | DS13: - | DT13: - | DU13: 14.543269 | DV13: 76 | DW13: - | DX13: 48.287172 | DY13: _ | DZ13: _ | EA13: 0 | EB13: 73.142857 | EC13: _ | ED13: 27.947598 | EE13: 5.3571429 | EF13: 0 | EG13: 8.3333333 | EH13: 53.125 | EI13: 0 | EJ13: 40.969163 | EK13: 25.925926 | EL13: 0 | EM13: 64.285714 | EN13: 25 | EO13: 0 | EP13: 40 | EQ13: 6 | ER13: 5 | ES13: 36 | ET13: 47 | EU13: 0 | EV13: 41.333333 | EW13: 7.4074074 | EX13: 5.7142857 | EY13: 36.956522 | EZ13: 21.428571 | FA13: 0 | FB13: 32.327586 | FC13: 6 | FD13: 30 | FE13: 13.636364 | FF13: 68.75 | FG13: 0 | FH13: 30.869565 | FI13: 7.1428571 | FJ13: 12.820513 | FK13: 8.3333333 | FL13: 31.034483 | FM13: 0 | FN13: 36.315789 | FO13: 0 | FP13: 3.3333333 | FQ13: 0 | FR13: 50 | FS13: 8.9285714 | FT13: 43.478261 | FU13: 4.1666667 | FV13: 0 | FW13: 0 | FX13: 48.387097 | FY13: 0 | FZ13: 43 | GA13: 0 | GB13: 11 | GC13: 9 | GD13: 48 | GE13: 0 | GF13: 38.461538 | GG13: 0 | GH13: 12.121212 | GI13: 44.117647 | GJ13: 20.689655 | GK13: 0 | GL13: 32.142857 | GM13: 3.9215686 | GN13: 9.375 | GO13: 48.484848 | GP13: 44 | GQ13: 0 | GR13: 37.435897 | GS13: 0 | GT13: 11.111111 | GU13: 12.5 | GV13: 32 | GW13: 0 | GX13: 28.494624 | GY13: 0 | GZ13: 0 | HA13: 100 | HB13: 36.666667
A14: تخبط السياسات الاقتصادية | DF14: 29 | DG14: 6 | DH14: 43 | DI14: 6 | DJ14: 45 | DK14: 98 | DL14: 24.434389 | DM14: 12.727273 | DN14: 13.333333 | DO14: 20.495868 | DP14: 0 | DQ14: 80.672269 | DR14: 37.272727 | DS14: 3.7735849 | DT14: 25 | DU14: 96.955128 | DV14: 16 | DW14: 100 | DX14: 32.589286 | DY14: 7.8431373 | DZ14: 15 | EA14: 95.238095 | EB14: 21.428571 | EC14: 100 | ED14: 29.694323 | EE14: 0 | EF14: 0 | EG14: 97.916667 | EH14: 28.125 | EI14: 90.384615 | EJ14: 44.493392 | EK14: 3.7037037 | EL14: 61.764706 | EM14: 0 | EN14: 50 | EO14: 100 | EP14: 50 | EQ14: 13 | ER14: 26 | ES14: 4 | ET14: 47 | EU14: 100 | EV14: 44 | EW14: 14.814815 | EX14: 11.428571 | EY14: 4.3478261 | EZ14: 25 | FA14: 100 | FB14: 51.293103 | FC14: 18 | FD14: 17.5 | FE14: 54.545455 | FF14: 56.25 | FG14: 100 | FH14: 67.826087 | FI14: 23.214286 | FJ14: 20.512821 | FK14: 100 | FL14: 62.068966 | FM14: 100 | FN14: 68.947368 | FO14: 17.073171 | FP14: 30 | FQ14: 100 | FR14: 80.769231 | FS14: 98.214286 | FT14: 56.521739 | FU14: 72.916667 | FV14: 41.025641 | FW14: 36.363636 | FX14: 64.516129 | FY14: 98.148148 | FZ14: 66 | GA14: 52 | GB14: 34 | GC14: 0 | GD14: 72 | GE14: 19 | GF14: 50.961538 | GG14: 50 | GH14: 24.242424 | GI14: 29.411765 | GJ14: 79.310345 | GK14: 31.111111 | GL14: 42.346939 | GM14: 43.137255 | GN14: 9.375 | GO14: 0 | GP14: 44 | GQ14: 16.326531 | GR14: 52.820513 | GS14: 58.974359 | GT14: 30.555556 | GU14: 0 | GV14: 64 | GW14: 0 | GX14: 37.096774 | GY14: 59.52381 | GZ14: 15 | HA14: 15 | HB14: 10
A15: انقطاع الكهرباء | DF15: 24 | DG15: 38 | DH15: 14 | DI15: 5 | DJ15: 0 | DK15: 0 | DL15: 18.552036 | DM15: 20 | DN15: 0 | DO15: 3.3333333 | DP15: 0 | DQ15: 0 | DR15: 9.0909091 | DS15: 1.8867925 | DT15: 13.888889 | DU15: 8.6182336 | DV15: 0 | DW15: 0 | DX15: 3.5714286 | DY15: 11.764706 | DZ15: 5 | EA15: 9.5238095 | EB15: 0 | EC15: 13.333333 | ED15: 6.1135371 | EE15: 1.7857143 | EF15: 0 | EG15: 8.3333333 | EH15: 0 | EI15: 0 | EJ15: 28.193833 | EK15: 18.518519 | EL15: 17.647059 | EM15: 23.809524 | EN15: 0 | EO15: 0 | EP15: 28 | EQ15: 11 | ER15: 0 | ES15: 21 | ET15: 6 | EU15: 0 | EV15: 20 | EW15: 16.666667 | EX15: 0 | EY15: 17.391304 | EZ15: 0 | FA15: 0 | FB15: 17.672414 | FC15: 12 | FD15: 0 | FE15: 2.2727273 | FF15: 50 | FG15: 6.3829787 | FH15: 13.043478 | FI15: 14.285714 | FJ15: 0 | FK15: 0 | FL15: 20.689655 | FM15: 30.188679 | FN15: 11.578947 | FO15: 26.829268 | FP15: 0 | FQ15: 10 | FR15: 42.307692 | FS15: 26.785714 | FT15: 48.792271 | FU15: 100 | FV15: 64.102564 | FW15: 66.666667 | FX15: 58.064516 | FY15: 70.37037 | FZ15: 6 | GA15: 8 | GB15: 11 | GC15: 0 | GD15: 16 | GE15: 3 | GF15: 15.384615 | GG15: 15.384615 | GH15: 6.0606061 | GI15: 0 | GJ15: 17.241379 | GK15: 8.8888889 | GL15: 11.22449 | GM15: 5.8823529 | GN15: 0 | GO15: 0 | GP15: 0 | GQ15: 0 | GR15: 13.846154 | GS15: 2.5641026 | GT15: 5.5555556 | GU15: 0 | GV15: 0 | GW15: 12.903226 | GX15: 13.978495 | GY15: 11.904762 | GZ15: 0 | HA15: 0 | HB15: 0
A16: غياب المعلومات عن السوق المحلي والخارجي | DF16: 19 | DG16: 25 | DH16: 0 | DI16: 31 | DJ16: 45 | DK16: 17 | DL16: 26.244344 | DM16: 36.363636 | DN16: 0 | DO16: 1.1111111 | DP16: 0 | DQ16: 0 | DR16: 18.636364 | DS16: 26.415094 | DT16: 0 | DU16: 5.1282051 | DV16: 16 | DW16: 3.4482759 | DX16: 8.9285714 | DY16: 7.8431373 | DZ16: 0 | EA16: 19.047619 | EB16: 17.857143 | EC16: 10 | ED16: 11.353712 | EE16: 12.5 | EF16: 0 | EG16: 0 | EH16: 18.75 | EI16: 0 | EJ16: 27.753304 | EK16: 24.074074 | EL16: 23.529412 | EM16: 26.190476 | EN16: 0 | EO16: 3.5714286 | EP16: 25 | EQ16: 13 | ER16: 0 | ES16: 28 | ET16: 0 | EU16: 0 | EV16: 11.555556 | EW16: 16.666667 | EX16: 0 | EY16: 23.913043 | EZ16: 0 | FA16: 0 | FB16: 18.103448 | FC16: 28 | FD16: 0 | FE16: 6.8181818 | FF16: 9.375 | FG16: 14.893617 | FH16: 16.956522 | FI16: 21.428571 | FJ16: 0 | FK16: 0 | FL16: 13.793103 | FM16: 20.754717 | FN16: 27.894737 | FO16: 26.829268 | FP16: 0 | FQ16: 0 | FR16: 26.923077 | FS16: 32.142857 | FT16: 50.724638 | FU16: 25 | FV16: 28.205128 | FW16: 33.333333 | FX16: 67.741935 | FY16: 11.111111 | FZ16: 48 | GA16: 10 | GB16: 16 | GC16: 0 | GD16: 32 | GE16: 3 | GF16: 42.307692 | GG16: 26.923077 | GH16: 6.0606061 | GI16: 8.8235294 | GJ16: 24.137931 | GK16: 6.6666667 | GL16: 24.489796 | GM16: 7.8431373 | GN16: 0 | GO16: 6.0606061 | GP16: 32 | GQ16: 0 | GR16: 37.948718 | GS16: 10.25641 | GT16: 16.666667 | GU16: 50 | GV16: 28 | GW16: 20.967742 | GX16: 30.645161 | GY16: 11.904762 | GZ16: 17.5 | HA16: 15 | HB16: 6.6666667
A17: أخرى | DF17: 13 | DG17: ــ | DH17: 50 | DI17: 20 | DJ17: 28 | DK17: 23 | DL17: 5.4298643 | DM17: 0 | DN17: 0 | DO17: 3.8888889 | DP17: 0 | DQ17: 94.908552 | DR17: 7.2727273 | DS17: 0 | DT17: 0 | DU17: 17.236467 | DV17: 0 | DW17: 41.37931 | DX17: 1.7857143 | DY17: 0 | DZ17: 0 | EA17: 0 | EB17: 0 | EC17: 40 | ED17: 0 | EE17: 0 | EF17: 0 | EG17: 8.3333333 | EH17: 0 | EI17: 46.153846 | EJ17: 1.7621145 | EK17: 0 | EL17: 0 | EM17: 0 | EN17: 0 | EO17: 35.714286 | EP17: 2 | EQ17: 0 | ER17: 0 | ES17: 0 | ET17: 0 | EU17: 56 | EV17: 3.1111111 | EW17: 0 | EX17: 8.5714286 | EY17: 0 | EZ17: 28.571429 | FA17: 25.396825 | FB17: 0 | FC17: 0 | FD17: 0 | FE17: 9.0909091 | FF17: 12.5 | FG17: 25.531915 | FH17: 13.913043 | FI17: 0 | FJ17: 10.25641 | FK17: 8.3333333 | FL17: 41.37931 | FM17: 15.09434 | FN17: 3.6842105 | FO17: 0 | FP17: 0 | FQ17: 20 | FR17: 0 | FS17: 44.642857 | FT17: 9.178744 | FU17: 8.3333333 | FV17: 33.333333 | FW17: 36.363636 | FX17: 38.709677 | FY17: 14.814815 | FZ17: 4 | GA17: 0 | GB17: 0 | GC17: 0 | GD17: 0 | GE17: 25 | GF17: 9.6153846 | GG17: 0 | GH17: 0 | GI17: 58.823529 | GJ17: 0 | GK17: 53.333333 | GL17: 4.0816327 | GM17: 0 | GN17: 0 | GO17: 36.363636 | GP17: 16 | GQ17: 65.306122 | GR17: 9.2307692 | GS17: 0 | GT17: 25 | GU17: 16.666667 | GV17: 0 | GW17: 77.419355 | GX17: 2.1505376 | GY17: 0 | GZ17: 0 | HA17: 40 | HB17: 0
A18: غموض توجهات السياسية الاقتصادية في المستقبل | DF18: 9 | DG18: 23 | DH18: 0 | DI18: 0 | DJ18: 0 | DK18: 0 | DL18: 4.0723982 | DM18: 20 | DN18: 0 | DO18: 1.1111111 | DP18: 0 | DQ18: 0 | DR18: 1.3636364 | DS18: 11.320755 | DT18: 0 | DU18: 0 | DV18: 0 | DW18: 0 | DX18: 1.7857143 | DY18: 7.8431373 | DZ18: 0 | EA18: 0 | EB18: 0 | EC18: 0 | ED18: 0.87336245 | EE18: 8.9285714 | EF18: 0 | EG18: 0 | EH18: 0 | EI18: 0 | EJ18: 14.096916 | EK18: 12.962963 | EL18: 11.764706 | EM18: 19.047619 | EN18: 0 | EO18: 0 | EP18: 16 | EQ18: 11 | ER18: 0 | ES18: 17 | ET18: 0 | EU18: 0 | EV18: 8 | EW18: 3.7037037 | EX18: 0 | EY18: 15.217391 | EZ18: 0 | FA18: 0 | FB18: 7.3275862 | FC18: 12 | FD18: 0 | FE18: 0 | FF18: 0 | FG18: 0 | FH18: 1.7391304 | FI18: 10.714286 | FJ18: 0 | FK18: 0 | FL18: 6.8965517 | FM18: 11.320755 | FN18: 6.3157895 | FO18: 7.3170732 | FP18: 0 | FQ18: 0 | FR18: 19.230769 | FS18: 7.1428571 | FT18: 72.463768 | FU18: 87.5 | FV18: 25.641026 | FW18: 60.606061 | FX18: 58.064516 | FY18: 100 | FZ18: 71 | GA18: 67 | GB18: 24 | GC18: 70 | GD18: 64 | GE18: 100 | GF18: 67.788462 | GG18: 42.307692 | GH18: 15.151515 | GI18: 70.588235 | GJ18: 34.482759 | GK18: 100 | GL18: 48.979592 | GM18: 31.372549 | GN18: 6.25 | GO18: 63.636364 | GP18: 60 | GQ18: 100 | GR18: 53.333333 | GS18: 56.410256 | GT18: 25 | GU18: 79.166667 | GV18: 36 | GW18: 100 | GX18: 39.784946 | GY18: 45.238095 | GZ18: 7.5 | HA18: 95 | HB18: 6.6666667
A19: الحصول على الخدمات التمويل | DF19: 7 | DG19: 8 | DH19: 0 | DI19: 40 | DJ19: 27 | DK19: ــ | DL19: 6.0242577 | DM19: 9.0909091 | DN19: 0 | DO19: 0 | DP19: 40.909091 | DQ19: - | DR19: 4.4893378 | DS19: 0 | DT19: 0 | DU19: 4.3091168 | DV19: 16 | DW19: - | DX19: 0 | DY19: 7.8431373 | DZ19: 2.5 | EA19: 76.190476 | EB19: 10.714286 | EC19: _ | ED19: 2.6200873 | EE19: 0 | EF19: 0 | EG19: 0 | EH19: 18.75 | EI19: 0 | EJ19: 10.572687 | EK19: 3.7037037 | EL19: 8.8235294 | EM19: 0 | EN19: 12.5 | EO19: 0 | EP19: 12 | EQ19: 6 | ER19: 0 | ES19: 0 | ET19: 28 | EU19: 0 | EV19: 8.8888889 | EW19: 0 | EX19: 0 | EY19: 0 | EZ19: 25 | FA19: 0 | FB19: 9.0517241 | FC19: 0 | FD19: 0 | FE19: 6.8181818 | FF19: 46.875 | FG19: 0 | FH19: 10.434783 | FI19: 3.5714286 | FJ19: 28.205128 | FK19: 6.25 | FL19: 58.62069 | FM19: 15.09434 | FN19: 19.473684 | FO19: 2.4390244 | FP19: 30 | FQ19: 10 | FR19: 53.846154 | FS19: 19.642857 | FT19: 19.806763 | FU19: 29.166667 | FV19: 30.769231 | FW19: 24.242424 | FX19: 58.064516 | FY19: 0 | FZ19: 19 | GA19: 31 | GB19: 42 | GC19: 0 | GD19: 40 | GE19: 0 | GF19: 32.211538 | GG19: 11.538462 | GH19: 18.181818 | GI19: 11.764706 | GJ19: 65.517241 | GK19: 0 | GL19: 32.142857 | GM19: 21.568627 | GN19: 6.25 | GO19: 12.121212 | GP19: 32 | GQ19: 0 | GR19: 25.641026 | GS19: 23.076923 | GT19: 11.111111 | GU19: 25 | GV19: 64 | GW19: 0 | GX19: 22.043011 | GY19: 26.190476 | GZ19: 20 | HA19: 0 | HB19: 66.666667
A20: النقل واللوجستيات | DF20: 7 | DG20: 6 | DH20: 0 | DI20: 40 | DJ20: 9 | DK20: ــ | DL20: 6.0242577 | DM20: 9.0909091 | DN20: 0 | DO20: 0 | DP20: 40.909091 | DQ20: - | DR20: 4.4893378 | DS20: 0 | DT20: 0 | DU20: 8.6182336 | DV20: 16 | DW20: - | DX20: 0 | DY20: 9.8039216 | DZ20: 0 | EA20: 76.190476 | EB20: 10.714286 | EC20: _ | ED20: 1.7467249 | EE20: 0 | EF20: 0 | EG20: 0 | EH20: 12.5 | EI20: 0 | EJ20: 8.8105727 | EK20: 3.7037037 | EL20: 8.8235294 | EM20: 0 | EN20: 15.625 | EO20: 0 | EP20: 10 | EQ20: 4 | ER20: 0 | ES20: 0 | ET20: 22 | EU20: 0 | EV20: 8 | EW20: 0 | EX20: 0 | EY20: 0 | EZ20: 28.571429 | FA20: 0 | FB20: 6.4655172 | FC20: 0 | FD20: 2.5 | FE20: 0 | FF20: 50 | FG20: 0 | FH20: 9.1304348 | FI20: 0 | FJ20: 23.076923 | FK20: 0 | FL20: 48.275862 | FM20: 9.4339623 | FN20: 18.421053 | FO20: 0 | FP20: 26.666667 | FQ20: 0 | FR20: 73.076923 | FS20: 19.642857 | FT20: 31.884058 | FU20: 37.5 | FV20: 46.153846 | FW20: 12.121212 | FX20: 38.709677 | FY20: 0 | FZ20: 40 | GA20: 8 | GB20: 37 | GC20: 7 | GD20: 28 | GE20: 0 | GF20: 30.769231 | GG20: 9.6153846 | GH20: 27.272727 | GI20: 11.764706 | GJ20: 34.482759 | GK20: 4.4444444 | GL20: 48.979592 | GM20: 7.8431373 | GN20: 59.375 | GO20: 6.0606061 | GP20: 64 | GQ20: 0 | GR20: 47.179487 | GS20: 20.512821 | GT20: 41.666667 | GU20: 16.666667 | GV20: 36 | GW20: 0 | GX20: 54.83871 | GY20: 45.238095 | GZ20: 32.5 | HA20: 0 | HB20: 43.333333
A21: سعر الصرف | DF21: 7 | DG21: 10 | DH21: 0 | DI21: 0 | DJ21: 9 | DK21: 0 | DL21: 2.2624434 | DM21: 0 | DN21: 0 | DO21: 0 | DP21: 0 | DQ21: 0 | DR21: 86.363636 | DS21: 83.018868 | DT21: 66.666667 | DU21: 100 | DV21: 72 | DW21: 0 | DX21: 86.797718 | DY21: 94.117647 | DZ21: 65 | EA21: 100 | EB21: 71 | EC21: 55 | ED21: 86.026201 | EE21: 94.642857 | EF21: 100 | EG21: 100 | EH21: 100 | EI21: 15.384615 | EJ21: 91.629956 | EK21: 100 | EL21: 91.176471 | EM21: 97.619048 | EN21: 90.625 | EO21: 0 | EP21: 96 | EQ21: 98 | ER21: 87 | ES21: 100 | ET21: 100 | EU21: 6 | EV21: 90.666667 | EW21: 100 | EX21: 65.714286 | EY21: 91.304348 | EZ21: 53.571429 | FA21: 80.952381 | FB21: 92.672414 | FC21: 100 | FD21: 92.5 | FE21: 100 | FF21: 78.125 | FG21: 40.425532 | FH21: 96.086957 | FI21: 100 | FJ21: 87.179487 | FK21: 100 | FL21: 100 | FM21: 39.622642 | FN21: 91.052632 | FO21: 82.926829 | FP21: 96.666667 | FQ21: 100 | FR21: 96.153846 | FS21: 100 | FT21: 76.328502 | FU21: 93.75 | FV21: 15.384615 | FW21: 84.848485 | FX21: 25.806452 | FY21: 27.777778 | FZ21: 59 | GA21: 83 | GB21: 26 | GC21: 4 | GD21: 52 | GE21: 6 | GF21: 68.75 | GG21: 96.153846 | GH21: 60.606061 | GI21: 32.352941 | GJ21: 93.103448 | GK21: 20 | GL21: 46.428571 | GM21: 82.352941 | GN21: 37.5 | GO21: 0 | GP21: 48 | GQ21: 0 | GR21: 38.461538 | GS21: 92.307692 | GT21: 30.555556 | GU21: 0 | GV21: 40 | GW21: 0 | GX21: 37.634409 | GY21: 78.571429 | GZ21: 2.5 | HA21: 0 | HB21: 13.333333
A22: عدم تفضيل المنتج المحلي في التعاقدات الحكومية | DF22: 1 | DG22: 4 | DH22: 7 | DI22: 0 | DJ22: 0 | DK22: ــ | DL22: 1.8072773 | DM22: 3.6363636 | DN22: 0 | DO22: 0 | DP22: 0 | DQ22: - | DR22: 10.662177 | DS22: 0 | DT22: 11.111111 | DU22: 0 | DV22: 16 | DW22: - | DX22: 0 | DY22: 13.72549 | DZ22: 0 | EA22: 76.190476 | EB22: 4 | EC22: _ | ED22: 2.1834061 | EE22: 0 | EF22: 0 | EG22: 0 | EH22: 12.5 | EI22: 0 | EJ22: 21.145374 | EK22: 5.5555556 | EL22: 55.882353 | EM22: 0 | EN22: 53.125 | EO22: 1.7857143 | EP22: 23 | EQ22: 8 | ER22: 79 | ES22: 0 | ET22: 50 | EU22: 0 | EV22: 20.444444 | EW22: 7.4074074 | EX22: 71.428571 | EY22: 0 | EZ22: 57.142857 | FA22: 0 | FB22: 25 | FC22: 0 | FD22: 100 | FE22: 6.8181818 | FF22: 90.625 | FG22: 0 | FH22: 33.478261 | FI22: 8.9285714 | FJ22: 87.179487 | FK22: 6.25 | FL22: 82.758621 | FM22: 16.981132 | FN22: 44.210526 | FO22: 4.8780488 | FP22: 83.333333 | FQ22: 10 | FR22: 92.307692 | FS22: 33.928571 | FT22: 36.231884 | FU22: 29.166667 | FV22: 5.1282051 | FW22: 0 | FX22: 35.483871 | FY22: 9.2592593 | FZ22: 22 | GA22: 8 | GB22: 0 | GC22: 0 | GD22: 32 | GE22: 3 | GF22: 15.384615 | GG22: 17.307692 | GH22: 6.0606061 | GI22: 0 | GJ22: 20.689655 | GK22: 0 | GL22: 12.244898 | GM22: 3.9215686 | GN22: 0 | GO22: 0 | GP22: 16 | GQ22: 0 | GR22: 12.820513 | GS22: 2.5641026 | GT22: 0 | GU22: 0 | GV22: 8 | GW22: 0 | GX22: 10.752688 | GY22: 7.1428571 | GZ22: 0 | HA22: 0 | HB22: 3.3333333
A23: المنافسة غير العادلة من الدولة | DF23: 0 | DG23: 0 | DH23: 0 | DI23: 0 | DJ23: 0 | DK23: 71 | DL23: 7.1674208 | DM23: 8.3487941 | DN23: 0 | DO23: - | DP23: 0 | DQ23: 100 | DR23: 0 | DS23: 0 | DT23: 0 | DU23: - | DV23: 0 | DW23: 68.965517 | DX23: 0 | DY23: 4.5480914 | DZ23: 0 | EA23: _ | EB23: 0 | EC23: 80 | ED23: 0 | EE23: 0 | EF23: 0 | EG23: 0 | EH23: 0 | EI23: 0 | EJ23: 0.88105727 | EK23: 1.8518519 | EL23: 2.9411765 | EM23: 7.1428571 | EN23: 0 | EO23: 7.1428571 | EP23: 3 | EQ23: 2 | ER23: 0 | ES23: 0 | ET23: 0 | EU23: 0 | EV23: 0 | EW23: 0 | EX23: 0 | EY23: 0 | EZ23: 0 | FA23: 9.5238095 | FB23: 0 | FC23: 0 | FD23: 0 | FE23: 0 | FF23: 0 | FG23: 17.021277 | FH23: 1.3043478 | FI23: 0 | FJ23: 0 | FK23: 0 | FL23: 6.8965517 | FM23: 30.188679 | FN23: 5.7894737 | FO23: 0 | FP23: 3.3333333 | FQ23: 0 | FR23: 15.384615 | FS23: 39.285714 | FT23: 28.985507 | FU23: 97.916667 | FV23: 28.205128 | FW23: 0 | FX23: 70.967742 | FY23: 11.111111 | FZ23: 28 | GA23: 94 | GB23: 13 | GC23: 0 | GD23: 56 | GE23: 6 | GF23: 21.153846 | GG23: 80.769231 | GH23: 0 | GI23: 5.8823529 | GJ23: 37.931034 | GK23: 8.8888889 | GL23: 18.367347 | GM23: 47.058824 | GN23: 9.375 | GO23: 0 | GP23: 56 | GQ23: 0 | GR23: 13.333333 | GS23: 58.974359 | GT23: 11.111111 | GU23: 0 | GV23: 60 | GW23: 0 | GX23: 6.4516129 | GY23: 40.47619 | GZ23: 5 | HA23: 0 | HB23: 6.6666667

Sheet Sectoral Constraints Fig 2-3 EN
B1: Jan - Mar 2017 | H1: Apr - Jun 2017 | N1: Jul - Sep 2017 | T1: Oct - Dec 2017 | Z1: Jan - Mar 2018 | AF1: Apr - Jun 2018 | AL1: Jul - Sep 2018 | AR1: Oct - Dec 2018 | AX1: Jan - Mar 2019 | BD1: Apr - Jun 2019 | BJ1: Jul - Sep 2019 | BP1: Oct - Dec 2019 | BV1: Jan - Mar 2020 | CB1: Apr - Jun 2020 | CH1: Jul - Sep 2020 | CN1: Oct - Dec 2020 | CT1: Jan - Mar 2021 | CZ1: Apr - Jun 2021 | DF1: Jul - Sep 2021 | DL1: Oct - Dec 2021 | DR1: Jan - Mar 2022 | DX1: Apr - June 2022 | ED1: Jul - Sep 2022 | EJ1: Oct - Dec 2022 | EP1: Jan - Mar 2023 | EV1: Apr - June 2023
B5: Manufacturing | C5: Construction | D5: Tourism | E5: Transport | F5: Communications | G5: Financial Services | H5: Manufacturing | I5: Construction | J5: Tourism | K5: Transport | L5: Communications | M5: Financial Services | N5: Manufacturing | O5: Construction | P5: Tourism | Q5: Transport | R5: Communications | S5: Financial Services | T5: Manufacturing | U5: Construction | V5: Tourism | W5: Transport | X5: Communications | Y5: Financial Services | Z5: Manufacturing | AA5: Construction | AB5: Tourism | AC5: Transport | AD5: Communications | AE5: Financial Services | AF5: Manufacturing | AG5: Construction | AH5: Tourism | AI5: Transport | AJ5: Communications | AK5: Financial Services | AL5: Manufacturing | AM5: Construction | AN5: Tourism | AO5: Transport | AP5: Communications | AQ5: Financial Services | AR5: Manufacturing | AS5: Construction | AT5: Tourism | AU5: Transport | AV5: Communications | AW5: Financial Services | AX5: Manufacturing | AY5: Construction | AZ5: Tourism | BA5: Transport | BB5: Communications | BC5: Financial Services | BD5: Manufacturing | BE5: Construction | BF5: Tourism | BG5: Transport | BH5: Communications | BI5: Financial Services | BJ5: Manufacturing | BK5: Construction | BL5: Tourism | BM5: Transport | BN5: Communications | BO5: Financial Services | BP5: Manufacturing | BQ5: Construction | BR5: Tourism | BS5: Transport | BT5: Communications | BU5: Financial Services | BV5: Manufacturing | BW5: Construction | BX5: Tourism | BY5: Transport | BZ5: Communications | CA5: Financial Services | CB5: Manufacturing | CC5: Construction | CD5: Tourism | CE5: Transport | CF5: Communications | CG5: Financial Services | CH5: Manufacturing | CI5: Construction | CJ5: Tourism | CK5: Transport | CL5: Communications | CM5: Financial Services | CN5: Manufacturing | CO5: Construction | CP5: Tourism | CQ5: Transport | CR5: Communications | CS5: Financial Services | CT5: Manufacturing | CU5: Construction | CV5: Tourism | CW5: Transport | CX5: Communications | CY5: Financial Services | CZ5: Manufacturing | DA5: Construction | DB5: Tourism | DC5: Transport | DD5: Communications | DE5: Financial Services | DF5: Manufacturing | DG5: Construction | DH5: Tourism | DI5: Transport | DJ5: Communications | DK5: Financial Services | DL5: Manufacturing | DM5: Construction | DN5: Tourism | DO5: Transport | DP5: Communications | DQ5: Financial Services | DR5: Manufacturing | DS5: Construction | DT5: Tourism | DU5: Transport | DV5: Communications | DW5: Financial Services | DX5: Manufacturing | DY5: Construction | DZ5: Tourism | EA5: Transport | EB5: Communications | EC5: Financial Services | ED5: Manufacturing | EE5: Construction | EF5: Tourism | EG5: Transport | EH5: Communications | EI5: Financial Services | EJ5: Manufacturing | EK5: Construction | EL5: Tourism | EM5: Transport | EN5: Communications | EO5: Financial Services | EP5: Manufacturing | EQ5: Construction | ER5: Tourism | ES5: Transport | ET5: Communications | EU5: Financial Services | EV5: Manufacturing | EW5: Construction | EX5: Tourism | EY5: Transport | EZ5: Communications | FA5: Financial Services
A6: High production costs | B6: ='Sectoral Constraints Fig 2-3 AR'!B6 -> 0 | C6: ='Sectoral Constraints Fig 2-3 AR'!C6 -> 0 | D6: ='Sectoral Constraints Fig 2-3 AR'!D6 -> 0 | E6: ='Sectoral Constraints Fig 2-3 AR'!E6 -> 0 | F6: ='Sectoral Constraints Fig 2-3 AR'!F6 -> 0 | G6: ='Sectoral Constraints Fig 2-3 AR'!G6 -> 0 | H6: ='Sectoral Constraints Fig 2-3 AR'!H6 -> 0 | I6: ='Sectoral Constraints Fig 2-3 AR'!I6 -> 0 | ... DW6: ='Sectoral Constraints Fig 2-3 AR'!DW6 -> - | DX6: 90.625 | DY6: 100 | DZ6: 60 | EA6: _ | EB6: 46.428571 | EC6: _ | ED6: 98.689956 | EE6: 96.428571 | EF6: 75 | EG6: 0 | EH6: 81.25 | EI6: 0 | EJ6: 98.237885 | EK6: 88.888889 | EL6: 100 | EM6: 92.857143 | EN6: 81.25 | EO6: 1.7857143 | EP6: 99 | EQ6: 100 | ER6: 82 | ES6: 96 | ET6: 84 | EU6: 0 | EV6: 96.888889 | EW6: 96.296296 | EX6: 62.857143 | EY6: 89.130435 | EZ6: 60.714286 | FA6: 0
A7: Increased government services fees | B7: ='Sectoral Constraints Fig 2-3 AR'!B7 -> 0 | C7: ='Sectoral Constraints Fig 2-3 AR'!C7 -> 0 | D7: ='Sectoral Constraints Fig 2-3 AR'!D7 -> 0 | E7: ='Sectoral Constraints Fig 2-3 AR'!E7 -> 0 | F7: ='Sectoral Constraints Fig 2-3 AR'!F7 -> 0 | G7: ='Sectoral Constraints Fig 2-3 AR'!G7 -> 0 | H7: ='Sectoral Constraints Fig 2-3 AR'!H7 -> 0 | I7: ='Sectoral Constraints Fig 2-3 AR'!I7 -> 0 | ... DW7: ='Sectoral Constraints Fig 2-3 AR'!DW7 -> 43.103448 | DX7: 68.75 | DY7: 78.431373 | DZ7: 42.5 | EA7: 30.952381 | EB7: 39.285714 | EC7: 53.333333 | ED7: 74.235808 | EE7: 83.928571 | EF7: 45 | EG7: 6.25 | EH7: 50 | EI7: 28.846154 | EJ7: 54.185022 | EK7: 59.259259 | EL7: 79.411765 | EM7: 71.428571 | EN7: 56.25 | EO7: 0 | EP7: 63 | EQ7: 57 | ER7: 79 | ES7: 70 | ET7: 63 | EU7: 19 | EV7: 52 | EW7: 68.518519 | EX7: 37.142857 | EY7: 60.869565 | EZ7: 28.571429 | FA7: 0
A8: Government procedures | B8: ='Sectoral Constraints Fig 2-3 AR'!B8 -> 0 | C8: ='Sectoral Constraints Fig 2-3 AR'!C8 -> 0 | D8: ='Sectoral Constraints Fig 2-3 AR'!D8 -> 0 | E8: ='Sectoral Constraints Fig 2-3 AR'!E8 -> 0 | F8: ='Sectoral Constraints Fig 2-3 AR'!F8 -> 0 | G8: ='Sectoral Constraints Fig 2-3 AR'!G8 -> 0 | H8: ='Sectoral Constraints Fig 2-3 AR'!H8 -> 0 | I8: ='Sectoral Constraints Fig 2-3 AR'!I8 -> 0 | ... DW8: ='Sectoral Constraints Fig 2-3 AR'!DW8 -> 3.4482759 | DX8: 67.857143 | DY8: 58.823529 | DZ8: 30 | EA8: 26.190476 | EB8: 60.714286 | EC8: 10 | ED8: 69.432314 | EE8: 66.071429 | EF8: 30 | EG8: 14.583333 | EH8: 68.75 | EI8: 0 | EJ8: 66.960352 | EK8: 50 | EL8: 61.764706 | EM8: 52.380952 | EN8: 68.75 | EO8: 1.7857143 | EP8: 65 | EQ8: 60 | ER8: 54 | ES8: 62 | ET8: 75 | EU8: 0 | EV8: 68.444444 | EW8: 61.111111 | EX8: 31.428571 | EY8: 56.521739 | EZ8: 64.285714 | FA8: 0
A9: Weak purchasing power | B9: ='Sectoral Constraints Fig 2-3 AR'!B9 -> 0 | C9: ='Sectoral Constraints Fig 2-3 AR'!C9 -> 0 | D9: ='Sectoral Constraints Fig 2-3 AR'!D9 -> 0 | E9: ='Sectoral Constraints Fig 2-3 AR'!E9 -> 0 | F9: ='Sectoral Constraints Fig 2-3 AR'!F9 -> 0 | G9: ='Sectoral Constraints Fig 2-3 AR'!G9 -> 0 | H9: ='Sectoral Constraints Fig 2-3 AR'!H9 -> 0 | I9: ='Sectoral Constraints Fig 2-3 AR'!I9 -> 0 | ... DW9: ='Sectoral Constraints Fig 2-3 AR'!DW9 -> - | DX9: 66.517857 | DY9: 88.235294 | DZ9: 47.5 | EA9: _ | EB9: 17.857143 | EC9: _ | ED9: 83.842795 | EE9: 100 | EF9: 55 | EG9: 0 | EH9: 34.375 | EI9: 0 | EJ9: 87.665198 | EK9: 96.296296 | EL9: 64.705882 | EM9: 100 | EN9: 34.375 | EO9: 0 | EP9: 90 | EQ9: 89 | ER9: 64 | ES9: 96 | ET9: 50 | EU9: 0 | EV9: 81.777778 | EW9: 94.444444 | EX9: 57.142857 | EY9: 89.130435 | EZ9: 50 | FA9: 0
A10: Taxation system | B10: ='Sectoral Constraints Fig 2-3 AR'!B10 -> 0 | C10: ='Sectoral Constraints Fig 2-3 AR'!C10 -> 0 | D10: ='Sectoral Constraints Fig 2-3 AR'!D10 -> 0 | E10: ='Sectoral Constraints Fig 2-3 AR'!E10 -> 0 | F10: ='Sectoral Constraints Fig 2-3 AR'!F10 -> 0 | G10: ='Sectoral Constraints Fig 2-3 AR'!G10 -> 0 | H10: ='Sectoral Constraints Fig 2-3 AR'!H10 -> 0 | I10: ='Sectoral Constraints Fig 2-3 AR'!I10 -> 0 | ... DW10: ='Sectoral Constraints Fig 2-3 AR'!DW10 -> 82.758621 | DX10: 40.625 | DY10: 41.176471 | DZ10: 62.5 | EA10: 0 | EB10: 53.571429 | EC10: 85 | ED10: 39.30131 | EE10: 62.5 | EF10: 42.5 | EG10: 20.833333 | EH10: 43.75 | EI10: 76.923077 | EJ10: 51.54185 | EK10: 46.296296 | EL10: 70.588235 | EM10: 47.619048 | EN10: 50 | EO10: 100 | EP10: 53 | EQ10: 40 | ER10: 92 | ES10: 66 | ET10: 63 | EU10: 81 | EV10: 51.111111 | EW10: 57.407407 | EX10: 65.714286 | EY10: 60.869565 | EZ10: 64.285714 | FA10: 100
A11: Lack of skilled labor | B11: ='Sectoral Constraints Fig 2-3 AR'!B11 -> 0 | C11: ='Sectoral Constraints Fig 2-3 AR'!C11 -> 0 | D11: ='Sectoral Constraints Fig 2-3 AR'!D11 -> 0 | E11: ='Sectoral Constraints Fig 2-3 AR'!E11 -> 0 | F11: ='Sectoral Constraints Fig 2-3 AR'!F11 -> 0 | G11: ='Sectoral Constraints Fig 2-3 AR'!G11 -> 0 | H11: ='Sectoral Constraints Fig 2-3 AR'!H11 -> 0 | I11: ='Sectoral Constraints Fig 2-3 AR'!I11 -> 0 | ... DW11: ='Sectoral Constraints Fig 2-3 AR'!DW11 -> 0 | DX11: 28.125 | DY11: 27.45098 | DZ11: 20 | EA11: 0 | EB11: 39.285714 | EC11: 7.5851852 | ED11: 29.257642 | EE11: 8.9285714 | EF11: 15 | EG11: 0 | EH11: 43.75 | EI11: 3.8461538 | EJ11: 29.515419 | EK11: 14.814815 | EL11: 8.8235294 | EM11: 28.571429 | EN11: 6.25 | EO11: 3.5714286 | EP11: 38 | EQ11: 17 | ER11: 0 | ES11: 13 | ET11: 9 | EU11: 0 | EV11: 45.777778 | EW11: 12.962963 | EX11: 8.5714286 | EY11: 10.869565 | EZ11: 42.857143 | FA11: 0
A12: High inflation | B12: ='Sectoral Constraints Fig 2-3 AR'!B12 -> 0 | C12: ='Sectoral Constraints Fig 2-3 AR'!C12 -> 0 | D12: ='Sectoral Constraints Fig 2-3 AR'!D12 -> 0 | E12: ='Sectoral Constraints Fig 2-3 AR'!E12 -> 0 | F12: ='Sectoral Constraints Fig 2-3 AR'!F12 -> 0 | G12: ='Sectoral Constraints Fig 2-3 AR'!G12 -> 0 | H12: ='Sectoral Constraints Fig 2-3 AR'!H12 -> 0 | I12: ='Sectoral Constraints Fig 2-3 AR'!I12 -> 0 | ... DW12: ='Sectoral Constraints Fig 2-3 AR'!DW12 -> 79.310345 | DX12: 100 | DY12: 100 | DZ12: 100 | EA12: 97.619048 | EB12: 100 | EC12: 86.666667 | ED12: 100 | EE12: 98.214286 | EF12: 100 | EG12: 85.416667 | EH12: 100 | EI12: 100 | EJ12: 100 | EK12: 100 | EL12: 100 | EM12: 100 | EN12: 100 | EO12: 26.785714 | EP12: 100 | EQ12: 94 | ER12: 100 | ES12: 100 | ET12: 100 | EU12: 36 | EV12: 100 | EW12: 100 | EX12: 100 | EY12: 100 | EZ12: 100 | FA12: 26.984127
A13: Customs system | B13: ='Sectoral Constraints Fig 2-3 AR'!B13 -> 0 | C13: ='Sectoral Constraints Fig 2-3 AR'!C13 -> 0 | D13: ='Sectoral Constraints Fig 2-3 AR'!D13 -> 0 | E13: ='Sectoral Constraints Fig 2-3 AR'!E13 -> 0 | F13: ='Sectoral Constraints Fig 2-3 AR'!F13 -> 0 | G13: ='Sectoral Constraints Fig 2-3 AR'!G13 -> 0 | H13: ='Sectoral Constraints Fig 2-3 AR'!H13 -> 0 | I13: ='Sectoral Constraints Fig 2-3 AR'!I13 -> 0 | ... DW13: ='Sectoral Constraints Fig 2-3 AR'!DW13 -> - | DX13: 48.287172 | DY13: _ | DZ13: _ | EA13: 0 | EB13: 73.142857 | EC13: _ | ED13: 27.947598 | EE13: 5.3571429 | EF13: 0 | EG13: 8.3333333 | EH13: 53.125 | EI13: 0 | EJ13: 40.969163 | EK13: 25.925926 | EL13: 0 | EM13: 64.285714 | EN13: 25 | EO13: 0 | EP13: 40 | EQ13: 6 | ER13: 5 | ES13: 36 | ET13: 47 | EU13: 0 | EV13: 41.333333 | EW13: 7.4074074 | EX13: 5.7142857 | EY13: 36.956522 | EZ13: 21.428571 | FA13: 0
A14: Unstable economic, fiscal and monetary policy | B14: ='Sectoral Constraints Fig 2-3 AR'!B14 -> 0 | C14: ='Sectoral Constraints Fig 2-3 AR'!C14 -> 0 | D14: ='Sectoral Constraints Fig 2-3 AR'!D14 -> 0 | E14: ='Sectoral Constraints Fig 2-3 AR'!E14 -> 0 | F14: ='Sectoral Constraints Fig 2-3 AR'!F14 -> 0 | G14: ='Sectoral Constraints Fig 2-3 AR'!G14 -> 0 | H14: ='Sectoral Constraints Fig 2-3 AR'!H14 -> 0 | I14: ='Sectoral Constraints Fig 2-3 AR'!I14 -> 0 | ... DW14: ='Sectoral Constraints Fig 2-3 AR'!DW14 -> 100 | DX14: 32.589286 | DY14: 7.8431373 | DZ14: 15 | EA14: 95.238095 | EB14: 21.428571 | EC14: 100 | ED14: 29.694323 | EE14: 0 | EF14: 0 | EG14: 97.916667 | EH14: 28.125 | EI14: 90.384615 | EJ14: 44.493392 | EK14: 3.7037037 | EL14: 61.764706 | EM14: 0 | EN14: 50 | EO14: 100 | EP14: 50 | EQ14: 13 | ER14: 26 | ES14: 4 | ET14: 47 | EU14: 100 | EV14: 44 | EW14: 14.814815 | EX14: 11.428571 | EY14: 4.3478261 | EZ14: 25 | FA14: 100
A15: Corruption | B15: ='Sectoral Constraints Fig 2-3 AR'!B15 -> 0 | C15: ='Sectoral Constraints Fig 2-3 AR'!C15 -> 0 | D15: ='Sectoral Constraints Fig 2-3 AR'!D15 -> 0 | E15: ='Sectoral Constraints Fig 2-3 AR'!E15 -> 0 | F15: ='Sectoral Constraints Fig 2-3 AR'!F15 -> 0 | G15: ='Sectoral Constraints Fig 2-3 AR'!G15 -> 0 | H15: ='Sectoral Constraints Fig 2-3 AR'!H15 -> 0 | I15: ='Sectoral Constraints Fig 2-3 AR'!I15 -> 0 | ... DW15: ='Sectoral Constraints Fig 2-3 AR'!DW15 -> 0 | DX15: 3.5714286 | DY15: 11.764706 | DZ15: 5 | EA15: 9.5238095 | EB15: 0 | EC15: 13.333333 | ED15: 6.1135371 | EE15: 1.7857143 | EF15: 0 | EG15: 8.3333333 | EH15: 0 | EI15: 0 | EJ15: 28.193833 | EK15: 18.518519 | EL15: 17.647059 | EM15: 23.809524 | EN15: 0 | EO15: 0 | EP15: 28 | EQ15: 11 | ER15: 0 | ES15: 21 | ET15: 6 | EU15: 0 | EV15: 20 | EW15: 16.666667 | EX15: 0 | EY15: 17.391304 | EZ15: 0 | FA15: 0
A16: Infrastructure | B16: ='Sectoral Constraints Fig 2-3 AR'!B16 -> 0 | C16: ='Sectoral Constraints Fig 2-3 AR'!C16 -> 0 | D16: ='Sectoral Constraints Fig 2-3 AR'!D16 -> 0 | E16: ='Sectoral Constraints Fig 2-3 AR'!E16 -> 0 | F16: ='Sectoral Constraints Fig 2-3 AR'!F16 -> 0 | G16: ='Sectoral Constraints Fig 2-3 AR'!G16 -> 0 | H16: ='Sectoral Constraints Fig 2-3 AR'!H16 -> 0 | I16: ='Sectoral Constraints Fig 2-3 AR'!I16 -> 0 | ... DW16: ='Sectoral Constraints Fig 2-3 AR'!DW16 -> 3.4482759 | DX16: 8.9285714 | DY16: 7.8431373 | DZ16: 0 | EA16: 19.047619 | EB16: 17.857143 | EC16: 10 | ED16: 11.353712 | EE16: 12.5 | EF16: 0 | EG16: 0 | EH16: 18.75 | EI16: 0 | EJ16: 27.753304 | EK16: 24.074074 | EL16: 23.529412 | EM16: 26.190476 | EN16: 0 | EO16: 3.5714286 | EP16: 25 | EQ16: 13 | ER16: 0 | ES16: 28 | ET16: 0 | EU16: 0 | EV16: 11.555556 | EW16: 16.666667 | EX16: 0 | EY16: 23.913043 | EZ16: 0 | FA16: 0
A17: Precautionary measures | B17: ='Sectoral Constraints Fig 2-3 AR'!#REF! -> #REF! | C17: ='Sectoral Constraints Fig 2-3 AR'!#REF! -> #REF! | D17: ='Sectoral Constraints Fig 2-3 AR'!#REF! -> #REF! | E17: ='Sectoral Constraints Fig 2-3 AR'!#REF! -> #REF! | F17: ='Sectoral Constraints Fig 2-3 AR'!#REF! -> #REF! | G17: ='Sectoral Constraints Fig 2-3 AR'!#REF! -> #REF! | H17: ='Sectoral Constraints Fig 2-3 AR'!#REF! -> #REF! | I17: ='Sectoral Constraints Fig 2-3 AR'!#REF! -> #REF! | ... DW17: ='Sectoral Constraints Fig 2-3 AR'!#REF! -> #REF! | DX17: 0 | DY17: 9.0961829 | DZ17: 0 | EA17: _ | EB17: 0 | EC17: 0 | ED17: 0 | EE17: 0 | EF17: 0 | EG17: 0 | EH17: 0 | EI17: 0 | EJ17: 1.7621145 | EK17: 1.8518519 | EL17: 0 | EM17: 4.7619048 | EN17: 0 | EO17: 0 | EP17: 2 | EQ17: 4 | ER17: 0 | ES17: 0 | ET17: 0 | EU17: 0 | EV17: 0 | EW17: 0 | EX17: 0 | EY17: 0 | EZ17: 0 | FA17: 0
A18: Others | B18: ='Sectoral Constraints Fig 2-3 AR'!B17 -> 0 | C18: ='Sectoral Constraints Fig 2-3 AR'!C17 -> 0 | D18: ='Sectoral Constraints Fig 2-3 AR'!D17 -> 0 | E18: ='Sectoral Constraints Fig 2-3 AR'!E17 -> 0 | F18: ='Sectoral Constraints Fig 2-3 AR'!F17 -> 0 | G18: ='Sectoral Constraints Fig 2-3 AR'!G17 -> 0 | H18: ='Sectoral Constraints Fig 2-3 AR'!H17 -> 0 | I18: ='Sectoral Constraints Fig 2-3 AR'!I17 -> 0 | ... DW18: ='Sectoral Constraints Fig 2-3 AR'!DW17 -> 41.37931 | DX18: 1.7857143 | DY18: 0 | DZ18: 0 | EA18: 0 | EB18: 0 | EC18: 40 | ED18: 0 | EE18: 0 | EF18: 0 | EG18: 8.3333333 | EH18: 0 | EI18: 46.153846 | EJ18: 1.7621145 | EK18: 0 | EL18: 0 | EM18: 0 | EN18: 0 | EO18: 35.714286 | EP18: 2 | EQ18: 0 | ER18: 0 | ES18: 0 | ET18: 0 | EU18: 56 | EV18: 3.1111111 | EW18: 0 | EX18: 8.5714286 | EY18: 0 | EZ18: 28.571429 | FA18: 25.396825
A19: Crimes and thefts | B19: ='Sectoral Constraints Fig 2-3 AR'!B18 -> 0 | C19: ='Sectoral Constraints Fig 2-3 AR'!C18 -> 0 | D19: ='Sectoral Constraints Fig 2-3 AR'!D18 -> 0 | E19: ='Sectoral Constraints Fig 2-3 AR'!E18 -> 0 | F19: ='Sectoral Constraints Fig 2-3 AR'!F18 -> 0 | G19: ='Sectoral Constraints Fig 2-3 AR'!G18 -> 0 | H19: ='Sectoral Constraints Fig 2-3 AR'!H18 -> 0 | I19: ='Sectoral Constraints Fig 2-3 AR'!I18 -> 0 | ... DW19: ='Sectoral Constraints Fig 2-3 AR'!DW18 -> 0 | DX19: 1.7857143 | DY19: 7.8431373 | DZ19: 0 | EA19: 0 | EB19: 0 | EC19: 0 | ED19: 0.87336245 | EE19: 8.9285714 | EF19: 0 | EG19: 0 | EH19: 0 | EI19: 0 | EJ19: 14.096916 | EK19: 12.962963 | EL19: 11.764706 | EM19: 19.047619 | EN19: 0 | EO19: 0 | EP19: 16 | EQ19: 11 | ER19: 0 | ES19: 17 | ET19: 0 | EU19: 0 | EV19: 8 | EW19: 3.7037037 | EX19: 0 | EY19: 15.217391 | EZ19: 0 | FA19: 0
A20: Access to financial and credit services | B20: ='Sectoral Constraints Fig 2-3 AR'!B19 -> 0 | C20: ='Sectoral Constraints Fig 2-3 AR'!C19 -> 0 | D20: ='Sectoral Constraints Fig 2-3 AR'!D19 -> 0 | E20: ='Sectoral Constraints Fig 2-3 AR'!E19 -> 0 | F20: ='Sectoral Constraints Fig 2-3 AR'!F19 -> 0 | G20: ='Sectoral Constraints Fig 2-3 AR'!G19 -> 0 | H20: ='Sectoral Constraints Fig 2-3 AR'!H19 -> 0 | I20: ='Sectoral Constraints Fig 2-3 AR'!I19 -> 0 | ... DW20: ='Sectoral Constraints Fig 2-3 AR'!DW19 -> - | DX20: 0 | DY20: 7.8431373 | DZ20: 2.5 | EA20: 76.190476 | EB20: 10.714286 | EC20: _ | ED20: 2.6200873 | EE20: 0 | EF20: 0 | EG20: 0 | EH20: 18.75 | EI20: 0 | EJ20: 10.572687 | EK20: 3.7037037 | EL20: 8.8235294 | EM20: 0 | EN20: 12.5 | EO20: 0 | EP20: 12 | EQ20: 6 | ER20: 0 | ES20: 0 | ET20: 28 | EU20: 0 | EV20: 8.8888889 | EW20: 0 | EX20: 0 | EY20: 0 | EZ20: 25 | FA20: 0
A21: Difficult credit conditions | B21: ='Sectoral Constraints Fig 2-3 AR'!B20 -> 0 | C21: ='Sectoral Constraints Fig 2-3 AR'!C20 -> 0 | D21: ='Sectoral Constraints Fig 2-3 AR'!D20 -> 0 | E21: ='Sectoral Constraints Fig 2-3 AR'!E20 -> 0 | F21: ='Sectoral Constraints Fig 2-3 AR'!F20 -> 0 | G21: ='Sectoral Constraints Fig 2-3 AR'!G20 -> 0 | H21: ='Sectoral Constraints Fig 2-3 AR'!H20 -> 0 | I21: ='Sectoral Constraints Fig 2-3 AR'!I20 -> 0 | ... DW21: ='Sectoral Constraints Fig 2-3 AR'!DW20 -> - | DX21: 0 | DY21: 9.8039216 | DZ21: 0 | EA21: 76.190476 | EB21: 10.714286 | EC21: _ | ED21: 1.7467249 | EE21: 0 | EF21: 0 | EG21: 0 | EH21: 12.5 | EI21: 0 | EJ21: 8.8105727 | EK21: 3.7037037 | EL21: 8.8235294 | EM21: 0 | EN21: 15.625 | EO21: 0 | EP21: 10 | EQ21: 4 | ER21: 0 | ES21: 0 | ET21: 22 | EU21: 0 | EV21: 8 | EW21: 0 | EX21: 0 | EY21: 0 | EZ21: 28.571429 | FA21: 0
A22: Exchange rate | B22: ='Sectoral Constraints Fig 2-3 AR'!B21 -> 0 | C22: ='Sectoral Constraints Fig 2-3 AR'!C21 -> 0 | D22: ='Sectoral Constraints Fig 2-3 AR'!D21 -> 0 | E22: ='Sectoral Constraints Fig 2-3 AR'!E21 -> 0 | F22: ='Sectoral Constraints Fig 2-3 AR'!F21 -> 0 | G22: ='Sectoral Constraints Fig 2-3 AR'!G21 -> 0 | H22: ='Sectoral Constraints Fig 2-3 AR'!H21 -> 0 | I22: ='Sectoral Constraints Fig 2-3 AR'!I21 -> 0 | ... DW22: ='Sectoral Constraints Fig 2-3 AR'!DW21 -> 0 | DX22: 86.797718 | DY22: 94.117647 | DZ22: 65 | EA22: 100 | EB22: 71 | EC22: 55 | ED22: 86.026201 | EE22: 94.642857 | EF22: 100 | EG22: 100 | EH22: 100 | EI22: 15.384615 | EJ22: 91.629956 | EK22: 100 | EL22: 91.176471 | EM22: 97.619048 | EN22: 90.625 | EO22: 0 | EP22: 96 | EQ22: 98 | ER22: 87 | ES22: 100 | ET22: 100 | EU22: 6 | EV22: 90.666667 | EW22: 100 | EX22: 65.714286 | EY22: 91.304348 | EZ22: 53.571429 | FA22: 80.952381
A23: High loan interest rate | B23: ='Sectoral Constraints Fig 2-3 AR'!B22 -> 0 | C23: ='Sectoral Constraints Fig 2-3 AR'!C22 -> 0 | D23: ='Sectoral Constraints Fig 2-3 AR'!D22 -> 0 | E23: ='Sectoral Constraints Fig 2-3 AR'!E22 -> 0 | F23: ='Sectoral Constraints Fig 2-3 AR'!F22 -> 0 | G23: ='Sectoral Constraints Fig 2-3 AR'!G22 -> 0 | H23: ='Sectoral Constraints Fig 2-3 AR'!H22 -> 0 | I23: ='Sectoral Constraints Fig 2-3 AR'!I22 -> 0 | ... DW23: ='Sectoral Constraints Fig 2-3 AR'!DW22 -> - | DX23: 0 | DY23: 13.72549 | DZ23: 0 | EA23: 76.190476 | EB23: 4 | EC23: _ | ED23: 2.1834061 | EE23: 0 | EF23: 0 | EG23: 0 | EH23: 12.5 | EI23: 0 | EJ23: 21.145374 | EK23: 5.5555556 | EL23: 55.882353 | EM23: 0 | EN23: 53.125 | EO23: 1.7857143 | EP23: 23 | EQ23: 8 | ER23: 79 | ES23: 0 | ET23: 50 | EU23: 0 | EV23: 20.444444 | EW23: 7.4074074 | EX23: 71.428571 | EY23: 0 | EZ23: 57.142857 | FA23: 0
A24: Lack of transparency in the stocks market | B24: ='Sectoral Constraints Fig 2-3 AR'!B23 -> 0 | C24: ='Sectoral Constraints Fig 2-3 AR'!C23 -> 0 | D24: ='Sectoral Constraints Fig 2-3 AR'!D23 -> 0 | E24: ='Sectoral Constraints Fig 2-3 AR'!E23 -> 0 | F24: ='Sectoral Constraints Fig 2-3 AR'!F23 -> 0 | G24: ='Sectoral Constraints Fig 2-3 AR'!G23 -> 0 | H24: ='Sectoral Constraints Fig 2-3 AR'!H23 -> 0 | I24: ='Sectoral Constraints Fig 2-3 AR'!I23 -> 0 | ... DW24: ='Sectoral Constraints Fig 2-3 AR'!DW23 -> 68.965517 | DX24: 0 | DY24: 4.5480914 | DZ24: 0 | EA24: _ | EB24: 0 | EC24: 80 | ED24: 0 | EE24: 0 | EF24: 0 | EG24: 0 | EH24: 0 | EI24: 0 | EJ24: 0.88105727 | EK24: 1.8518519 | EL24: 2.9411765 | EM24: 7.1428571 | EN24: 0 | EO24: 7.1428571 | EP24: 3 | EQ24: 2 | ER24: 0 | ES24: 0 | ET24: 0 | EU24: 0 | EV24: 0 | EW24: 0 | EX24: 0 | EY24: 0 | EZ24: 0 | FA24: 9.5238095

Sheet Gov Priorities Fig 2-4 & 2.5
AU2: يناير - مارس 2022 | AW2: أبريل - يونيو 2022 | AY2: يوليو - سبتمبر 2022 | BB2: اكتوبر -ديسمبر 2022 | BD2: يناير - مارس 2023 | BF2: أبريل - يونيو 2023 | BH2: يوليو - سبتمبر 2023 | BJ2: اكتوبر -ديسمبر 2023 | BL2: يناير - مارس 2024 | BN2: أبريل - يونيو 2024 | BP2: يوليو - سبتمبر 2024 | BR2: اكتوبر -ديسمبر 2024 | BT2: يناير - مارس 2025 | BV2: أبريل - يونيو 2025 | BX2: يوليو - سبتمبر 2025 | BZ2: يوليو - سبتمبر 2025
E3: Priorities | F3: أولويات الحكومة | G3: Jan-Mar 2017 | I3: Apr-Jun 2017 | K3: Jul-Sep 2017 | M3: Oct-Dec 2017 | O3: Jan-Mar 2018 | Q3: Apr-Jun 2018 | S3: Jul-Sep 2018 | U3: Oct-Dec 2018 | W3: Jan-Mar 2019 | Y3: Apr-Jun 2019 | AA3: Jul-Sep 2019 | AC3: Oct-Dec 2019 | AE3: Jan-Mar 2020 | AG3: Apr-Jun 2020 | AI3: Jul-Sep 2020 | AK3: Oct-Dec 2020 | AM3: Jan-Mar 2021 | AO3: Apr-Jun 2021 | AQ3: Jul-Sep 2021 | AS3: Oct-Dec 2021 | AU3: Jan-Mar 2022 | AW3: Apr-Jun 2022 | AY3: Jul - Sep 2022 | BB3: Oct-Dec 2022 | BD3: Jan-Mar 2023 | BF3: Apr-Jun 203 | BH3: Jul - Sep 2023 | BJ3: Oct-Dec 2023 | BL3: Jan-Mar 2023 | BN3: Apr-Jun 204 | BP3: Jul - Sep 2023 | BR3: Oct-Dec 2023 | BT3: Jan-Mar 2023 | BV3: Apr-Jun 205 | BX3: Jul - Sep 2025 | BZ3: Jul - Sep 2023
E4: Economic policy consistency | F4: اتساق السياسات الاقتصادية | AQ4: 100 | AS4: 100 | AU4: 100 | AW4: 100 | AY4: 100 | BB4: 100 | BD4: 79.822616 | BF4: 86 | BH4: 78.33698 | BJ4: 87.103594 | BL4: 86.752137 | BN4: _ | BP4: 26.086957 | BR4: 39 | BT4: 34.285714 | BV4: 26.388889 | BX4: 28.846154
E5: Facilitating government procedures | F5: تسهيل الإجراءات الحكومية | AQ5: 90.867116 | AS5: 78.589421 | AU5: 83.333333 | AW5: 68.43318 | AY5: 80.487805 | BB5: 75.233645 | BD5: 72.062084 | BF5: 68 | BH5: 75.273523 | BJ5: 70.190275 | BL5: 70.726496 | BN5: 76.963351 | BP5: 27.536232 | BR5: 74 | BT5: 72.857143 | BV5: 33.333333 | BX5: 63.461538
E6: Transportation and logistics | F6: النقل واللوجستيات | AQ6: 71.794872 | AS6: 71.729439 | AU6: 54.761905 | AW6: 63.964865 | AY6: 76.341463 | BB6: 67.757009 | BD6: 81.374723 | BF6: 77 | BH6: 82.713348 | BJ6: 86.892178 | BL6: 80.128205 | BN6: _ | BP6: 2.8985507 | BR6: 2 | BT6: 1.4285714 | BV6: 8.3333333 | BX6: 9.6153846
E7: Taxation system | F7: المنظومة الضريبية | AQ7: 81.263275 | AS7: 67.749336 | AU7: 60.714286 | AW7: 69.124424 | AY7: 56.097561 | BB7: 58.17757 | BD7: 64.745011 | BF7: 72 | BH7: 69.365427 | BJ7: 63.002114 | BL7: 59.188034 | BN7: 68.586387 | BP7: 56.521739 | BR7: 85 | BT7: 42.857143 | BV7: 37.5 | BX7: 65.384615
E8: Reducing government service fees | F8: تخفيض الرسوم المفروضة على الخدمات الحكومية | AQ8: 81.684982 | AS8: 66.605907 | AU8: 78.571429 | AW8: 73.963134 | AY8: 73.413584 | BB8: 70.794393 | BD8: 61.419069 | BF8: 64 | BH8: 59.080963 | BJ8: 53.911205 | BL8: 59.401709 | BN8: 65.706806 | BP8: 27.536232 | BR8: 28 | BT8: 28.571429 | BV8: 31.944444 | BX8: 53.846154
E9: Inflation | F9: التضخم | AQ9: 39.89288 | AS9: 60.970023 | AU9: 57.142857 | AW9: 83.870968 | AY9: 98.292683 | BB9: 96.261682 | BD9: 100 | BF9: 100 | BH9: 100 | BJ9: 100 | BL9: 100 | BN9: 100 | BP9: 100 | BR9: 100 | BT9: 100 | BV9: 100 | BX9: 98.076923
E10: Exchange rate | F10: سعر الصرف | AQ10: 82.783883 | AS10: 53.938894 | AU10: 30.952381 | AW10: 38.479263 | AY10: 27.560976 | BB10: 16.82243 | BD10: 44.789357 | BF10: 40 | BH10: 49.234136 | BJ10: 42.283298 | BL10: 41.239316 | BN10: _ | BP10: 55.072464 | BR10: 37 | BT10: 38.571429 | BV10: 19.444444 | BX10: 19.230769
E11: Reducing energy and water costs | F11: تخفيض أسعار الطاقة والمياه | AQ11: 69.230769 | AS11: 52.141058 | AU11: 16.666667 | AW11: 33.410138 | AY11: 26.585366 | BB11: 24.766355 | BD11: 45.011086 | BF11: 43 | BH11: 49.234136 | BJ11: 43.551797 | BL11: 50.42735 | BN11: 55.497382 | BP11: 53.623188 | BR11: 93 | BT11: 50 | BV11: 86.111111 | BX11: 100
E12: Customs | F12: المنظومة الجمركية | AQ12: 49.284049 | AS12: 52.075976 | AU12: 89.410641 | AW12: 85.055444 | AY12: 75.670563 | BB12: 22.897196 | BD12: 39.467849 | BF12: 31 | BH12: 32.38512 | BJ12: 33.403805 | BL12: 22.008547 | BN12: 27.486911 | BP12: 10 | BR12: 20 | BT12: 10 | BV12: 16.666667 | BX12: 23.076923
E13: Providing qualified labor | F13: توفير العمالة المؤهلة | AQ13: 52.896256 | AS13: 47.858942 | AU13: 29.761905 | AW13: 35.253456 | AY13: 30.731707 | BB13: 29.672897 | BD13: 31.042129 | BF13: 41 | BH13: 47.483589 | BJ13: 40.803383 | BL13: 49.145299 | BN13: 40.314136 | BP13: 14 | BR13: 28 | BT13: 18.571429 | BV13: 22.222222 | BX13: 34.615385
E14: Facilitating export procedures | F14: تسهيل اجراء التصدير | AQ14: 37.307231 | AS14: 33.302954 | AU14: 21.428571 | AW14: 27.18894 | AY14: 23.809811 | BB14: 20.327103 | BD14: 30.155211 | BF14: 27 | BH14: 19.693654 | BJ14: 17.547569 | BL14: 16.452991 | BN14: 24.86911 | BP14: 1 | BR14: 2 | BT14: 4.2857143 | BV14: 11.111111 | BX14: 21.153846
E15: Reducing power outages | F15: تخفيض مدة انقطاع الكهرباء | AQ15: 28.419856 | AS15: 29.42459 | AU15: 16.915092 | AW15: 44.560531 | AY15: 45.88349 | BB15: 48.130841 | BD15: 46.119734 | BF15: 64 | BH15: 43.544858 | BJ15: 52.43129 | BL15: 51.709402 | BN15: 58.376963 | BP15: 23 | BR15: 0 | BT15: 2.8571429 | BV15: 0 | BX15: 3.8461538
E16: Providing funding services | F16: الحصول على خدمات التمويل | AQ16: 22.53209 | AS16: 17.420007 | AU16: 9.5238095 | AW16: 14.995426 | AY16: 14.385094 | BB16: 13.317757 | BD16: 18.403548 | BF16: 18 | BH16: 19.474836 | BJ16: 21.141649 | BL16: 23.504274 | BN16: 26.701571 | BP16: 9 | BR16: 20 | BT16: 10 | BV16: 18.055556 | BX16: 13.461538
E17: Other | F17: أخــــــــــــــــــــــــــرى | AQ17: - | AS17: 10.403757 | AU17: 14.285714 | AW17: 22.119816 | AY17: 14.390244 | BB17: 9.3457944 | BD17: 6.2084257 | BF17: 13 | BH17: 18.380744 | BJ17: 7.6109937 | BL17: 10.042735 | BN17: 9.6858639 | BP17: 16 | BR17: 28 | BT17: 27.142857 | BV17: 23.611111 | BX17: 40.384615
E18: Providing information on domestic and foreign markets | F18: توافر المعلومات عن السوق المحلي والخارجي | BN18: _ | BP18: 15 | BR18: 13 | BT18: 11.428571 | BV18: 5.5555556 | BX18: 32.692308
E19: Giving priority to locally-manufactured products in government contracts | F19: تفضيل المنتج المحلي في التعاقدات الحكومية | BN19: _ | BP19: 3 | BR19: 0 | BT19: 1.4285714 | BV19: 0 | BX19: 0
E20: Avoid unfair completion from the State | F20: منع المنافسة غير العادلة من الدولة | BN20: _ | BP20: 15 | BR20: 22 | BT20: 17.142857 | BV20: 13.888889 | BX20: 17.307692
E21: Disclosure of future economic policies | F21: الافصاح عن توجهات السياسية الاقتصادية في المستقبل | BN21: _ | BP21: 57 | BR21: 76 | BT21: 42.857143 | BV21: 45.833333 | BX21: 67.307692
G24: Jan-Mar 2017 | I24: Apr-Jun 2017 | K24: Jul-Sep 2017 | M24: Oct-Dec 2017 | O24: Jan-Mar 2018 | Q24: Apr-Jun 2018 | S24: Jul-Sep 2018 | U24: Oct-Dec 2018 | W24: Jan-Mar 2019 | Y24: Apr-Jun 2019 | AA24: Jul-Sep 2019 | AC24: Oct-Dec 2019 | AE24: Jan-Mar 2020 | AG24: Apr-Jun 2020 | AI24: Jul-Sep 2020 | AK24: Oct-Dec 2020 | AM24: Jan-Mar 2021 | AO24: Apr-Jun 2021 | AQ24: Jul-Sep 2021 | AS24: Oct-Dec 2021 | AU24: Jan-Mar 2022 | AW24: Apr-Jun 2022 | AY24: Jul - Sep 2022 | BA24: Oct-Dec 2022 | BC24: Jan-Mar 2023 | BE24: أبريل - يونيو 2023 | BH24: Jul - Sep 2023 | BJ24: Oct-Dec 2023 | BL24: Jan-Mar 2024 | BN24: أبريل - يونيو 2024 | BP24: Jul - Sep 2024 | BR24: Oct-Dec 2024 | BT24: Jan-Mar 2025 | BV24: أبريل - يونيو 2025 | BX24: Jul - Sep 2025 | BZ24: Jul - Sep 2025
A25: الشركات الكبيرة | B25: الشركات الصغيرة والمتوسطة | C25: Large | D25: SMEs | E25: Priorities | F25: أولويات الحكومة | G25: الشركات الكبيرة | H25: الشركات الصغيرة والمتوسطة | I25: الشركات الكبيرة | J25: الشركات الصغيرة والمتوسطة | K25: الشركات الكبيرة | L25: الشركات الصغيرة والمتوسطة | M25: الشركات الكبيرة | N25: الشركات الصغيرة والمتوسطة | O25: الشركات الكبيرة | P25: الشركات الصغيرة والمتوسطة | Q25: الشركات الكبيرة | R25: الشركات الصغيرة والمتوسطة | S25: الشركات الكبيرة | T25: الشركات الصغيرة والمتوسطة | U25: الشركات الكبيرة | V25: الشركات الصغيرة والمتوسطة | W25: الشركات الكبيرة | X25: الشركات الصغيرة والمتوسطة | Y25: الشركات الكبيرة | Z25: الشركات الصغيرة والمتوسطة | AA25: الشركات الكبيرة | AB25: الشركات الصغيرة والمتوسطة | AC25: الشركات الكبيرة | AD25: الشركات الصغيرة والمتوسطة | AE25: الشركات الكبيرة | AF25: الشركات الصغيرة والمتوسطة | AG25: الشركات الكبيرة | AH25: الشركات الصغيرة والمتوسطة | AI25: الشركات الكبيرة | AJ25: الشركات الصغيرة والمتوسطة | AK25: الشركات الكبيرة | AL25: الشركات الصغيرة والمتوسطة | AM25: الشركات الكبيرة | AN25: الشركات الصغيرة والمتوسطة | AO25: الشركات الكبيرة | AP25: الشركات الصغيرة والمتوسطة | AQ25: الشركات الكبيرة | AR25: الشركات الصغيرة والمتوسطة | AS25: الشركات الكبيرة | AT25: الشركات الصغيرة والمتوسطة | AU25: الشركات الكبيرة | AV25: الشركات الصغيرة والمتوسطة | AW25: الشركات الكبيرة | AX25: الشركات الصغيرة والمتوسطة | AY25: الشركات الكبيرة | AZ25: الشركات الصغيرة والمتوسطة | BA25: الشركات الكبيرة | BB25: الشركات الصغيرة والمتوسطة | BC25: الشركات الكبيرة | BD25: الشركات الصغيرة والمتوسطة | BE25: الشركات الكبيرة | BF25: الشركات الصغيرة والمتوسطة | BH25: الشركات الكبيرة | BI25: الشركات الصغيرة والمتوسطة | BJ25: الشركات الكبيرة | BK25: الشركات الصغيرة والمتوسطة | BL25: الشركات الكبيرة | BM25: الشركات الصغيرة والمتوسطة | BN25: الشركات الكبيرة | BO25: الشركات الصغيرة والمتوسطة | BP25: الشركات الكبيرة | BQ25: الشركات الصغيرة والمتوسطة | BR25: الشركات الكبيرة | BS25: الشركات الصغيرة والمتوسطة | BT25: الشركات الكبيرة | BU25: الشركات الصغيرة والمتوسطة | BV25: الشركات الكبيرة | BW25: الشركات الصغيرة والمتوسطة | BX25: الشركات الكبيرة | BY25: الشركات الصغيرة والمتوسطة | BZ25: الشركات الكبيرة | CA25: الشركات الصغيرة والمتوسطة
E26: Economic policy consistency | F26: اتساق السياسات الاقتصادية | AQ26: 100 | AR26: 100 | AS26: 100 | AT26: 100 | AU26: 100 | AV26: 86.365633 | AW26: 100 | AX26: 99 | AY26: 100 | AZ26: 97.538462 | BA26: 100 | BB26: 100 | BC26: 93.82716 | BD26: 76.756757 | BE26: 92 | BF26: 84 | BH26: 83.13253 | BI26: 77.272727 | BJ26: 92.941176 | BK26: 85.824742 | BL26: 91.860465 | BM26: 85.602094 | BN26: 100 | BO26: 94.303797 | BP26: 23 | BQ26: 27 | BR26: 23 | BS26: 42 | BT26: 23.076923 | BU26: 36.842105 | BV26: 26.315789 | BW26: 26.415094 | BX26: 36.363636 | BY26: 25.581395
E27: Facilitating government procedures | F27: تسهيل الإجراءات الحكومية | AQ27: 72.692308 | AR27: 95.022624 | AS27: 76.326923 | AT27: 79.252101 | AU27: 83.333333 | AV27: 68.852602 | AW27: 61.627907 | AX27: 69 | AY27: 76.344086 | AZ27: 79.692308 | BA27: 76.54321 | BB27: 74.927954 | BC27: 69.135802 | BD27: 72.702703 | BE27: 78 | BF27: 66 | BH27: 72.289157 | BI27: 75.935829 | BJ27: 85.882353 | BK27: 66.752577 | BL27: 65.116279 | BM27: 71.989529 | BN27: 73.972603 | BO27: 75.949367 | BP27: 23 | BQ27: 29 | BR27: 54 | BS27: 77 | BT27: 76.923077 | BU27: 71.929825 | BV27: 10.526316 | BW27: 41.509434 | BX27: 72.727273 | BY27: 58.139535
E28: Transportation and logistics | F28: النقل واللوجستيات | AQ28: 82.692308 | AR28: 69.230769 | AS28: 82.051282 | AT28: 69.114911 | AU28: 54.761905 | AV28: 57.816993 | AW28: 48.837209 | AX28: 67 | AY28: 50.537634 | AZ28: 81.846154 | BA28: 51.851852 | BB28: 71.469741 | BC28: 85.185185 | BD28: 80.540541 | BE28: 67 | BF28: 79 | BH28: 80.722892 | BI28: 83.15508 | BJ28: 91.764706 | BK28: 85.824742 | BL28: 80.232558 | BM28: 80.104712 | BN28: 78.082192 | BO28: 85.443038 | BP28: 8 | BQ28: 2 | BR28: 0 | BS28: 2 | BT28: 0 | BU28: 1.754386 | BV28: 10.526316 | BW28: 7.5471698 | BX28: 9.0909091 | BY28: 9.3023256
E29: Taxation system | F29: المنظومة الضريبية | AQ29: 58.557692 | AR29: 86.425339 | AS29: 46.644231 | AT29: 72.634651 | AU29: 60.714286 | AV29: 63.814606 | AW29: 43.023256 | AX29: 75 | AY29: 49.462366 | AZ29: 56.615385 | BA29: 33.333333 | BB29: 63.976945 | BC29: 60.493827 | BD29: 65.675676 | BE29: 57 | BF29: 75 | BH29: 60.240964 | BI29: 71.390374 | BJ29: 64.705882 | BK29: 62.628866 | BL29: 46.511628 | BM29: 62.041885 | BN29: 63.013699 | BO29: 68.35443 | BP29: 38 | BQ29: 61 | BR29: 46 | BS29: 93 | BT29: 38.461538 | BU29: 43.859649 | BV29: 15.789474 | BW29: 45.283019 | BX29: 63.636364 | BY29: 62.790698
E30: Reducing government service fees | F30: تخفيض الرسوم المفروضة على الخدمات الحكومية | AQ30: 63.461538 | AR30: 85.972851 | AS30: 43.817308 | AT30: 71.786834 | AU30: 78.571429 | AV30: 72.211265 | AW30: 67.44186 | AX30: 75 | AY30: 58.337067 | AZ30: 75.692308 | BA30: 74.074074 | BB30: 70.028818 | BC30: 59.259259 | BD30: 61.891892 | BE30: 61 | BF30: 65 | BH30: 54.216867 | BI30: 60.160428 | BJ30: 56.470588 | BK30: 53.350515 | BL30: 51.162791 | BM30: 61.256545 | BN30: 56.164384 | BO30: 66.455696 | BP30: 31 | BQ30: 27 | BR30: 46 | BS30: 21 | BT30: 23.076923 | BU30: 29.824561 | BV30: 10.526316 | BW30: 39.622642 | BX30: 36.363636 | BY30: 55.813953
E31: Inflation | F31: التضخم | AQ31: 46.442308 | AR31: 38.461538 | AS31: 39.576923 | AT31: 65.830721 | AU31: 57.142857 | AV31: 59.016516 | AW31: 82.55814 | AX31: 83 | AY31: 83.870968 | AZ31: 100 | BA31: 86.419753 | BB31: 98.559078 | BC31: 100 | BD31: 100 | BE31: 100 | BF31: 100 | BH31: 100 | BI31: 100 | BJ31: 100 | BK31: 100 | BL31: 100 | BM31: 100 | BN31: 90.410959 | BO31: 100 | BP31: 100 | BQ31: 100 | BR31: 100 | BS31: 95 | BT31: 100 | BU31: 100 | BV31: 100 | BW31: 100 | BX31: 100 | BY31: 93.023256
E32: Exchange rate | F32: سعر الصرف | AQ32: 57.692308 | AR32: 88.687783 | AS32: 40.990385 | AT32: 56.955806 | AU32: 30.952381 | AV32: 37.904917 | AW32: 43.023256 | AX32: 37.356322 | AY32: 26.88172 | AZ32: 27.076923 | BA32: 13.580247 | BB32: 17.579251 | BC32: 41.975309 | BD32: 45.405405 | BE32: 45 | BF32: 39 | BH32: 46.987952 | BI32: 49.73262 | BJ32: 57.647059 | BK32: 38.917526 | BL32: 39.534884 | BM32: 41.623037 | BN32: 41.09589 | BO32: 50.632911 | BP32: 54 | BQ32: 55 | BR32: 46 | BS32: 33 | BT32: 46.153846 | BU32: 36.842105 | BV32: 15.789474 | BW32: 20.754717 | BX32: 18.181818 | BY32: 18.604651
E33: Reducing energy and water costs | F33: تخفيض أسعار الطاقة والمياه | AQ33: 53.846154 | AR33: 72.850679 | AS33: 43.817308 | AT33: 54.063449 | AU33: 16.666667 | AV33: 35.265967 | AW33: 18.604651 | AX33: 37.068966 | AY33: 17.204301 | AZ33: 28.615385 | BA33: 16.049383 | BB33: 26.801153 | BC33: 46.91358 | BD33: 44.594595 | BE33: 49 | BF33: 42 | BH33: 45.783133 | BI33: 50 | BJ33: 61.176471 | BK33: 39.690722 | BL33: 47.674419 | BM33: 51.04712 | BN33: 41.09589 | BO33: 57.594937 | BP33: 31 | BQ33: 59 | BR33: 54 | BS33: 100 | BT33: 30.769231 | BU33: 54.385965 | BV33: 57.894737 | BW33: 96.226415 | BX33: 81.818182 | BY33: 100
E34: Customs | F34: المنظومة الجمركية | AQ34: 61.639676 | AR34: 45.91629 | AS34: 26.502404 | AT34: 57.897275 | AU34: 89.410641 | AV34: 100 | AW34: 51.082321 | AX34: 100 | AY34: 60.378864 | AZ34: 77.641514 | BA34: 38.271605 | BB34: 19.308357 | BC34: 56.790123 | BD34: 35.675676 | BE34: 51 | BF34: 26 | BH34: 54.216867 | BI34: 27.540107 | BJ34: 57.647059 | BK34: 28.092784 | BL34: 24.418605 | BM34: 21.465969 | BN34: 42.465753 | BO34: 23.417722 | BP34: 0 | BQ34: 13 | BR34: 23 | BS34: 19 | BT34: 23.076923 | BU34: 7.0175439 | BV34: 15.789474 | BW34: 16.981132 | BX34: 54.545455 | BY34: 13.953488
E35: Providing qualified labor | F35: توفير العمالة المؤهلة | AQ35: 54.519231 | AR35: 52.567181 | AS35: 32.509615 | AT35: 51.298841 | AU35: 29.761905 | AV35: 34.030748 | AW35: 19.767442 | AX35: 39.08046 | AY35: 22.580645 | AZ35: 32.307692 | BA35: 27.160494 | BB35: 30.259366 | BC35: 23.45679 | BD35: 32.702703 | BE35: 41 | BF35: 41 | BH35: 44.578313 | BI35: 48.128342 | BJ35: 54.117647 | BK35: 37.886598 | BL35: 50 | BM35: 48.95288 | BN35: 45.205479 | BO35: 38.291139 | BP35: 23 | BQ35: 13 | BR35: 31 | BS35: 26 | BT35: 38.461538 | BU35: 14.035088 | BV35: 5.2631579 | BW35: 28.301887 | BX35: 9.0909091 | BY35: 39.534884
E36: Facilitating export procedures | F36: تسهيل اجراء التصدير | AQ36: 42.403846 | AR36: 36.199095 | AS36: 18.375 | AT36: 36.677116 | AU36: 21.428571 | AV36: 28.788544 | AW36: 19.767442 | AX36: 29.022989 | AY36: 19.354839 | AZ36: 24.513354 | BA36: 11.111111 | BB36: 22.478386 | BC36: 23.45679 | BD36: 31.621622 | BE36: 20 | BF36: 28 | BH36: 18.072289 | BI36: 20.053476 | BJ36: 22.352941 | BK36: 16.494845 | BL36: 15.116279 | BM36: 16.753927 | BN36: 16.438356 | BO36: 26.265823 | BP36: 8 | BQ36: 0 | BR36: 0 | BS36: 2 | BT36: 0 | BU36: 5.2631579 | BV36: 5.2631579 | BW36: 13.207547 | BX36: 27.272727 | BY36: 18.604651
E37: Reducing power outages | F37: تخفيض مدة انقطاع الكهرباء | AQ37: 30.288462 | AR37: 27.997738 | AS37: 15.548077 | AT37: 32.667733 | AU37: 16.915092 | AV37: 21.111599 | AW37: 45.752451 | AX37: 44.299488 | AY37: 43.010753 | AZ37: 45.569697 | BA37: 34.567901 | BB37: 51.29683 | BC37: 43.209877 | BD37: 46.756757 | BE37: 63 | BF37: 64 | BH37: 45.783133 | BI37: 43.048128 | BJ37: 55.294118 | BK37: 51.804124 | BL37: 37.209302 | BM37: 54.973822 | BN37: 67.123288 | BO37: 55.063291 | BP37: 23 | BQ37: 36 | BR37: 0 | BS37: 0 | BT37: 0 | BU37: 3.5087719 | BV37: 0 | BW37: 0 | BX37: 0 | BY37: 4.6511628
E38: Providing funding services | F38: الحصول على خدمات التمويل | AQ38: 24.230769 | AR38: 22.171946 | AS38: 7.0673077 | AT38: 19.749216 | AU38: 9.5238095 | AV38: 17.99284 | AW38: 9.3023256 | AX38: 16.428949 | AY38: 7.5268817 | AZ38: 16.027963 | BA38: 7.4074074 | BB38: 14.697406 | BC38: 13.580247 | BD38: 19.459459 | BE38: 22 | BF38: 18 | BH38: 19.277108 | BI38: 19.518717 | BJ38: 18.823529 | BK38: 21.649485 | BL38: 24.418605 | BM38: 23.298429 | BN38: 31.506849 | BO38: 25 | BP38: 8 | BQ38: 9 | BR38: 15 | BS38: 21 | BT38: 30.769231 | BU38: 5.2631579 | BV38: 0 | BW38: 24.528302 | BX38: 18.181818 | BY38: 11.627907
E39: Other | F39: أخــــــــــــــــــــــــــرى | AQ39: - | AR39: - | AS39: 8.974359 | AT39: 10.751254 | AU39: 14.285714 | AV39: 23.030835 | AW39: 9.3023256 | AX39: 25.287356 | AY39: 21.505376 | AZ39: 12 | BA39: 0 | BB39: 11.527378 | BC39: 4.9382716 | BD39: 6.4864865 | BE39: 14 | BF39: 12 | BH39: 13.253012 | BI39: 19.518717 | BJ39: 9.4117647 | BK39: 7.2164948 | BL39: 13.953488 | BM39: 9.1623037 | BN39: 2.739726 | BO39: 11.075949 | BP39: 38 | BQ39: 11 | BR39: 23 | BS39: 28 | BT39: 23.076923 | BU39: 28.070175 | BV39: 10.526316 | BW39: 28.301887 | BX39: 9.0909091 | BY39: 46.511628
E40: Providing information on domestic and foreign markets | F40: توافر المعلومات عن السوق المحلي والخارجي | BP40: 31 | BQ40: 11 | BR40: 8 | BS40: 14 | BT40: 15.384615 | BU40: 10.526316 | BV40: 10.526316 | BW40: 3.7735849 | BX40: 27.272727 | BY40: 32.55814
E41: Giving priority to locally-manufactured products in government contracts | F41: تفضيل المنتج المحلي في التعاقدات الحكومية | BP41: 0 | BQ41: 4 | BR41: 0 | BS41: 0 | BT41: 0 | BU41: 1.754386 | BV41: 0 | BW41: 0 | BX41: 0 | BY41: 0
E42: Avoid unfair completion from the State | F42: منع المنافسة غير العادلة من الدولة | BP42: 8 | BQ42: 16 | BR42: 8 | BS42: 26 | BT42: 15.384615 | BU42: 17.54386 | BV42: 10.526316 | BW42: 15.09434 | BX42: 0 | BY42: 20.930233
E43: Disclosure of future economic policies | F43: الافصاح عن توجهات السياسية الاقتصادية في المستقبل | BP43: 62 | BQ43: 55 | BR43: 31 | BS43: 86 | BT43: 23.076923 | BU43: 47.368421 | BV43: 42.105263 | BW43: 47.169811 | BX43: 36.363636 | BY43: 72.093023

Sheet Sect. Gov Priorities Fig 2-6 AR
B1: يناير - مارس 2017 | H1: أبريل - يونيو 2017 | N1: يوليو - سبتمبر 2017 | T1: أكتوبر-ديسمبر 2017 | Z1: يناير - مارس 2018 | AF1: أبريل - يونيو 2018 | AL1: يوليو - سبتمبر 2018 | AR1: أكتوبر-ديسمبر 2018 | AX1: يناير - مارس 2019 | BD1: أبريل - يونيو 2019 | BJ1: يوليو - سبتمبر 2019 | BP1: أكتوبر-ديسمبر 2019 | BV1: يناير - مارس 2020 | CB1: أبريل - يونيو 2020 | CH1: يوليو - سبتمبر 2020 | CN1: أكتوبر-ديسمبر 2020 | CT1: يناير - مارس 2021 | CZ1: أبريل - يونيو 2021 | DF1: يوليو - سبتمبر 2021 | DL1: أكتوبر-ديسمبر 2021 | DR1: يناير-مارس 2021 | DX1: أبريل - يونيو 2022 | ED1: يوليو - سبتمبر 2022 | EJ1: أكتوبر-ديسمبر 2022 | EP1: يناير -مارس 2022 | EV1: أبريل -يونيو 2023 | FB1: يوليو - سبتمبر 2023 | FH1: أكتوبر-ديسمبر 2023 | FN1: يناير -مارس 2024 | FT1: أبريل -يونيو 2024 | FZ1: يوليو - سبتمبر 2024 | GF1: أكتوبر-ديسمبر 2023 | GL1: يناير -مارس 2025 | GR1: أبريل -يونيو 2025 | GX1: يوليو - سبتمبر 2025 | HD1: يوليو - سبتمبر 2025
B5: قطاع الصناعة التحويلية | C5: قطاع التشييد والبناء | D5: قطاع السياحة | E5: قطاع النقل | F5: قطاع الاتصالات | G5: قطاع الخدمات المالية | H5: قطاع الصناعة التحويلية | I5: قطاع التشييد والبناء | J5: قطاع السياحة | K5: قطاع النقل | L5: قطاع الاتصالات | M5: قطاع الخدمات المالية | N5: قطاع الصناعة التحويلية | O5: قطاع التشييد والبناء | P5: قطاع السياحة | Q5: قطاع النقل | R5: قطاع الاتصالات | S5: قطاع الخدمات المالية | T5: قطاع الصناعة التحويلية | U5: قطاع التشييد والبناء | V5: قطاع السياحة | W5: قطاع النقل | X5: قطاع الاتصالات | Y5: قطاع الخدمات المالية | Z5: قطاع الصناعة التحويلية | AA5: قطاع التشييد والبناء | AB5: قطاع السياحة | AC5: قطاع النقل | AD5: قطاع الاتصالات | AE5: قطاع الخدمات المالية | AF5: قطاع الصناعة التحويلية | AG5: قطاع التشييد والبناء | AH5: قطاع السياحة | AI5: قطاع النقل | AJ5: قطاع الاتصالات | AK5: قطاع الخدمات المالية | AL5: قطاع الصناعة التحويلية | AM5: قطاع التشييد والبناء | AN5: قطاع السياحة | AO5: قطاع النقل | AP5: قطاع الاتصالات | AQ5: قطاع الخدمات المالية | AR5: قطاع الصناعة التحويلية | AS5: قطاع التشييد والبناء | AT5: قطاع السياحة | AU5: قطاع النقل | AV5: قطاع الاتصالات | AW5: قطاع الخدمات المالية | AX5: قطاع الصناعة التحويلية | AY5: قطاع التشييد والبناء | AZ5: قطاع السياحة | BA5: قطاع النقل | BB5: قطاع الاتصالات | BC5: قطاع الخدمات المالية | BD5: قطاع الصناعة التحويلية | BE5: قطاع التشييد والبناء | BF5: قطاع السياحة | BG5: قطاع النقل | BH5: قطاع الاتصالات | BI5: قطاع الخدمات المالية | BJ5: قطاع الصناعة التحويلية | BK5: قطاع التشييد والبناء | BL5: قطاع السياحة | BM5: قطاع النقل | BN5: قطاع الاتصالات | BO5: قطاع الخدمات المالية | BP5: قطاع الصناعة التحويلية | BQ5: قطاع التشييد والبناء | BR5: قطاع السياحة | BS5: قطاع النقل | BT5: قطاع الاتصالات | BU5: قطاع الخدمات المالية | BV5: قطاع الصناعة التحويلية | BW5: قطاع التشييد والبناء | BX5: قطاع السياحة | BY5: قطاع النقل | BZ5: قطاع الاتصالات | CA5: قطاع الخدمات المالية | CB5: قطاع الصناعة التحويلية | CC5: قطاع التشييد والبناء | CD5: قطاع السياحة | CE5: قطاع النقل | CF5: قطاع الاتصالات | CG5: قطاع الخدمات المالية | CH5: قطاع الصناعة التحويلية | CI5: قطاع التشييد والبناء | CJ5: قطاع السياحة | CK5: قطاع النقل | CL5: قطاع الاتصالات | CM5: قطاع الخدمات المالية | CN5: قطاع الصناعة التحويلية | CO5: قطاع التشييد والبناء | CP5: قطاع السياحة | CQ5: قطاع النقل | CR5: قطاع الاتصالات | CS5: قطاع الخدمات المالية | CT5: قطاع الصناعة التحويلية | CU5: قطاع التشييد والبناء | CV5: قطاع السياحة | CW5: قطاع النقل | CX5: قطاع الاتصالات | CY5: قطاع الخدمات المالية | CZ5: قطاع الصناعة التحويلية | DA5: قطاع التشييد والبناء | DB5: قطاع السياحة | DC5: قطاع النقل | DD5: قطاع الاتصالات | DE5: قطاع الخدمات المالية | DF5: قطاع الصناعة التحويلية | DG5: قطاع التشييد والبناء | DH5: قطاع السياحة | DI5: قطاع النقل | DJ5: قطاع الاتصالات | DK5: قطاع الخدمات المالية | DL5: قطاع الصناعة التحويلية | DM5: قطاع التشييد والبناء | DN5: قطاع السياحة | DO5: قطاع النقل | DP5: قطاع الاتصالات | DQ5: قطاع الخدمات المالية | DR5: قطاع الصناعة التحويلية | DS5: قطاع التشييد والبناء | DT5: قطاع السياحة | DU5: قطاع النقل | DV5: قطاع الاتصالات | DW5: قطاع الخدمات المالية | DX5: قطاع الصناعة التحويلية | DY5: قطاع التشييد والبناء | DZ5: قطاع السياحة | EA5: قطاع النقل | EB5: قطاع الاتصالات | EC5: قطاع الخدمات المالية | ED5: قطاع الصناعة التحويلية | EE5: قطاع التشييد والبناء | EF5: قطاع السياحة | EG5: قطاع النقل | EH5: قطاع الاتصالات | EI5: قطاع الخدمات المالية | EJ5: قطاع الصناعة التحويلية | EK5: قطاع التشييد والبناء | EL5: قطاع السياحة | EM5: قطاع النقل | EN5: قطاع الاتصالات | EO5: قطاع الخدمات المالية | EP5: قطاع الصناعة التحويلية | EQ5: قطاع التشييد والبناء | ER5: قطاع السياحة | ES5: قطاع النقل | ET5: قطاع الاتصالات | EU5: قطاع الخدمات المالية | EV5: قطاع الصناعة التحويلية | EW5: قطاع التشييد والبناء | EX5: قطاع السياحة | EY5: قطاع النقل | EZ5: قطاع الاتصالات | FA5: قطاع الخدمات المالية | FB5: قطاع الصناعة التحويلية | FC5: قطاع التشييد والبناء | FD5: قطاع السياحة | FE5: قطاع النقل | FF5: قطاع الاتصالات | FG5: قطاع الخدمات المالية | FH5: قطاع الصناعة التحويلية | FI5: قطاع التشييد والبناء | FJ5: قطاع السياحة | FK5: قطاع النقل | FL5: قطاع الاتصالات | FM5: قطاع الخدمات المالية | FN5: قطاع الصناعة التحويلية | FO5: قطاع التشييد والبناء | FP5: قطاع السياحة | FQ5: قطاع النقل | FR5: قطاع الاتصالات | FS5: قطاع الخدمات المالية | FT5: قطاع الصناعة التحويلية | FU5: قطاع التشييد والبناء | FV5: قطاع السياحة | FW5: قطاع النقل | FX5: قطاع الاتصالات | FY5: قطاع الخدمات المالية | FZ5: قطاع الصناعة التحويلية | GA5: قطاع التشييد والبناء | GB5: قطاع السياحة | GC5: قطاع النقل | GD5: قطاع الاتصالات | GE5: قطاع الخدمات المالية | GF5: قطاع الصناعة التحويلية | GG5: قطاع التشييد والبناء | GH5: قطاع السياحة | GI5: قطاع النقل | GJ5: قطاع الاتصالات | GK5: قطاع الخدمات المالية | GL5: قطاع الصناعة التحويلية | GM5: قطاع التشييد والبناء | GN5: قطاع السياحة | GO5: قطاع النقل | GP5: قطاع الاتصالات | GQ5: قطاع الخدمات المالية | GR5: قطاع الصناعة التحويلية | GS5: قطاع التشييد والبناء | GT5: قطاع السياحة | GU5: قطاع النقل | GV5: قطاع الاتصالات | GW5: قطاع الخدمات المالية | GX5: قطاع الصناعة التحويلية | GY5: قطاع التشييد والبناء | GZ5: قطاع السياحة | HA5: قطاع النقل | HB5: قطاع الاتصالات | HC5: قطاع الخدمات المالية | HD5: قطاع الصناعة التحويلية | HE5: قطاع التشييد والبناء | HF5: قطاع السياحة | HG5: قطاع النقل | HH5: قطاع الاتصالات | HI5: قطاع الخدمات المالية
A6: اتساق السياسات الاقتصادية | DL6: 100 | DM6: 97.916667 | DN6: 100 | DO6: 100 | DP6: 100 | DQ6: 85.454545 | DR6: 100 | DS6: 100 | DT6: 100 | DU6: 96.09375 | DV6: 100 | DW6: 80.882353 | DX6: 100 | DY6: 98.148148 | DZ6: 100 | EA6: 97.222222 | EB6: 100 | EC6: 88.333333 | ED6: 100 | EE6: 92.592593 | EF6: 100 | EG6: 78.04878 | EH6: 100 | EI6: 71.666667 | EJ6: 100 | EK6: 100 | EL6: 100 | EM6: 78.26087 | EN6: 100 | EO6: 91.803279 | EP6: 79.72973 | EQ6: 79.62963 | ER6: 95 | ES6: 50 | ET6: 100 | EU6: 77.966102 | EV6: 82 | EW6: 88 | EX6: 100 | EY6: 71 | EZ6: 100 | FA6: 84 | FB6: 70.940171 | FC6: 83.928571 | FD6: 87.096774 | FE6: 81.25 | FF6: 96 | FG6: 87.301587 | FH6: 86.075949 | FI6: 72.727273 | FJ6: 100 | FK6: 66.666667 | FL6: 100 | FM6: 100 | FN6: 84.745763 | FO6: 70.909091 | FP6: 94.871795 | FQ6: 91.666667 | FR6: 90 | FS6: 93.650794 | FT6: 91.089109 | FU6: 73.584906 | FV6: 100 | FW6: 100 | FX6: 86.206897 | FY6: 94.117647 | FZ6: 14 | GA6: 9 | GB6: 13 | GC6: 33 | GD6: 0 | GE6: 75 | GF6: 28 | GG6: 20 | GH6: 14 | GI6: 0 | GJ6: 17 | GK6: 64 | GL6: 31.578947 | GM6: 45.454545 | GN6: 11.111111 | GO6: 12.5 | GP6: 0 | GQ6: 41.666667 | GR6: 21.052632 | GS6: 36.363636 | GT6: 0 | GU6: 0 | GV6: 0 | GW6: 50 | GX6: 25.806452 | GY6: 30 | GZ6: 28.571429 | HA6: 0 | HB6: 40 | HC6: 0
A7: تسهيل الإجراءات الحكومية | DL7: 90.306122 | DM7: 100 | DN7: 85 | DO7: 46.682099 | DP7: 88.479263 | DQ7: 21.818182 | DR7: 92.237443 | DS7: 100 | DT7: 100 | DU7: 42.1875 | DV7: 100 | DW7: 11.764706 | DX7: 81.447964 | DY7: 100 | DZ7: 72.5 | EA7: 19.444444 | EB7: 78.125 | EC7: 3.3333333 | ED7: 100 | EE7: 100 | EF7: 60 | EG7: 26.829268 | EH7: 68.75 | EI7: 10 | EJ7: 91.121495 | EK7: 100 | EL7: 88.888889 | EM7: 15.217391 | EN7: 93.75 | EO7: 6.557377 | EP7: 82.882883 | EQ7: 75.925926 | ER7: 72.5 | ES7: 83.333333 | ET7: 87.5 | EU7: 5.0847458 | EV7: 79 | EW7: 89 | EX7: 60 | EY7: 73 | EZ7: 75 | FA7: 0 | FB7: 91.025641 | FC7: 83.928571 | FD7: 90.322581 | FE7: 79.166667 | FF7: 72 | FG7: 0 | FH7: 78.059072 | FI7: 78.181818 | FJ7: 75 | FK7: 31.25 | FL7: 100 | FM7: 42.1875 | FN7: 86.016949 | FO7: 92.727273 | FP7: 69.230769 | FQ7: 16.666667 | FR7: 90 | FS7: 23.809524 | FT7: 87.623762 | FU7: 77.358491 | FV7: 54.285714 | FW7: 40 | FX7: 75.862069 | FY7: 37.254902 | FZ7: 36 | GA7: 18 | GB7: 13 | GC7: 0 | GD7: 60 | GE7: 0 | GF7: 55 | GG7: 70 | GH7: 57 | GI7: 20 | GJ7: 50 | GK7: 57 | GL7: 71.052632 | GM7: 63.636364 | GN7: 33.333333 | GO7: 62.5 | GP7: 57.142857 | GQ7: 41.666667 | GR7: 36.842105 | GS7: 45.454545 | GT7: 28.571429 | GU7: 0 | GV7: 25 | GW7: 14.285714 | GX7: 58.064516 | GY7: 30 | GZ7: 42.857143 | HA7: 71.428571 | HB7: 60 | HC7: 6.6666667
A8: النقل واللوجستيات | DL8: 82.31273 | DM8: 91.666667 | DN8: 37.5 | DO8: 11.111111 | DP8: 74.193548 | DQ8: 69.090909 | DR8: 78.538813 | DS8: 80.701754 | DT8: 0 | DU8: 51.5625 | DV8: 0 | DW8: 69.117647 | DX8: 71.597463 | DY8: 88.888889 | DZ8: 5 | EA8: 66.666667 | EB8: 0 | EC8: 76.666667 | ED8: 79.812207 | EE8: 88.888889 | EF8: 10 | EG8: 68.292683 | EH8: 9.375 | EI8: 100 | EJ8: 73.364486 | EK8: 96.296296 | EL8: 0 | EM8: 52.173913 | EN8: 18.75 | EO8: 83.606557 | EP8: 86.936937 | EQ8: 96.296296 | ER8: 40 | ES8: 64.583333 | ET8: 56.25 | EU8: 96.610169 | EV8: 87 | EW8: 79 | EX8: 5 | EY8: 76 | EZ8: 34 | FA8: 95 | FB8: 89.316239 | FC8: 94.642857 | FD8: 19.354839 | FE8: 83.333333 | FF8: 28 | FG8: 100 | FH8: 90.7173 | FI8: 98.181818 | FJ8: 45 | FK8: 66.666667 | FL8: 87.5 | FM8: 100 | FN8: 77.118644 | FO8: 89.090909 | FP8: 41.025641 | FQ8: 100 | FR8: 56.666667 | FS8: 100 | FT8: 87.623762 | FU8: 92.45283 | FV8: 22.857143 | FW8: 70 | FX8: 62.068966 | FY8: 92.156863 | FZ8: 0 | GA8: 0 | GB8: 0 | GC8: 17 | GD8: 20 | GE8: 0 | GF8: 3 | GG8: 0 | GH8: 0 | GI8: 0 | GJ8: 0 | GK8: 0 | GL8: 2.6315789 | GM8: 0 | GN8: 0 | GO8: 0 | GP8: 0 | GQ8: 0 | GR8: 5.2631579 | GS8: 0 | GT8: 28.571429 | GU8: 22.222222 | GV8: 0 | GW8: 0 | GX8: 6.4516129 | GY8: 10 | GZ8: 14.285714 | HA8: 0 | HB8: 20 | HC8: 0
A9: المنظومة الضريبية | DL9: 78.091564 | DM9: 97.916667 | DN9: 55 | DO9: 46.682099 | DP9: 46.34628 | DQ9: 21.818182 | DR9: 71.232877 | DS9: 82.45614 | DT9: 60 | DU9: 46.875 | DV9: 50 | DW9: 79.411765 | DX9: 69.230769 | DY9: 83.333333 | DZ9: 52.5 | EA9: 36.111111 | EB9: 43.75 | EC9: 90 | ED9: 48.356808 | EE9: 61.111111 | EF9: 67.5 | EG9: 0 | EH9: 50 | EI9: 85 | EJ9: 54.205607 | EK9: 83.333333 | EL9: 44.444444 | EM9: 15.217391 | EN9: 34.375 | EO9: 88.52459 | EP9: 61.711712 | EQ9: 64.814815 | ER9: 60 | ES9: 54.166667 | ET9: 43.75 | EU9: 94.915254 | EV9: 63 | EW9: 68 | EX9: 95 | EY9: 64 | EZ9: 63 | FA9: 94 | FB9: 60.25641 | FC9: 73.214286 | FD9: 70.967742 | FE9: 70.833333 | FF9: 68 | FG9: 98.412698 | FH9: 64.135021 | FI9: 41.818182 | FJ9: 80 | FK9: 25 | FL9: 87.5 | FM9: 79.6875 | FN9: 55.084746 | FO9: 63.636364 | FP9: 43.589744 | FQ9: 25 | FR9: 93.333333 | FS9: 87.301587 | FT9: 66.336634 | FU9: 37.735849 | FV9: 57.142857 | FW9: 30 | FX9: 93.103448 | FY9: 96.078431 | FZ9: 39 | GA9: 18 | GB9: 88 | GC9: 17 | GD9: 100 | GE9: 83 | GF9: 100 | GG9: 30 | GH9: 57 | GI9: 20 | GJ9: 100 | GK9: 14 | GL9: 23.684211 | GM9: 18.181818 | GN9: 55.555556 | GO9: 12.5 | GP9: 100 | GQ9: 50 | GR9: 39.473684 | GS9: 18.181818 | GT9: 100 | GU9: 0 | GV9: 75 | GW9: 0 | GX9: 38.709677 | GY9: 20 | GZ9: 28.571429 | HA9: 0 | HB9: 100 | HC9: 86.666667
A10: تخفيض الرسوم المفروضة على الخدمات الحكومية | DL10: 77.036273 | DM10: 83.333333 | DN10: 12.5 | DO10: 8.3333333 | DP10: 46.34628 | DQ10: 100 | DR10: 89.954338 | DS10: 91.22807 | DT10: 77.5 | DU10: 79.6875 | DV10: 56.25 | DW10: 51.470588 | DX10: 84.615385 | DY10: 94.444444 | DZ10: 45 | EA10: 69.444444 | EB10: 28.125 | EC10: 51.666667 | ED10: 83.997232 | EE10: 88.888889 | EF10: 20 | EG10: 48.780488 | EH10: 34.375 | EI10: 60 | EJ10: 86.448598 | EK10: 96.296296 | EL10: 52.777778 | EM10: 19.565217 | EN10: 46.875 | EO10: 37.704918 | EP10: 67.567568 | EQ10: 81.481481 | ER10: 72.5 | ES10: 64.583333 | ET10: 63 | EU10: 5.0847458 | EV10: 73 | EW10: 70 | EX10: 60 | EY10: 69 | EZ10: 44 | FA10: 30 | FB10: 66.666667 | FC10: 83.928571 | FD10: 48.387097 | FE10: 81.25 | FF10: 32 | FG10: 7.9365079 | FH10: 62.869198 | FI10: 67.272727 | FJ10: 52.5 | FK10: 35.416667 | FL10: 78.125 | FM10: 9.375 | FN10: 73.728814 | FO10: 65.454545 | FP10: 61.538462 | FQ10: 16.666667 | FR10: 70 | FS10: 23.809524 | FT10: 74.752475 | FU10: 54.716981 | FV10: 31.428571 | FW10: 50 | FX10: 79.310345 | FY10: 33.333333 | FZ10: 44 | GA10: 9 | GB10: 0 | GC10: 33 | GD10: 0 | GE10: 0 | GF10: 24 | GG10: 20 | GH10: 29 | GI10: 30 | GJ10: 17 | GK10: 0 | GL10: 21.052632 | GM10: 0 | GN10: 11.111111 | GO10: 100 | GP10: 0 | GQ10: 25 | GR10: 26.315789 | GS10: 9.0909091 | GT10: 28.571429 | GU10: 66.666667 | GV10: 25 | GW10: 21.428571 | GX10: 29.032258 | GY10: 20 | GZ10: 42.857143 | HA10: 100 | HB10: 0 | HC10: 46.666667
A11: التضخم | DL11: 68.066296 | DM11: 95.833333 | DN11: 7.5 | DO11: 63.020833 | DP11: 21.066491 | DQ11: 50.909091 | DR11: 75.342466 | DS11: 85.964912 | DT11: 50 | DU11: 42.1875 | DV11: 50 | DW11: 38.235294 | DX11: 86.877828 | DY11: 92.592593 | DZ11: 77.5 | EA11: 100 | EB11: 65.625 | EC11: 56.666667 | ED11: 95.774648 | EE11: 92.592593 | EF11: 80 | EG11: 100 | EH11: 75 | EI11: 86.666667 | EJ11: 97.196262 | EK11: 100 | EL11: 58.333333 | EM11: 100 | EN11: 68.75 | EO11: 100 | EP11: 100 | EQ11: 100 | ER11: 100 | ES11: 95.833333 | ET11: 93.75 | EU11: 100 | EV11: 100 | EW11: 100 | EX11: 100 | EY11: 87 | EZ11: 100 | FA11: 100 | FB11: 100 | FC11: 100 | FD11: 100 | FE11: 100 | FF11: 100 | FG11: 100 | FH11: 100 | FI11: 100 | FJ11: 95 | FK11: 100 | FL11: 96.875 | FM11: 100 | FN11: 100 | FO11: 100 | FP11: 100 | FQ11: 100 | FR11: 100 | FS11: 95.238095 | FT11: 100 | FU11: 100 | FV11: 88.571429 | FW11: 80 | FX11: 100 | FY11: 68.627451 | FZ11: 100 | GA11: 100 | GB11: 100 | GC11: 100 | GD11: 80 | GE11: 33 | GF11: 86 | GG11: 100 | GH11: 71 | GI11: 90 | GJ11: 33 | GK11: 21 | GL11: 100 | GM11: 100 | GN11: 100 | GO11: 25 | GP11: 71.428571 | GQ11: 41.666667 | GR11: 89.473684 | GS11: 100 | GT11: 85.714286 | GU11: 66.666667 | GV11: 50 | GW11: 92.857143 | GX11: 83.870968 | GY11: 100 | GZ11: 100 | HA11: 85.714286 | HB11: 40 | HC11: 0
A12: سعر الصرف | DL12: 67.346939 | DM12: 58.333333 | DN12: 15 | DO12: 11.670525 | DP12: 46.34628 | DQ12: 14.545455 | DR12: 43.835616 | DS12: 82.45614 | DT12: 70 | DU12: 9.375 | DV12: 28.125 | DW12: 0 | DX12: 46.153846 | DY12: 68.518519 | DZ12: 50 | EA12: 22.222222 | EB12: 0 | EC12: 0 | ED12: 24.413146 | EE12: 51.851852 | EF12: 77.5 | EG12: 0 | EH12: 6.25 | EI12: 0 | EJ12: 22.897196 | EK12: 42.592593 | EL12: 0 | EM12: 0 | EN12: 0 | EO12: 0 | EP12: 48.648649 | EQ12: 68.518519 | ER12: 15 | ES12: 100 | ET12: 0 | EU12: 5.0847458 | EV12: 47 | EW12: 61 | EX12: 3 | EY12: 85 | EZ12: 0 | FA12: 0 | FB12: 55.128205 | FC12: 71.428571 | FD12: 22.580645 | FE12: 95.833333 | FF12: 12 | FG12: 0 | FH12: 54.008439 | FI12: 81.818182 | FJ12: 17.5 | FK12: 16.666667 | FL12: 37.5 | FM12: 0 | FN12: 41.525424 | FO12: 83.636364 | FP12: 51.282051 | FQ12: 0 | FR12: 60 | FS12: 17.460317 | FT12: 57.920792 | FU12: 66.037736 | FV12: 20 | FW12: 7.5 | FX12: 62.068966 | FY12: 19.607843 | FZ12: 61 | GA12: 91 | GB12: 0 | GC12: 67 | GD12: 0 | GE12: 17 | GF12: 48 | GG12: 40 | GH12: 0 | GI12: 10 | GJ12: 0 | GK12: 7 | GL12: 28.947368 | GM12: 36.363636 | GN12: 22.222222 | GO12: 25 | GP12: 71.428571 | GQ12: 25 | GR12: 18.421053 | GS12: 36.363636 | GT12: 0 | GU12: 22.222222 | GV12: 25 | GW12: 0 | GX12: 16.129032 | GY12: 30 | GZ12: 0 | HA12: 14.285714 | HB12: 20 | HC12: 0
A13: تخفيض أسعار الطاقة والمياة | DL13: 65.306122 | DM13: 75 | DN13: 30 | DO13: 35.011574 | DP13: 16.853193 | DQ13: 21.818182 | DR13: 50.684932 | DS13: 73.684211 | DT13: 0 | DU13: 7.03125 | DV13: 0 | DW13: 7.3529412 | DX13: 46.153846 | DY13: 62.962963 | DZ13: 5 | EA13: 13.888889 | EB13: 0 | EC13: 3.3333333 | ED13: 30.985915 | EE13: 40.740741 | EF13: 10 | EG13: 29.268293 | EH13: 9.375 | EI13: 3.3333333 | EJ13: 29.439252 | EK13: 50 | EL13: 0 | EM13: 28.26087 | EN13: 0 | EO13: 4.9180328 | EP13: 53.603604 | EQ13: 62.962963 | ER13: 15 | ES13: 91.666667 | ET13: 0 | EU13: 0 | EV13: 55 | EW13: 59 | EX13: 0 | EY13: 80 | EZ13: 0 | FA13: 0 | FB13: 57.692308 | FC13: 69.642857 | FD13: 19.354839 | FE13: 89.583333 | FF13: 8 | FG13: 0 | FH13: 52.320675 | FI13: 78.181818 | FJ13: 12.5 | FK13: 33.333333 | FL13: 34.375 | FM13: 10.9375 | FN13: 58.898305 | FO13: 80 | FP13: 43.589744 | FQ13: 16.666667 | FR13: 46.666667 | FS13: 22.222222 | FT13: 65.346535 | FU13: 69.811321 | FV13: 22.857143 | FW13: 22.5 | FX13: 51.724138 | FY13: 21.568627 | FZ13: 47 | GA13: 27 | GB13: 88 | GC13: 100 | GD13: 40 | GE13: 17 | GF13: 93 | GG13: 20 | GH13: 100 | GI13: 100 | GJ13: 33 | GK13: 14 | GL13: 52.631579 | GM13: 9.0909091 | GN13: 66.666667 | GO13: 87.5 | GP13: 0 | GQ13: 8.3333333 | GR13: 100 | GS13: 27.272727 | GT13: 100 | GU13: 100 | GV13: 100 | GW13: 7.1428571 | GX13: 100 | GY13: 60 | GZ13: 100 | HA13: 85.714286 | HB13: 40 | HC13: 0
A14: المنظومة الجمركية | DL14: 60.15161 | DM14: 91.666667 | DN14: 72.5 | DO14: 2.7777778 | DP14: 42.132982 | DQ14: 16.363636 | DR14: 88.904036 | DS14: 63.157895 | DT14: - | DU14: 100 | DV14: 65.625 | DW14: - | DX14: 62.263939 | DY14: - | DZ14: - | EA14: 18.75 | EB14: 50 | EC14: - | ED14: 59.404043 | EE14: _ | EF14: _ | EG14: 0 | EH14: 64 | EI14: _ | EJ14: 33.64486 | EK14: 14.814815 | EL14: 0 | EM14: 8.6956522 | EN14: 43.75 | EO14: 0 | EP14: 52.702703 | EQ14: 35.185185 | ER14: 0 | ES14: 62.5 | ET14: 37.5 | EU14: 0 | EV14: 41 | EW14: 5 | EX14: 3 | EY14: 100 | EZ14: 47 | FA14: 0 | FB14: 46.581197 | FC14: 7.1428571 | FD14: 9.6774194 | FE14: 54.166667 | FF14: 24 | FG14: 0 | FH14: 44.303797 | FI14: 5.4545455 | FJ14: 60 | FK14: 12.5 | FL14: 62.5 | FM14: 0 | FN14: 33.474576 | FO14: 7.2727273 | FP14: 10.25641 | FQ14: 0 | FR14: 43.333333 | FS14: 4.7619048 | FT14: 35.643564 | FU14: 0 | FV14: 17.142857 | FW14: 0 | FX14: 65.517241 | FY14: 15.686275 | FZ14: 8 | GA14: 0 | GB14: 0 | GC14: 0 | GD14: 80 | GE14: 0 | GF14: 28 | GG14: 0 | GH14: 14 | GI14: 0 | GJ14: 33 | GK14: 0 | GL14: 10.526316 | GM14: 0 | GN14: 0 | GO14: 37.5 | GP14: 0 | GQ14: 0 | GR14: 13.157895 | GS14: 9.0909091 | GT14: 14.285714 | GU14: 55.555556 | GV14: 0 | GW14: 0 | GX14: 32.258065 | GY14: 0 | GZ14: 0 | HA14: 14.285714 | HB14: 20 | HC14: 0
A15: توفير العمالة المؤهلة | DL15: 49.789172 | DM15: 50.739645 | DN15: 0 | DO15: 74.691358 | DP15: 33.706386 | DQ15: - | DR15: 53.834318 | DS15: 63.157895 | DT15: 5 | DU15: 7.03125 | DV15: 28.125 | DW15: 0 | DX15: 49.321267 | DY15: 51.851852 | DZ15: 5 | EA15: 0 | EB15: 43.75 | EC15: 0 | ED15: 37.558685 | EE15: 38.888889 | EF15: 20 | EG15: 0 | EH15: 40.625 | EI15: 6.6666667 | EJ15: 40.654206 | EK15: 25.925926 | EL15: 22.222222 | EM15: 0 | EN15: 43.75 | EO15: 6.557377 | EP15: 36.936937 | EQ15: 42.592593 | ER15: 12.5 | ES15: 47.916667 | ET15: 15.625 | EU15: 3.3898305 | EV15: 51 | EW15: 54 | EX15: 0 | EY15: 64 | EZ15: 25 | FA15: 0 | FB15: 57.264957 | FC15: 55.357143 | FD15: 16.129032 | FE15: 70.833333 | FF15: 52 | FG15: 0 | FH15: 51.054852 | FI15: 32.727273 | FJ15: 42.5 | FK15: 8.3333333 | FL15: 81.25 | FM15: 10.9375 | FN15: 60.169492 | FO15: 50.909091 | FP15: 46.153846 | FQ15: 0 | FR15: 86.666667 | FS15: 25.396825 | FT15: 47.029703 | FU15: 26.415094 | FV15: 40 | FW15: 0 | FX15: 65.517241 | FY15: 23.529412 | FZ15: 19 | GA15: 9 | GB15: 13 | GC15: 0 | GD15: 20 | GE15: 0 | GF15: 21 | GG15: 0 | GH15: 29 | GI15: 0 | GJ15: 67 | GK15: 21 | GL15: 18.421053 | GM15: 0 | GN15: 22.222222 | GO15: 0 | GP15: 28.571429 | GQ15: 16.666667 | GR15: 23.684211 | GS15: 9.0909091 | GT15: 28.571429 | GU15: 0 | GV15: 100 | GW15: 0 | GX15: 41.935484 | GY15: 10 | GZ15: 42.857143 | HA15: 0 | HB15: 20 | HC15: 0
A16: تسهيل اجراء التصدير | DL16: 37.462845 | DM16: 60.404339 | DN16: 0 | DO16: 0 | DP16: 12.639895 | DQ16: 21.818182 | DR16: 40.182648 | DS16: 77.192982 | DT16: 0 | DU16: 14.0625 | DV16: 0 | DW16: 0 | DX16: 34.38914 | DY16: 61.111111 | DZ16: 0 | EA16: 8.3333333 | EB16: 12.5 | EC16: 3.3333333 | ED16: 24.413146 | EE16: 38.888889 | EF16: 0 | EG16: 24.390244 | EH16: 21.875 | EI16: 11.377778 | EJ16: 24.766355 | EK16: 48.148148 | EL16: 0 | EM16: 0 | EN16: 21.875 | EO16: 1.6393443 | EP16: 38.288288 | EQ16: 37.037037 | ER16: 22.5 | ES16: 35.416667 | ET16: 0 | EU16: 8.4745763 | EV16: 37 | EW16: 41 | EX16: 0 | EY16: 31 | EZ16: 0 | FA16: 0 | FB16: 23.076923 | FC16: 30.357143 | FD16: 0 | FE16: 39.583333 | FF16: 0 | FG16: 0 | FH16: 23.206751 | FI16: 25.454545 | FJ16: 0 | FK16: 14.583333 | FL16: 21.875 | FM16: 0 | FN16: 19.915254 | FO16: 20 | FP16: 0 | FQ16: 0 | FR16: 16.666667 | FS16: 22.222222 | FT16: 25.742574 | FU16: 16.981132 | FV16: 0 | FW16: 10 | FX16: 44.827586 | FY16: 33.333333 | FZ16: 3 | GA16: 0 | GB16: 0 | GC16: 0 | GD16: 0 | GE16: 0 | GF16: 3 | GG16: 0 | GH16: 0 | GI16: 0 | GJ16: 0 | GK16: 0 | GL16: 7.8947368 | GM16: 0 | GN16: 0 | GO16: 0 | GP16: 0 | GQ16: 0 | GR16: 21.052632 | GS16: 0 | GT16: 0 | GU16: 0 | GV16: 0 | GW16: 0 | GX16: 35.483871 | GY16: 0 | GZ16: 0 | HA16: 0 | HB16: 0 | HC16: 0
A17: تخفيض مدة انقطاع الكهرباء | DL17: 27.965222 | DM17: 77.083333 | DN17: 0 | DO17: 56.018519 | DP17: 37.919684 | DQ17: 12.727273 | DR17: 29.680365 | DS17: 63.157895 | DT17: 0 | DU17: 0 | DV17: 0 | DW17: 0 | DX17: 45.701357 | DY17: 60.493827 | DZ17: 27.5 | EA17: 33.333333 | EB17: 9.375 | EC17: 60 | ED17: 37.386051 | EE17: 46.296296 | EF17: 42.5 | EG17: 39.02439 | EH17: 21.875 | EI17: 71.666667 | EJ17: 47.196262 | EK17: 42.592593 | EL17: 13.888889 | EM17: 67.391304 | EN17: 28.125 | EO17: 60.655738 | EP17: 50.45045 | EQ17: 42.592593 | ER17: 50 | ES17: 52.083333 | ET17: 65.625 | EU17: 11.864407 | EV17: 71 | EW17: 46 | EX17: 33 | EY17: 29 | EZ17: 69 | FA17: 94 | FB17: 45.299145 | FC17: 53.571429 | FD17: 9.6774194 | FE17: 47.916667 | FF17: 12 | FG17: 53.968254 | FH17: 52.320675 | FI17: 69.090909 | FJ17: 67.5 | FK17: 31.25 | FL17: 56.25 | FM17: 40.625 | FN17: 53.389831 | FO17: 81.818182 | FP17: 38.461538 | FQ17: 8.3333333 | FR17: 46.666667 | FS17: 60.31746 | FT17: 50 | FU17: 30.188679 | FV17: 51.428571 | FW17: 40 | FX17: 72.413793 | FY17: 100 | FZ17: 25 | GA17: 27 | GB17: 13 | GC17: 67 | GD17: 0 | GE17: 50 | GF17: 0 | GG17: 0 | GH17: 0 | GI17: 0 | GJ17: 0 | GK17: 0 | GL17: 2.6315789 | GM17: 0 | GN17: 0 | GO17: 0 | GP17: 0 | GQ17: 8.3333333 | GR17: 0 | GS17: 0 | GT17: 0 | GU17: 0 | GV17: 0 | GW17: 0 | GX17: 6.4516129 | GY17: 0 | GZ17: 0 | HA17: 0 | HB17: 0 | HC17: 0
A18: الخدمات المالية والائتمانية | DL18: 23.216411 | DM18: 39.583333 | DN18: 0 | DO18: 4.6682099 | DP18: 12.639895 | DQ18: 0 | DR18: 19.178082 | DS18: 54.385965 | DT18: 0 | DU18: 0 | DV18: 31.25 | DW18: 0 | DX18: 16.289593 | DY18: 45.101907 | DZ18: 0 | EA18: 8.3333333 | EB18: 12.5 | EC18: 0 | ED18: 17.370892 | EE18: 27.777778 | EF18: 0 | EG18: 4.8780488 | EH18: 12.5 | EI18: 0 | EJ18: 15.88785 | EK18: 24.074074 | EL18: 0 | EM18: 8.6956522 | EN18: 18.75 | EO18: 0 | EP18: 22.072072 | EQ18: 20.37037 | ER18: 12.5 | ES18: 20.833333 | ET18: 18.75 | EU18: 3.3898305 | EV18: 25 | EW18: 20 | EX18: 0 | EY18: 20 | EZ18: 18.75 | FA18: 0 | FB18: 21.367521 | FC18: 26.785714 | FD18: 0 | FE18: 27.083333 | FF18: 36 | FG18: 3.1746032 | FH18: 22.362869 | FI18: 5.4545455 | FJ18: 2.5 | FK18: 33.333333 | FL18: 59.375 | FM18: 12.5 | FN18: 21.186441 | FO18: 32.727273 | FP18: 25.641026 | FQ18: 16.666667 | FR18: 43.333333 | FS18: 17.460317 | FT18: 23.267327 | FU18: 7.5471698 | FV18: 22.857143 | FW18: 20 | FX18: 65.517241 | FY18: 31.372549 | FZ18: 0 | GA18: 0 | GB18: 25 | GC18: 17 | GD18: 60 | GE18: 0 | GF18: 21 | GG18: 0 | GH18: 43 | GI18: 0 | GJ18: 33 | GK18: 0 | GL18: 18.421053 | GM18: 0 | GN18: 0 | GO18: 0 | GP18: 0 | GQ18: 0 | GR18: 23.684211 | GS18: 0 | GT18: 0 | GU18: 11.111111 | GV18: 75 | GW18: 0 | GX18: 9.6774194 | GY18: 0 | GZ18: 0 | HA18: 14.285714 | HB18: 60 | HC18: 0
A19: أخــــــــــــــــــــــــــرى | DL19: 7.1428571 | DM19: - | DN19: 10 | DO19: 28.009259 | DP19: - | DQ19: 21.818182 | DR19: 12.785388 | DS19: 0 | DT19: 0 | DU19: 28.125 | DV19: 0 | DW19: 100 | DX19: 7.239819 | DY19: 0 | DZ19: 0 | EA19: 55.555556 | EB19: 0 | EC19: 100 | ED19: 7.5117371 | EE19: 0 | EF19: 0 | EG19: 19.512195 | EH19: 12.5 | EI19: 51.666667 | EJ19: 1.8691589 | EK19: 0 | EL19: 0 | EM19: 0 | EN19: 0 | EO19: 59.016393 | EP19: 1.8018018 | EQ19: 0 | ER19: 0 | ES19: 0 | ET19: 0 | EU19: 40.677966 | EV19: 9 | EW19: 0 | EX19: 0 | EY19: 0 | EZ19: 0 | FA19: 63 | FB19: 11.111111 | FC19: 0 | FD19: 9.6774194 | FE19: 0 | FF19: 60 | FG19: 63.492063 | FH19: 6.7510549 | FI19: 0 | FJ19: 0 | FK19: 0 | FL19: 12.5 | FM19: 25 | FN19: 8.4745763 | FO19: 0 | FP19: 10.25641 | FQ19: 25 | FR19: 23.333333 | FS19: 6.3492063 | FT19: 3.960396 | FU19: 0 | FV19: 0 | FW19: 10 | FX19: 13.793103 | FY19: 41.176471 | FZ19: 14 | GA19: 0 | GB19: 13 | GC19: 33 | GD19: 0 | GE19: 25 | GF19: 24 | GG19: 10 | GH19: 0 | GI19: 10 | GJ19: 0 | GK19: 43 | GL19: 26.315789 | GM19: 18.181818 | GN19: 0 | GO19: 37.5 | GP19: 0 | GQ19: 33.333333 | GR19: 15.789474 | GS19: 18.181818 | GT19: 0 | GU19: 11.111111 | GV19: 25 | GW19: 50 | GX19: 25.806452 | GY19: 30 | GZ19: 0 | HA19: 14.285714 | HB19: 0 | HC19: 60
A20: توافر المعلومات عن السوق المحلي والخارجي | FZ20: 22 | GA20: 0 | GB20: 0 | GC20: 33 | GD20: 0 | GE20: 0 | GF20: 24 | GG20: 0 | GH20: 0 | GI20: 0 | GJ20: 0 | GK20: 0 | GL20: 18.421053 | GM20: 0 | GN20: 0 | GO20: 0 | GP20: 14.285714 | GQ20: 0 | GR20: 7.8947368 | GS20: 0 | GT20: 0 | GU20: 11.111111 | GV20: 0 | GW20: 0 | GX20: 32.258065 | GY20: 0 | GZ20: 14.285714 | HA20: 28.571429 | HB20: 20 | HC20: 20
A21: تفضيل المنتج المحلي في التعاقدات الحكومية | FZ21: 6 | GA21: 0 | GB21: 0 | GC21: 0 | GD21: 0 | GE21: 0 | GF21: 0 | GG21: 0 | GH21: 0 | GI21: 0 | GJ21: 0 | GK21: 0 | GL21: 0 | GM21: 0 | GN21: 0 | GO21: 0 | GP21: 0 | GQ21: 8.3333333 | GR21: 0 | GS21: 0 | GT21: 0 | GU21: 0 | GV21: 0 | GW21: 0 | GX21: 0 | GY21: 0 | GZ21: 0 | HA21: 0 | HB21: 0 | HC21: 0
A22: منع المنافسة غير العادلة من الدولة | FZ22: 6 | GA22: 55 | GB22: 13 | GC22: 0 | GD22: 20 | GE22: 0 | GF22: 10 | GG22: 70 | GH22: 14 | GI22: 0 | GJ22: 17 | GK22: 0 | GL22: 7.8947368 | GM22: 81.818182 | GN22: 0 | GO22: 0 | GP22: 0 | GQ22: 0 | GR22: 2.6315789 | GS22: 45.454545 | GT22: 14.285714 | GU22: 0 | GV22: 50 | GW22: 7.1428571 | GX22: 3.2258065 | GY22: 60 | GZ22: 0 | HA22: 0 | HB22: 40 | HC22: 0
A23: وضوح توجهات السياسية الاقتصادية في المستقبل | FZ23: 56 | GA23: 18 | GB23: 0 | GC23: 83 | GD23: 0 | GE23: 100 | GF23: 52 | GG23: 40 | GH23: 0 | GI23: 80 | GJ23: 0 | GK23: 100 | GL23: 31.578947 | GM23: 9.0909091 | GN23: 11.111111 | GO23: 50 | GP23: 0 | GQ23: 100 | GR23: 28.947368 | GS23: 27.272727 | GT23: 0 | GU23: 33.333333 | GV23: 50 | GW23: 100 | GX23: 35.483871 | GY23: 20 | GZ23: 14.285714 | HA23: 85.714286 | HB23: 0 | HC23: 100

Sheet Sect. Gov Priorities Fig 2-6 EN
B1: Jan - Mar 2017 | H1: Apr - Jun 2017 | N1: Jul - Sep 2017 | T1: Oct - Dec 2017 | Z1: Jan - Mar 2018 | AF1: Apr - Jun 2018 | AL1: Jul - Sep 2018 | AR1: Oct - Dec 2018 | AX1: Jan - Mar 2019 | BD1: Apr - Jun 2019 | BJ1: Jul - Sep 2019 | BP1: Oct - Dec 2019 | BV1: Jan - Mar 2020 | CB1: Apr - Jun 2020 | CH1: Jul - Sep 2020 | CN1: Oct - Dec 2020 | CT1: Jan - Mar 2021 | CZ1: Apr - Jun 2021 | DF1: Jul - Sep 2021 | DL1: Oct - Dec 2021 | DR1: Apr - Jun 2022 | DX1: Apr - Jun 2022 | ED1: Oct - Dec 2022 | EJ1: Jan - Mar 2023 | EP1: Apr - Jun 2023 | EV1: Jul - Sep 2023
B5: Manufacturing | C5: Construction | D5: Tourism | E5: Transport | F5: Communications | G5: Financial Services | H5: Manufacturing | I5: Construction | J5: Tourism | K5: Transport | L5: Communications | M5: Financial Services | N5: Manufacturing | O5: Construction | P5: Tourism | Q5: Transport | R5: Communications | S5: Financial Services | T5: Manufacturing | U5: Construction | V5: Tourism | W5: Transport | X5: Communications | Y5: Financial Services | Z5: Manufacturing | AA5: Construction | AB5: Tourism | AC5: Transport | AD5: Communications | AE5: Financial Services | AF5: Manufacturing | AG5: Construction | AH5: Tourism | AI5: Transport | AJ5: Communications | AK5: Financial Services | AL5: Manufacturing | AM5: Construction | AN5: Tourism | AO5: Transport | AP5: Communications | AQ5: Financial Services | AR5: Manufacturing | AS5: Construction | AT5: Tourism | AU5: Transport | AV5: Communications | AW5: Financial Services | AX5: Manufacturing | AY5: Construction | AZ5: Tourism | BA5: Transport | BB5: Communications | BC5: Financial Services | BD5: Manufacturing | BE5: Construction | BF5: Tourism | BG5: Transport | BH5: Communications | BI5: Financial Services | BJ5: Manufacturing | BK5: Construction | BL5: Tourism | BM5: Transport | BN5: Communications | BO5: Financial Services | BP5: Manufacturing | BQ5: Construction | BR5: Tourism | BS5: Transport | BT5: Communications | BU5: Financial Services | BV5: Manufacturing | BW5: Construction | BX5: Tourism | BY5: Transport | BZ5: Communications | CA5: Financial Services | CB5: Manufacturing | CC5: Construction | CD5: Tourism | CE5: Transport | CF5: Communications | CG5: Financial Services | CH5: Manufacturing | CI5: Construction | CJ5: Tourism | CK5: Transport | CL5: Communications | CM5: Financial Services | CN5: Manufacturing | CO5: Construction | CP5: Tourism | CQ5: Transport | CR5: Communications | CS5: Financial Services | CT5: Manufacturing | CU5: Construction | CV5: Tourism | CW5: Transport | CX5: Communications | CY5: Financial Services | CZ5: Manufacturing | DA5: Construction | DB5: Tourism | DC5: Transport | DD5: Communications | DE5: Financial Services | DF5: Manufacturing | DG5: Construction | DH5: Tourism | DI5: Transport | DJ5: Communications | DK5: Financial Services | DL5: Manufacturing | DM5: Construction | DN5: Tourism | DO5: Transport | DP5: Communications | DQ5: Financial Services | DR5: Manufacturing | DS5: Construction | DT5: Tourism | DU5: Transport | DV5: Communications | DW5: Financial Services | DX5: Manufacturing | DY5: Construction | DZ5: Tourism | EA5: Transport | EB5: Communications | EC5: Financial Services | ED5: Manufacturing | EE5: Construction | EF5: Tourism | EG5: Transport | EH5: Communications | EI5: Financial Services | EJ5: Manufacturing | EK5: Construction | EL5: Tourism | EM5: Transport | EN5: Communications | EO5: Financial Services | EP5: Manufacturing | EQ5: Construction | ER5: Tourism | ES5: Transport | ET5: Communications | EU5: Financial Services | EV5: Manufacturing | EW5: Construction | EX5: Tourism | EY5: Transport | EZ5: Communications | FA5: Financial Services
A6: Digitalization of government services | B6: ='Sect. Gov Priorities Fig 2-6 AR'!B6 -> 0 | C6: ='Sect. Gov Priorities Fig 2-6 AR'!C6 -> 0 | D6: ='Sect. Gov Priorities Fig 2-6 AR'!D6 -> 0 | E6: ='Sect. Gov Priorities Fig 2-6 AR'!E6 -> 0 | F6: ='Sect. Gov Priorities Fig 2-6 AR'!F6 -> 0 | G6: ='Sect. Gov Priorities Fig 2-6 AR'!G6 -> 0 | H6: ='Sect. Gov Priorities Fig 2-6 AR'!H6 -> 0 | I6: ='Sect. Gov Priorities Fig 2-6 AR'!I6 -> 0 | ... DW6: ='Sect. Gov Priorities Fig 2-6 AR'!DW6 -> 80.882353 | DX6: 100 | DY6: 92.592593 | DZ6: 100 | EA6: 78.04878 | EB6: 100 | EC6: 71.666667 | ED6: 100 | EE6: 100 | EF6: 100 | EG6: 78.26087 | EH6: 100 | EI6: 91.803279 | EJ6: 79.72973 | EK6: 79.62963 | EL6: 95 | EM6: 50 | EN6: 100 | EO6: 77.966102 | EP6: 82 | EQ6: 88 | ER6: 100 | ES6: 71 | ET6: 100 | EU6: 84 | EV6: 70.940171 | EW6: 83.928571 | EX6: 87.096774 | EY6: 81.25 | EZ6: 96 | FA6: 87.301587
A7: Facilitating government procedures | B7: ='Sect. Gov Priorities Fig 2-6 AR'!B7 -> 0 | C7: ='Sect. Gov Priorities Fig 2-6 AR'!C7 -> 0 | D7: ='Sect. Gov Priorities Fig 2-6 AR'!D7 -> 0 | E7: ='Sect. Gov Priorities Fig 2-6 AR'!E7 -> 0 | F7: ='Sect. Gov Priorities Fig 2-6 AR'!F7 -> 0 | G7: ='Sect. Gov Priorities Fig 2-6 AR'!G7 -> 0 | H7: ='Sect. Gov Priorities Fig 2-6 AR'!H7 -> 0 | I7: ='Sect. Gov Priorities Fig 2-6 AR'!I7 -> 0 | ... DW7: ='Sect. Gov Priorities Fig 2-6 AR'!DW7 -> 11.764706 | DX7: 100 | DY7: 100 | DZ7: 60 | EA7: 26.829268 | EB7: 68.75 | EC7: 10 | ED7: 91.121495 | EE7: 100 | EF7: 88.888889 | EG7: 15.217391 | EH7: 93.75 | EI7: 6.557377 | EJ7: 82.882883 | EK7: 75.925926 | EL7: 72.5 | EM7: 83.333333 | EN7: 87.5 | EO7: 5.0847458 | EP7: 79 | EQ7: 89 | ER7: 60 | ES7: 73 | ET7: 75 | EU7: 0 | EV7: 91.025641 | EW7: 83.928571 | EX7: 90.322581 | EY7: 79.166667 | EZ7: 72 | FA7: 0
A8: Investment policy | B8: ='Sect. Gov Priorities Fig 2-6 AR'!B8 -> 0 | C8: ='Sect. Gov Priorities Fig 2-6 AR'!C8 -> 0 | D8: ='Sect. Gov Priorities Fig 2-6 AR'!D8 -> 0 | E8: ='Sect. Gov Priorities Fig 2-6 AR'!E8 -> 0 | F8: ='Sect. Gov Priorities Fig 2-6 AR'!F8 -> 0 | G8: ='Sect. Gov Priorities Fig 2-6 AR'!G8 -> 0 | H8: ='Sect. Gov Priorities Fig 2-6 AR'!H8 -> 0 | I8: ='Sect. Gov Priorities Fig 2-6 AR'!I8 -> 0 | ... DW8: ='Sect. Gov Priorities Fig 2-6 AR'!DW8 -> 69.117647 | DX8: 79.812207 | DY8: 88.888889 | DZ8: 10 | EA8: 68.292683 | EB8: 9.375 | EC8: 100 | ED8: 73.364486 | EE8: 96.296296 | EF8: 0 | EG8: 52.173913 | EH8: 18.75 | EI8: 83.606557 | EJ8: 86.936937 | EK8: 96.296296 | EL8: 40 | EM8: 64.583333 | EN8: 56.25 | EO8: 96.610169 | EP8: 87 | EQ8: 79 | ER8: 5 | ES8: 76 | ET8: 34 | EU8: 95 | EV8: 89.316239 | EW8: 94.642857 | EX8: 19.354839 | EY8: 83.333333 | EZ8: 28 | FA8: 100
A9: Tax system | B9: ='Sect. Gov Priorities Fig 2-6 AR'!B9 -> 0 | C9: ='Sect. Gov Priorities Fig 2-6 AR'!C9 -> 0 | D9: ='Sect. Gov Priorities Fig 2-6 AR'!D9 -> 0 | E9: ='Sect. Gov Priorities Fig 2-6 AR'!E9 -> 0 | F9: ='Sect. Gov Priorities Fig 2-6 AR'!F9 -> 0 | G9: ='Sect. Gov Priorities Fig 2-6 AR'!G9 -> 0 | H9: ='Sect. Gov Priorities Fig 2-6 AR'!H9 -> 0 | I9: ='Sect. Gov Priorities Fig 2-6 AR'!I9 -> 0 | ... DW9: ='Sect. Gov Priorities Fig 2-6 AR'!DW9 -> 79.411765 | DX9: 48.356808 | DY9: 61.111111 | DZ9: 67.5 | EA9: 0 | EB9: 50 | EC9: 85 | ED9: 54.205607 | EE9: 83.333333 | EF9: 44.444444 | EG9: 15.217391 | EH9: 34.375 | EI9: 88.52459 | EJ9: 61.711712 | EK9: 64.814815 | EL9: 60 | EM9: 54.166667 | EN9: 43.75 | EO9: 94.915254 | EP9: 63 | EQ9: 68 | ER9: 95 | ES9: 64 | ET9: 63 | EU9: 94 | EV9: 60.25641 | EW9: 73.214286 | EX9: 70.967742 | EY9: 70.833333 | EZ9: 68 | FA9: 98.412698
A10: Reducing government services fees | B10: ='Sect. Gov Priorities Fig 2-6 AR'!B10 -> 0 | C10: ='Sect. Gov Priorities Fig 2-6 AR'!C10 -> 0 | D10: ='Sect. Gov Priorities Fig 2-6 AR'!D10 -> 0 | E10: ='Sect. Gov Priorities Fig 2-6 AR'!E10 -> 0 | F10: ='Sect. Gov Priorities Fig 2-6 AR'!F10 -> 0 | G10: ='Sect. Gov Priorities Fig 2-6 AR'!G10 -> 0 | H10: ='Sect. Gov Priorities Fig 2-6 AR'!H10 -> 0 | I10: ='Sect. Gov Priorities Fig 2-6 AR'!I10 -> 0 | ... DW10: ='Sect. Gov Priorities Fig 2-6 AR'!DW10 -> 51.470588 | DX10: 83.997232 | DY10: 88.888889 | DZ10: 20 | EA10: 48.780488 | EB10: 34.375 | EC10: 60 | ED10: 86.448598 | EE10: 96.296296 | EF10: 52.777778 | EG10: 19.565217 | EH10: 46.875 | EI10: 37.704918 | EJ10: 67.567568 | EK10: 81.481481 | EL10: 72.5 | EM10: 64.583333 | EN10: 63 | EO10: 5.0847458 | EP10: 73 | EQ10: 70 | ER10: 60 | ES10: 69 | ET10: 44 | EU10: 30 | EV10: 66.666667 | EW10: 83.928571 | EX10: 48.387097 | EY10: 81.25 | EZ10: 32 | FA10: 7.9365079
A11: Inflation | B11: ='Sect. Gov Priorities Fig 2-6 AR'!B11 -> 0 | C11: ='Sect. Gov Priorities Fig 2-6 AR'!C11 -> 0 | D11: ='Sect. Gov Priorities Fig 2-6 AR'!D11 -> 0 | E11: ='Sect. Gov Priorities Fig 2-6 AR'!E11 -> 0 | F11: ='Sect. Gov Priorities Fig 2-6 AR'!F11 -> 0 | G11: ='Sect. Gov Priorities Fig 2-6 AR'!G11 -> 0 | H11: ='Sect. Gov Priorities Fig 2-6 AR'!H11 -> 0 | I11: ='Sect. Gov Priorities Fig 2-6 AR'!I11 -> 0 | ... DW11: ='Sect. Gov Priorities Fig 2-6 AR'!DW11 -> 38.235294 | DX11: 95.774648 | DY11: 92.592593 | DZ11: 80 | EA11: 100 | EB11: 75 | EC11: 86.666667 | ED11: 97.196262 | EE11: 100 | EF11: 58.333333 | EG11: 100 | EH11: 68.75 | EI11: 100 | EJ11: 100 | EK11: 100 | EL11: 100 | EM11: 95.833333 | EN11: 93.75 | EO11: 100 | EP11: 100 | EQ11: 100 | ER11: 100 | ES11: 87 | ET11: 100 | EU11: 100 | EV11: 100 | EW11: 100 | EX11: 100 | EY11: 100 | EZ11: 100 | FA11: 100
A12: Supporting hit sectors | B12: ='Sect. Gov Priorities Fig 2-6 AR'!B12 -> 0 | C12: ='Sect. Gov Priorities Fig 2-6 AR'!C12 -> 0 | D12: ='Sect. Gov Priorities Fig 2-6 AR'!D12 -> 0 | E12: ='Sect. Gov Priorities Fig 2-6 AR'!E12 -> 0 | F12: ='Sect. Gov Priorities Fig 2-6 AR'!F12 -> 0 | G12: ='Sect. Gov Priorities Fig 2-6 AR'!G12 -> 0 | H12: ='Sect. Gov Priorities Fig 2-6 AR'!H12 -> 0 | I12: ='Sect. Gov Priorities Fig 2-6 AR'!I12 -> 0 | ... DW12: ='Sect. Gov Priorities Fig 2-6 AR'!DW12 -> 0 | DX12: 24.413146 | DY12: 51.851852 | DZ12: 77.5 | EA12: 0 | EB12: 6.25 | EC12: 0 | ED12: 22.897196 | EE12: 42.592593 | EF12: 0 | EG12: 0 | EH12: 0 | EI12: 0 | EJ12: 48.648649 | EK12: 68.518519 | EL12: 15 | EM12: 100 | EN12: 0 | EO12: 5.0847458 | EP12: 47 | EQ12: 61 | ER12: 3 | ES12: 85 | ET12: 0 | EU12: 0 | EV12: 55.128205 | EW12: 71.428571 | EX12: 22.580645 | EY12: 95.833333 | EZ12: 12 | FA12: 0
A13: Reducing energy prices | B13: ='Sect. Gov Priorities Fig 2-6 AR'!B13 -> 0 | C13: ='Sect. Gov Priorities Fig 2-6 AR'!C13 -> 0 | D13: ='Sect. Gov Priorities Fig 2-6 AR'!D13 -> 0 | E13: ='Sect. Gov Priorities Fig 2-6 AR'!E13 -> 0 | F13: ='Sect. Gov Priorities Fig 2-6 AR'!F13 -> 0 | G13: ='Sect. Gov Priorities Fig 2-6 AR'!G13 -> 0 | H13: ='Sect. Gov Priorities Fig 2-6 AR'!H13 -> 0 | I13: ='Sect. Gov Priorities Fig 2-6 AR'!I13 -> 0 | ... DW13: ='Sect. Gov Priorities Fig 2-6 AR'!DW13 -> 7.3529412 | DX13: 30.985915 | DY13: 40.740741 | DZ13: 10 | EA13: 29.268293 | EB13: 9.375 | EC13: 3.3333333 | ED13: 29.439252 | EE13: 50 | EF13: 0 | EG13: 28.26087 | EH13: 0 | EI13: 4.9180328 | EJ13: 53.603604 | EK13: 62.962963 | EL13: 15 | EM13: 91.666667 | EN13: 0 | EO13: 0 | EP13: 55 | EQ13: 59 | ER13: 0 | ES13: 80 | ET13: 0 | EU13: 0 | EV13: 57.692308 | EW13: 69.642857 | EX13: 19.354839 | EY13: 89.583333 | EZ13: 8 | FA13: 0
A14: Customs system | B14: ='Sect. Gov Priorities Fig 2-6 AR'!B14 -> 0 | C14: ='Sect. Gov Priorities Fig 2-6 AR'!C14 -> 0 | D14: ='Sect. Gov Priorities Fig 2-6 AR'!D14 -> 0 | E14: ='Sect. Gov Priorities Fig 2-6 AR'!E14 -> 0 | F14: ='Sect. Gov Priorities Fig 2-6 AR'!F14 -> 0 | G14: ='Sect. Gov Priorities Fig 2-6 AR'!G14 -> 0 | H14: ='Sect. Gov Priorities Fig 2-6 AR'!H14 -> 0 | I14: ='Sect. Gov Priorities Fig 2-6 AR'!I14 -> 0 | ... DW14: ='Sect. Gov Priorities Fig 2-6 AR'!DW14 -> - | DX14: 59.404043 | DY14: _ | DZ14: _ | EA14: 0 | EB14: 64 | EC14: _ | ED14: 33.64486 | EE14: 14.814815 | EF14: 0 | EG14: 8.6956522 | EH14: 43.75 | EI14: 0 | EJ14: 52.702703 | EK14: 35.185185 | EL14: 0 | EM14: 62.5 | EN14: 37.5 | EO14: 0 | EP14: 41 | EQ14: 5 | ER14: 3 | ES14: 100 | ET14: 47 | EU14: 0 | EV14: 46.581197 | EW14: 7.1428571 | EX14: 9.6774194 | EY14: 54.166667 | EZ14: 24 | FA14: 0
A15: Providing skilled labor | B15: ='Sect. Gov Priorities Fig 2-6 AR'!B15 -> 0 | C15: ='Sect. Gov Priorities Fig 2-6 AR'!C15 -> 0 | D15: ='Sect. Gov Priorities Fig 2-6 AR'!D15 -> 0 | E15: ='Sect. Gov Priorities Fig 2-6 AR'!E15 -> 0 | F15: ='Sect. Gov Priorities Fig 2-6 AR'!F15 -> 0 | G15: ='Sect. Gov Priorities Fig 2-6 AR'!G15 -> 0 | H15: ='Sect. Gov Priorities Fig 2-6 AR'!H15 -> 0 | I15: ='Sect. Gov Priorities Fig 2-6 AR'!I15 -> 0 | ... DW15: ='Sect. Gov Priorities Fig 2-6 AR'!DW15 -> 0 | DX15: 37.558685 | DY15: 38.888889 | DZ15: 20 | EA15: 0 | EB15: 40.625 | EC15: 6.6666667 | ED15: 40.654206 | EE15: 25.925926 | EF15: 22.222222 | EG15: 0 | EH15: 43.75 | EI15: 6.557377 | EJ15: 36.936937 | EK15: 42.592593 | EL15: 12.5 | EM15: 47.916667 | EN15: 15.625 | EO15: 3.3898305 | EP15: 51 | EQ15: 54 | ER15: 0 | ES15: 64 | ET15: 25 | EU15: 0 | EV15: 57.264957 | EW15: 55.357143 | EX15: 16.129032 | EY15: 70.833333 | EZ15: 52 | FA15: 0
A16: Infrastructure | B16: ='Sect. Gov Priorities Fig 2-6 AR'!B16 -> 0 | C16: ='Sect. Gov Priorities Fig 2-6 AR'!C16 -> 0 | D16: ='Sect. Gov Priorities Fig 2-6 AR'!D16 -> 0 | E16: ='Sect. Gov Priorities Fig 2-6 AR'!E16 -> 0 | F16: ='Sect. Gov Priorities Fig 2-6 AR'!F16 -> 0 | G16: ='Sect. Gov Priorities Fig 2-6 AR'!G16 -> 0 | H16: ='Sect. Gov Priorities Fig 2-6 AR'!H16 -> 0 | I16: ='Sect. Gov Priorities Fig 2-6 AR'!I16 -> 0 | ... DW16: ='Sect. Gov Priorities Fig 2-6 AR'!DW16 -> 0 | DX16: 24.413146 | DY16: 38.888889 | DZ16: 0 | EA16: 24.390244 | EB16: 21.875 | EC16: 11.377778 | ED16: 24.766355 | EE16: 48.148148 | EF16: 0 | EG16: 0 | EH16: 21.875 | EI16: 1.6393443 | EJ16: 38.288288 | EK16: 37.037037 | EL16: 22.5 | EM16: 35.416667 | EN16: 0 | EO16: 8.4745763 | EP16: 37 | EQ16: 41 | ER16: 0 | ES16: 31 | ET16: 0 | EU16: 0 | EV16: 23.076923 | EW16: 30.357143 | EX16: 0 | EY16: 39.583333 | EZ16: 0 | FA16: 0
A17: Interest rate | B17: ='Sect. Gov Priorities Fig 2-6 AR'!B17 -> 0 | C17: ='Sect. Gov Priorities Fig 2-6 AR'!C17 -> 0 | D17: ='Sect. Gov Priorities Fig 2-6 AR'!D17 -> 0 | E17: ='Sect. Gov Priorities Fig 2-6 AR'!E17 -> 0 | F17: ='Sect. Gov Priorities Fig 2-6 AR'!F17 -> 0 | G17: ='Sect. Gov Priorities Fig 2-6 AR'!G17 -> 0 | H17: ='Sect. Gov Priorities Fig 2-6 AR'!H17 -> 0 | I17: ='Sect. Gov Priorities Fig 2-6 AR'!I17 -> 0 | ... DW17: ='Sect. Gov Priorities Fig 2-6 AR'!DW17 -> 0 | DX17: 37.386051 | DY17: 46.296296 | DZ17: 42.5 | EA17: 39.02439 | EB17: 21.875 | EC17: 71.666667 | ED17: 47.196262 | EE17: 42.592593 | EF17: 13.888889 | EG17: 67.391304 | EH17: 28.125 | EI17: 60.655738 | EJ17: 50.45045 | EK17: 42.592593 | EL17: 50 | EM17: 52.083333 | EN17: 65.625 | EO17: 11.864407 | EP17: 71 | EQ17: 46 | ER17: 33 | ES17: 29 | ET17: 69 | EU17: 94 | EV17: 45.299145 | EW17: 53.571429 | EX17: 9.6774194 | EY17: 47.916667 | EZ17: 12 | FA17: 53.968254
A18: Credit and financial services | B18: ='Sect. Gov Priorities Fig 2-6 AR'!B18 -> 0 | C18: ='Sect. Gov Priorities Fig 2-6 AR'!C18 -> 0 | D18: ='Sect. Gov Priorities Fig 2-6 AR'!D18 -> 0 | E18: ='Sect. Gov Priorities Fig 2-6 AR'!E18 -> 0 | F18: ='Sect. Gov Priorities Fig 2-6 AR'!F18 -> 0 | G18: ='Sect. Gov Priorities Fig 2-6 AR'!G18 -> 0 | H18: ='Sect. Gov Priorities Fig 2-6 AR'!H18 -> 0 | I18: ='Sect. Gov Priorities Fig 2-6 AR'!I18 -> 0 | ... DW18: ='Sect. Gov Priorities Fig 2-6 AR'!DW18 -> 0 | DX18: 17.370892 | DY18: 27.777778 | DZ18: 0 | EA18: 4.8780488 | EB18: 12.5 | EC18: 0 | ED18: 15.88785 | EE18: 24.074074 | EF18: 0 | EG18: 8.6956522 | EH18: 18.75 | EI18: 0 | EJ18: 22.072072 | EK18: 20.37037 | EL18: 12.5 | EM18: 20.833333 | EN18: 18.75 | EO18: 3.3898305 | EP18: 25 | EQ18: 20 | ER18: 0 | ES18: 20 | ET18: 18.75 | EU18: 0 | EV18: 21.367521 | EW18: 26.785714 | EX18: 0 | EY18: 27.083333 | EZ18: 36 | FA18: 3.1746032
A19: Others | B19: ='Sect. Gov Priorities Fig 2-6 AR'!B19 -> 0 | C19: ='Sect. Gov Priorities Fig 2-6 AR'!C19 -> 0 | D19: ='Sect. Gov Priorities Fig 2-6 AR'!D19 -> 0 | E19: ='Sect. Gov Priorities Fig 2-6 AR'!E19 -> 0 | F19: ='Sect. Gov Priorities Fig 2-6 AR'!F19 -> 0 | G19: ='Sect. Gov Priorities Fig 2-6 AR'!G19 -> 0 | H19: ='Sect. Gov Priorities Fig 2-6 AR'!H19 -> 0 | I19: ='Sect. Gov Priorities Fig 2-6 AR'!I19 -> 0 | ... DW19: ='Sect. Gov Priorities Fig 2-6 AR'!DW19 -> 100 | DX19: 7.5117371 | DY19: 0 | DZ19: 0 | EA19: 19.512195 | EB19: 12.5 | EC19: 51.666667 | ED19: 1.8691589 | EE19: 0 | EF19: 0 | EG19: 0 | EH19: 0 | EI19: 59.016393 | EJ19: 1.8018018 | EK19: 0 | EL19: 0 | EM19: 0 | EN19: 0 | EO19: 40.677966 | EP19: 9 | EQ19: 0 | ER19: 0 | ES19: 0 | ET19: 0 | EU19: 63 | EV19: 11.111111 | EW19: 0 | EX19: 9.6774194 | EY19: 0 | EZ19: 60 | FA19: 63.492063

Sheet PExpections Fig 2-7 n
P3: انخفض | Q3: ظل ثابت | R3: ارتفع | S3: المتغير
S4: سعر الفائدة
S5: سعر الدولار
S6: معدل التضخم
S7: الرسوم الجمركية
S8: مدة انقطاع الكهرباء
S9: معدل الضرائب
S10: رسوم الطاقة والمياه والصرف
P17: Decrease | Q17: Stability | R17: Increase | S17: المتغير
P18: 64.166667 | Q18: 35.833333 | R18: 0 | S18: Interest rate
P19: 6.6666667 | Q19: 60 | R19: 33.333333 | S19: Exchange rate
P20: 5 | Q20: 55 | R20: 40 | S20: Inflation rate
P21: 0 | Q21: 65 | R21: 35 | S21: Custom fees
P22: 80.672269 | Q22: 14.285714 | R22: 5.0420168 | S22: Power outage
P23: 0.83333333 | Q23: 94.166667 | R23: 5 | S23: Taxation rate
P24: 0 | Q24: 46.666667 | R24: 53.333333 | S24: Energy, water and waste costs
